Workbook

Sheet Temporada Alta PPT
T2: 2206451.6 | U2: 429032.26 | V2: 2206451.6 | W2: 3064516.1 | X2: 0.4 | Z2: 310000 | AB2: 3519400
C3: =SUM(C5:C114) -> 43 | F3: =SUM(F5:F114) -> 7
A4: Modelo PDV 1 | B4: Tipo | C4: Q | D4: Modelo PDV 2 | E4: Tipo | F4: Q | G4: Sup. Días Se, | H4: Tipo Supervisión | I4: Zona/Ciudad | J4: Cadena | K4: Sucursal | L4: Venta Promedio | M4: Incremento de Venta | N4: Venta Total | O4: Comisión Retail | P4: Margen Tienda | Q4: Supervisión | R4: Vendedor / Reposición 01 | S4: Vendedor / Reposición 02 | T4: Bodegaje | U4: Packing | V4: Picking | W4: Transporte | X4: Costo Mercadería | Y4: Merma | Z4: Muebles | AA4: Margen Operacional | AB4: Gastos de Administración | AC4: Resultado Actual | AD4: Resultado Modelo | AE4: Diferencial
A5: Vendedor 1/2 Full | B5: Outsourcing | C5: 1 | D5: Vendedor 1/2 3 días | E5: Outsourcing | F5: 1 | G5: 2 | H5: Supervisor Regiones | I5: Viña del Mar | J5: Ripley | K5: Marina Arauco | L5: =IFERROR(VLOOKUP(CONCATENATE(J5,K5),Ventas!D:H,4,0),0) -> 3692307.7 | M5: =IF(SUM(C5,F5)>0,L5*0.1,0) -> 369230.77 | N5: =SUM(L5:M5) -> 4061538.5 | O5: =N5*IFERROR(VLOOKUP(J5,Tabla11[],3,0),0) -> 1421538.5 | P5: =N5-O5 -> 2640000 | Q5: =IFERROR(G5/SUMIF(I:I,I5,G:G),0)*VLOOKUP(H5,Modelos[],14,0)+IFERROR(G5/SUMIF(I:I,I5,G:G),0)*VLOOKUP(I5,Tabla13[],2,0) -> 82422.042 | R5: =IFERROR(VLOOKUP(A5,Modelos[],IF(B5="EST",15,14),0),0)*C5 -> 310333.79 | S5: =IFERROR(VLOOKUP(D5,Modelos[],IF(E5="EST",15,14),0),0)*F5 -> 204526.8 | T5: =IF($L5<0,0,IFERROR((T$2*IFERROR(VLOOKUP(J5,Tabla11[],2,0),0))*($L5/SUM($L$5:$L$46)),0)) -> 21188.574 | U5: =IF($L5<0,0,IFERROR((U$2*IFERROR(VLOOKUP(J5,Tabla11[],2,0),0))*($L5/SUM($L$5:$L$46)),0)) -> 4120.0005 | V5: =IF($L5<0,0,IFERROR((V$2*IFERROR(VLOOKUP(J5,Tabla11[],2,0),0))*($L5/SUM($L$5:$L$46)),0)) -> 21188.574 | W5: =IF($L5<0,0,IFERROR((W$2*IFERROR(VLOOKUP(J5,Tabla11[],2,0),0))*($L5/SUM($L$5:$L$46)),0)) -> 29428.575 | X5: =P5*$X$2 -> 1056000 | Y5: =+X5*IFERROR(VLOOKUP(J5,Tabla11[],4,0),0) -> 158400 | Z5: =IF(L5>0,$Z$2/12,0) -> 25833.333 | AA5: =P5-SUM(Q5:Z5) -> 726558.31 | AB5: =IF($L5<0,0,IFERROR((AB$2*IFERROR(VLOOKUP(J5,Tabla11[],2,0),0))*($L5/SUM($L$5:$L$46)),0)) -> 33796.829 | AC5: =L5-L5*IFERROR(VLOOKUP(J5,Tabla11[],3,0),0)-Q5-T5-U5-V5-W5-L5*$X$2-(L5*$X$2)*IFERROR(VLOOKUP(J5,Tabla11[],4,0),0)-AB5-Z5 -> 483560.53 | AD5: =AA5-AB5 -> 692761.48 | AE5: =ROUND(AD5-AC5,9) -> 209200.95
A6: Vendedor 1/2 3 días | B6: Outsourcing | C6: 1 | E6: Outsourcing | G6: 0 | H6: Supervisor Regiones | I6: Puerto Montt | J6: Ripley | K6: M.Costanera P.Montt | L6: =IFERROR(VLOOKUP(CONCATENATE(J6,K6),Ventas!D:H,4,0),0) -> 2895783.1 | M6: =IF(SUM(C6,F6)>0,L6*0.1,0) -> 289578.31 | N6: =SUM(L6:M6) -> 3185361.4 | O6: =N6*IFERROR(VLOOKUP(J6,Tabla11[],3,0),0) -> 1114876.5 | P6: =N6-O6 -> 2070484.9 | Q6: =IFERROR(G6/SUMIF(I:I,I6,G:G),0)*VLOOKUP(H6,Modelos[],14,0)+IFERROR(G6/SUMIF(I:I,I6,G:G),0)*VLOOKUP(I6,Tabla13[],2,0) -> 0 | R6: =IFERROR(VLOOKUP(A6,Modelos[],IF(B6="EST",15,14),0),0)*C6 -> 204526.8 | S6: =IFERROR(VLOOKUP(D6,Modelos[],IF(E6="EST",15,14),0),0)*F6 -> 0 | T6: =IF($L6<0,0,IFERROR((T$2*IFERROR(VLOOKUP(J6,Tabla11[],2,0),0))*($L6/SUM($L$5:$L$46)),0)) -> 16617.66 | U6: =IF($L6<0,0,IFERROR((U$2*IFERROR(VLOOKUP(J6,Tabla11[],2,0),0))*($L6/SUM($L$5:$L$46)),0)) -> 3231.2117 | V6: =IF($L6<0,0,IFERROR((V$2*IFERROR(VLOOKUP(J6,Tabla11[],2,0),0))*($L6/SUM($L$5:$L$46)),0)) -> 16617.66 | W6: =IF($L6<0,0,IFERROR((W$2*IFERROR(VLOOKUP(J6,Tabla11[],2,0),0))*($L6/SUM($L$5:$L$46)),0)) -> 23080.083 | X6: =P6*$X$2 -> 828193.96 | Y6: =+X6*IFERROR(VLOOKUP(J6,Tabla11[],4,0),0) -> 124229.09 | Z6: =IF(L6>0,$Z$2/12,0) -> 25833.333 | AA6: =P6-SUM(Q6:Z6) -> 828155.1 | AB6: =IF($L6<0,0,IFERROR((AB$2*IFERROR(VLOOKUP(J6,Tabla11[],2,0),0))*($L6/SUM($L$5:$L$46)),0)) -> 26505.994 | AC6: =L6-L6*IFERROR(VLOOKUP(J6,Tabla11[],3,0),0)-Q6-T6-U6-V6-W6-L6*$X$2-(L6*$X$2)*IFERROR(VLOOKUP(J6,Tabla11[],4,0),0)-AB6-Z6 -> 438312.84 | AD6: =AA6-AB6 -> 801649.1 | AE6: =ROUND(AD6-AC6,9) -> 363336.26
A7: Vendedor 1/2 Full | B7: Outsourcing | C7: 1 | D7: Vendedor 1/2 3 días | E7: Outsourcing | F7: 1 | G7: 1 | H7: Supervisor Regiones | I7: VI-VII | J7: Ripley | K7: Talca | L7: =IFERROR(VLOOKUP(CONCATENATE(J7,K7),Ventas!D:H,4,0),0) -> 2875784.6 | M7: =IF(SUM(C7,F7)>0,L7*0.1,0) -> 287578.46 | N7: =SUM(L7:M7) -> 3163363.1 | O7: =N7*IFERROR(VLOOKUP(J7,Tabla11[],3,0),0) -> 1107177.1 | P7: =N7-O7 -> 2056186 | Q7: =IFERROR(G7/SUMIF(I:I,I7,G:G),0)*VLOOKUP(H7,Modelos[],14,0)+IFERROR(G7/SUMIF(I:I,I7,G:G),0)*VLOOKUP(I7,Tabla13[],2,0) -> 51647.612 | R7: =IFERROR(VLOOKUP(A7,Modelos[],IF(B7="EST",15,14),0),0)*C7 -> 310333.79 | S7: =IFERROR(VLOOKUP(D7,Modelos[],IF(E7="EST",15,14),0),0)*F7 -> 204526.8 | T7: =IF($L7<0,0,IFERROR((T$2*IFERROR(VLOOKUP(J7,Tabla11[],2,0),0))*($L7/SUM($L$5:$L$46)),0)) -> 16502.897 | U7: =IF($L7<0,0,IFERROR((U$2*IFERROR(VLOOKUP(J7,Tabla11[],2,0),0))*($L7/SUM($L$5:$L$46)),0)) -> 3208.8967 | V7: =IF($L7<0,0,IFERROR((V$2*IFERROR(VLOOKUP(J7,Tabla11[],2,0),0))*($L7/SUM($L$5:$L$46)),0)) -> 16502.897 | W7: =IF($L7<0,0,IFERROR((W$2*IFERROR(VLOOKUP(J7,Tabla11[],2,0),0))*($L7/SUM($L$5:$L$46)),0)) -> 22920.691 | X7: =P7*$X$2 -> 822474.4 | Y7: =+X7*IFERROR(VLOOKUP(J7,Tabla11[],4,0),0) -> 123371.16 | Z7: =IF(L7>0,$Z$2/12,0) -> 25833.333 | AA7: =P7-SUM(Q7:Z7) -> 458863.52 | AB7: =IF($L7<0,0,IFERROR((AB$2*IFERROR(VLOOKUP(J7,Tabla11[],2,0),0))*($L7/SUM($L$5:$L$46)),0)) -> 26322.942 | AC7: =L7-L7*IFERROR(VLOOKUP(J7,Tabla11[],3,0),0)-Q7-T7-U7-V7-W7-L7*$X$2-(L7*$X$2)*IFERROR(VLOOKUP(J7,Tabla11[],4,0),0)-AB7-Z7 -> 383459.81 | AD7: =AA7-AB7 -> 432540.58 | AE7: =ROUND(AD7-AC7,9) -> 49080.774
A8: Vendedor 1/2 Full | B8: Outsourcing | C8: 1 | E8: Outsourcing | G8: 3 | H8: Supervisor Part | I8: Temuco | J8: Ripley | K8: Temuco | L8: =IFERROR(VLOOKUP(CONCATENATE(J8,K8),Ventas!D:H,4,0),0) -> 2814513.8 | M8: =IF(SUM(C8,F8)>0,L8*0.1,0) -> 281451.38 | N8: =SUM(L8:M8) -> 3095965.2 | O8: =N8*IFERROR(VLOOKUP(J8,Tabla11[],3,0),0) -> 1083587.8 | P8: =N8-O8 -> 2012377.4 | Q8: =IFERROR(G8/SUMIF(I:I,I8,G:G),0)*VLOOKUP(H8,Modelos[],14,0)+IFERROR(G8/SUMIF(I:I,I8,G:G),0)*VLOOKUP(I8,Tabla13[],2,0) -> 65246.163 | R8: =IFERROR(VLOOKUP(A8,Modelos[],IF(B8="EST",15,14),0),0)*C8 -> 310333.79 | S8: =IFERROR(VLOOKUP(D8,Modelos[],IF(E8="EST",15,14),0),0)*F8 -> 0 | T8: =IF($L8<0,0,IFERROR((T$2*IFERROR(VLOOKUP(J8,Tabla11[],2,0),0))*($L8/SUM($L$5:$L$46)),0)) -> 16151.291 | U8: =IF($L8<0,0,IFERROR((U$2*IFERROR(VLOOKUP(J8,Tabla11[],2,0),0))*($L8/SUM($L$5:$L$46)),0)) -> 3140.5287 | V8: =IF($L8<0,0,IFERROR((V$2*IFERROR(VLOOKUP(J8,Tabla11[],2,0),0))*($L8/SUM($L$5:$L$46)),0)) -> 16151.291 | W8: =IF($L8<0,0,IFERROR((W$2*IFERROR(VLOOKUP(J8,Tabla11[],2,0),0))*($L8/SUM($L$5:$L$46)),0)) -> 22432.348 | X8: =P8*$X$2 -> 804950.96 | Y8: =+X8*IFERROR(VLOOKUP(J8,Tabla11[],4,0),0) -> 120742.64 | Z8: =IF(L8>0,$Z$2/12,0) -> 25833.333 | AA8: =P8-SUM(Q8:Z8) -> 627395.05 | AB8: =IF($L8<0,0,IFERROR((AB$2*IFERROR(VLOOKUP(J8,Tabla11[],2,0),0))*($L8/SUM($L$5:$L$46)),0)) -> 25762.111 | AC8: =L8-L8*IFERROR(VLOOKUP(J8,Tabla11[],3,0),0)-Q8-T8-U8-V8-W8-L8*$X$2-(L8*$X$2)*IFERROR(VLOOKUP(J8,Tabla11[],4,0),0)-AB8-Z8 -> 360040.57 | AD8: =AA8-AB8 -> 601632.94 | AE8: =ROUND(AD8-AC8,9) -> 241592.38
A9: Vendedor 1/2 Full | B9: Outsourcing | C9: 1 | E9: Outsourcing | G9: 3 | H9: Supervisor Regiones | I9: V° Interior | J9: Ripley | K9: La Calera | L9: =IFERROR(VLOOKUP(CONCATENATE(J9,K9),Ventas!D:H,4,0),0) -> 2704320 | M9: =IF(SUM(C9,F9)>0,L9*0.1,0) -> 270432 | N9: =SUM(L9:M9) -> 2974752 | O9: =N9*IFERROR(VLOOKUP(J9,Tabla11[],3,0),0) -> 1041163.2 | P9: =N9-O9 -> 1933588.8 | Q9: =IFERROR(G9/SUMIF(I:I,I9,G:G),0)*VLOOKUP(H9,Modelos[],14,0)+IFERROR(G9/SUMIF(I:I,I9,G:G),0)*VLOOKUP(I9,Tabla13[],2,0) -> 179573.44 | R9: =IFERROR(VLOOKUP(A9,Modelos[],IF(B9="EST",15,14),0),0)*C9 -> 310333.79 | S9: =IFERROR(VLOOKUP(D9,Modelos[],IF(E9="EST",15,14),0),0)*F9 -> 0 | T9: =IF($L9<0,0,IFERROR((T$2*IFERROR(VLOOKUP(J9,Tabla11[],2,0),0))*($L9/SUM($L$5:$L$46)),0)) -> 15518.935 | U9: =IF($L9<0,0,IFERROR((U$2*IFERROR(VLOOKUP(J9,Tabla11[],2,0),0))*($L9/SUM($L$5:$L$46)),0)) -> 3017.5707 | V9: =IF($L9<0,0,IFERROR((V$2*IFERROR(VLOOKUP(J9,Tabla11[],2,0),0))*($L9/SUM($L$5:$L$46)),0)) -> 15518.935 | W9: =IF($L9<0,0,IFERROR((W$2*IFERROR(VLOOKUP(J9,Tabla11[],2,0),0))*($L9/SUM($L$5:$L$46)),0)) -> 21554.077 | X9: =P9*$X$2 -> 773435.52 | Y9: =+X9*IFERROR(VLOOKUP(J9,Tabla11[],4,0),0) -> 116015.33 | Z9: =IF(L9>0,$Z$2/12,0) -> 25833.333 | AA9: =P9-SUM(Q9:Z9) -> 472787.87 | AB9: =IF($L9<0,0,IFERROR((AB$2*IFERROR(VLOOKUP(J9,Tabla11[],2,0),0))*($L9/SUM($L$5:$L$46)),0)) -> 24753.473 | AC9: =L9-L9*IFERROR(VLOOKUP(J9,Tabla11[],3,0),0)-Q9-T9-U9-V9-W9-L9*$X$2-(L9*$X$2)*IFERROR(VLOOKUP(J9,Tabla11[],4,0),0)-AB9-Z9 -> 228051.03 | AD9: =AA9-AB9 -> 448034.4 | AE9: =ROUND(AD9-AC9,9) -> 219983.36
B10: Outsourcing | E10: Outsourcing | G10: 3 | H10: Supervisor Regiones | I10: Concepción | J10: Ripley | K10: Mall Concepcion | L10: =IFERROR(VLOOKUP(CONCATENATE(J10,K10),Ventas!D:H,4,0),0) -> 2604672.3 | M10: =IF(SUM(C10,F10)>0,L10*0.1,0) -> 0 | N10: =SUM(L10:M10) -> 2604672.3 | O10: =N10*IFERROR(VLOOKUP(J10,Tabla11[],3,0),0) -> 911635.31 | P10: =N10-O10 -> 1693037 | Q10: =IFERROR(G10/SUMIF(I:I,I10,G:G),0)*VLOOKUP(H10,Modelos[],14,0)+IFERROR(G10/SUMIF(I:I,I10,G:G),0)*VLOOKUP(I10,Tabla13[],2,0) -> 106001.17 | R10: =IFERROR(VLOOKUP(A10,Modelos[],IF(B10="EST",15,14),0),0)*C10 -> 0 | S10: =IFERROR(VLOOKUP(D10,Modelos[],IF(E10="EST",15,14),0),0)*F10 -> 0 | T10: =IF($L10<0,0,IFERROR((T$2*IFERROR(VLOOKUP(J10,Tabla11[],2,0),0))*($L10/SUM($L$5:$L$46)),0)) -> 14947.1 | U10: =IF($L10<0,0,IFERROR((U$2*IFERROR(VLOOKUP(J10,Tabla11[],2,0),0))*($L10/SUM($L$5:$L$46)),0)) -> 2906.3805 | V10: =IF($L10<0,0,IFERROR((V$2*IFERROR(VLOOKUP(J10,Tabla11[],2,0),0))*($L10/SUM($L$5:$L$46)),0)) -> 14947.1 | W10: =IF($L10<0,0,IFERROR((W$2*IFERROR(VLOOKUP(J10,Tabla11[],2,0),0))*($L10/SUM($L$5:$L$46)),0)) -> 20759.861 | X10: =P10*$X$2 -> 677214.8 | Y10: =+X10*IFERROR(VLOOKUP(J10,Tabla11[],4,0),0) -> 101582.22 | Z10: =IF(L10>0,$Z$2/12,0) -> 25833.333 | AA10: =P10-SUM(Q10:Z10) -> 728845.03 | AB10: =IF($L10<0,0,IFERROR((AB$2*IFERROR(VLOOKUP(J10,Tabla11[],2,0),0))*($L10/SUM($L$5:$L$46)),0)) -> 23841.367 | AC10: =L10-L10*IFERROR(VLOOKUP(J10,Tabla11[],3,0),0)-Q10-T10-U10-V10-W10-L10*$X$2-(L10*$X$2)*IFERROR(VLOOKUP(J10,Tabla11[],4,0),0)-AB10-Z10 -> 285651.42 | AD10: =AA10-AB10 -> 705003.66 | AE10: =ROUND(AD10-AC10,9) -> 419352.24
A11: Vendedor 1/2 2 días | B11: Outsourcing | C11: 1 | E11: Outsourcing | G11: 2 | H11: Supervisor Regiones | I11: V° Interior | J11: Ripley | K11: Los Andes | L11: =IFERROR(VLOOKUP(CONCATENATE(J11,K11),Ventas!D:H,4,0),0) -> 2542166.2 | M11: =IF(SUM(C11,F11)>0,L11*0.1,0) -> 254216.62 | N11: =SUM(L11:M11) -> 2796382.8 | O11: =N11*IFERROR(VLOOKUP(J11,Tabla11[],3,0),0) -> 978733.97 | P11: =N11-O11 -> 1817648.8 | Q11: =IFERROR(G11/SUMIF(I:I,I11,G:G),0)*VLOOKUP(H11,Modelos[],14,0)+IFERROR(G11/SUMIF(I:I,I11,G:G),0)*VLOOKUP(I11,Tabla13[],2,0) -> 119715.63 | R11: =IFERROR(VLOOKUP(A11,Modelos[],IF(B11="EST",15,14),0),0)*C11 -> 154393.47 | S11: =IFERROR(VLOOKUP(D11,Modelos[],IF(E11="EST",15,14),0),0)*F11 -> 0 | T11: =IF($L11<0,0,IFERROR((T$2*IFERROR(VLOOKUP(J11,Tabla11[],2,0),0))*($L11/SUM($L$5:$L$46)),0)) -> 14588.404 | U11: =IF($L11<0,0,IFERROR((U$2*IFERROR(VLOOKUP(J11,Tabla11[],2,0),0))*($L11/SUM($L$5:$L$46)),0)) -> 2836.6341 | V11: =IF($L11<0,0,IFERROR((V$2*IFERROR(VLOOKUP(J11,Tabla11[],2,0),0))*($L11/SUM($L$5:$L$46)),0)) -> 14588.404 | W11: =IF($L11<0,0,IFERROR((W$2*IFERROR(VLOOKUP(J11,Tabla11[],2,0),0))*($L11/SUM($L$5:$L$46)),0)) -> 20261.672 | X11: =P11*$X$2 -> 727059.52 | Y11: =+X11*IFERROR(VLOOKUP(J11,Tabla11[],4,0),0) -> 109058.93 | Z11: =IF(L11>0,$Z$2/12,0) -> 25833.333 | AA11: =P11-SUM(Q11:Z11) -> 629312.81 | AB11: =IF($L11<0,0,IFERROR((AB$2*IFERROR(VLOOKUP(J11,Tabla11[],2,0),0))*($L11/SUM($L$5:$L$46)),0)) -> 23269.229 | AC11: =L11-L11*IFERROR(VLOOKUP(J11,Tabla11[],3,0),0)-Q11-T11-U11-V11-W11-L11*$X$2-(L11*$X$2)*IFERROR(VLOOKUP(J11,Tabla11[],4,0),0)-AB11-Z11 -> 261918.27 | AD11: =AA11-AB11 -> 606043.58 | AE11: =ROUND(AD11-AC11,9) -> 344125.32
A12: Vendedor Full | B12: Outsourcing | C12: 1 | D12: Vendedor 2 días | E12: Outsourcing | F12: 1 | G12: 2 | H12: Supervisor Santiago | I12: Santiago 01 | J12: Ripley | K12: Costanera Center | L12: =IFERROR(VLOOKUP(CONCATENATE(J12,K12),Ventas!D:H,4,0),0) -> 2331083.1 | M12: =IF(SUM(C12,F12)>0,L12*0.1,0) -> 233108.31 | N12: =SUM(L12:M12) -> 2564191.4 | O12: =N12*IFERROR(VLOOKUP(J12,Tabla11[],3,0),0) -> 897466.98 | P12: =N12-O12 -> 1666724.4 | Q12: =IFERROR(G12/SUMIF(I:I,I12,G:G),0)*VLOOKUP(H12,Modelos[],14,0)+IFERROR(G12/SUMIF(I:I,I12,G:G),0)*VLOOKUP(I12,Tabla13[],2,0) -> 46336.658 | R12: =IFERROR(VLOOKUP(A12,Modelos[],IF(B12="EST",15,14),0),0)*C12 -> 598680.59 | S12: =IFERROR(VLOOKUP(D12,Modelos[],IF(E12="EST",15,14),0),0)*F12 -> 281148.89 | T12: =IF($L12<0,0,IFERROR((T$2*IFERROR(VLOOKUP(J12,Tabla11[],2,0),0))*($L12/SUM($L$5:$L$46)),0)) -> 13377.088 | U12: =IF($L12<0,0,IFERROR((U$2*IFERROR(VLOOKUP(J12,Tabla11[],2,0),0))*($L12/SUM($L$5:$L$46)),0)) -> 2601.1005 | V12: =IF($L12<0,0,IFERROR((V$2*IFERROR(VLOOKUP(J12,Tabla11[],2,0),0))*($L12/SUM($L$5:$L$46)),0)) -> 13377.088 | W12: =IF($L12<0,0,IFERROR((W$2*IFERROR(VLOOKUP(J12,Tabla11[],2,0),0))*($L12/SUM($L$5:$L$46)),0)) -> 18579.289 | X12: =P12*$X$2 -> 666689.76 | Y12: =+X12*IFERROR(VLOOKUP(J12,Tabla11[],4,0),0) -> 100003.46 | Z12: =IF(L12>0,$Z$2/12,0) -> 25833.333 | AA12: =P12-SUM(Q12:Z12) -> -99902.861 | AB12: =IF($L12<0,0,IFERROR((AB$2*IFERROR(VLOOKUP(J12,Tabla11[],2,0),0))*($L12/SUM($L$5:$L$46)),0)) -> 21337.121 | AC12: =L12-L12*IFERROR(VLOOKUP(J12,Tabla11[],3,0),0)-Q12-T12-U12-V12-W12-L12*$X$2-(L12*$X$2)*IFERROR(VLOOKUP(J12,Tabla11[],4,0),0)-AB12-Z12 -> 301464.11 | AD12: =AA12-AB12 -> -121239.98 | AE12: =ROUND(AD12-AC12,9) -> -422704.09
A13: Vendedor 1/2 3 días | B13: Outsourcing | C13: 1 | E13: Outsourcing | G13: 3 | H13: Supervisor Santiago | I13: Santiago 02 | J13: Ripley | K13: Florida Center | L13: =IFERROR(VLOOKUP(CONCATENATE(J13,K13),Ventas!D:H,4,0),0) -> 2069249.2 | M13: =IF(SUM(C13,F13)>0,L13*0.1,0) -> 206924.92 | N13: =SUM(L13:M13) -> 2276174.2 | O13: =N13*IFERROR(VLOOKUP(J13,Tabla11[],3,0),0) -> 796660.95 | P13: =N13-O13 -> 1479513.2 | Q13: =IFERROR(G13/SUMIF(I:I,I13,G:G),0)*VLOOKUP(H13,Modelos[],14,0)+IFERROR(G13/SUMIF(I:I,I13,G:G),0)*VLOOKUP(I13,Tabla13[],2,0) -> 69504.988 | R13: =IFERROR(VLOOKUP(A13,Modelos[],IF(B13="EST",15,14),0),0)*C13 -> 204526.8 | S13: =IFERROR(VLOOKUP(D13,Modelos[],IF(E13="EST",15,14),0),0)*F13 -> 0 | T13: =IF($L13<0,0,IFERROR((T$2*IFERROR(VLOOKUP(J13,Tabla11[],2,0),0))*($L13/SUM($L$5:$L$46)),0)) -> 11874.536 | U13: =IF($L13<0,0,IFERROR((U$2*IFERROR(VLOOKUP(J13,Tabla11[],2,0),0))*($L13/SUM($L$5:$L$46)),0)) -> 2308.9375 | V13: =IF($L13<0,0,IFERROR((V$2*IFERROR(VLOOKUP(J13,Tabla11[],2,0),0))*($L13/SUM($L$5:$L$46)),0)) -> 11874.536 | W13: =IF($L13<0,0,IFERROR((W$2*IFERROR(VLOOKUP(J13,Tabla11[],2,0),0))*($L13/SUM($L$5:$L$46)),0)) -> 16492.411 | X13: =P13*$X$2 -> 591805.28 | Y13: =+X13*IFERROR(VLOOKUP(J13,Tabla11[],4,0),0) -> 88770.792 | Z13: =IF(L13>0,$Z$2/12,0) -> 25833.333 | AA13: =P13-SUM(Q13:Z13) -> 456521.59 | AB13: =IF($L13<0,0,IFERROR((AB$2*IFERROR(VLOOKUP(J13,Tabla11[],2,0),0))*($L13/SUM($L$5:$L$46)),0)) -> 18940.475 | AC13: =L13-L13*IFERROR(VLOOKUP(J13,Tabla11[],3,0),0)-Q13-T13-U13-V13-W13-L13*$X$2-(L13*$X$2)*IFERROR(VLOOKUP(J13,Tabla11[],4,0),0)-AB13-Z13 -> 236328.14 | AD13: =AA13-AB13 -> 437581.11 | AE13: =ROUND(AD13-AC13,9) -> 201252.97
A14: Vendedor 1/2 3 días | B14: Outsourcing | C14: 1 | E14: Outsourcing | G14: 2 | H14: Supervisor Santiago | I14: Santiago 01 | J14: Ripley | K14: Plaza Egana | L14: =IFERROR(VLOOKUP(CONCATENATE(J14,K14),Ventas!D:H,4,0),0) -> 1873333.8 | M14: =IF(SUM(C14,F14)>0,L14*0.1,0) -> 187333.38 | N14: =SUM(L14:M14) -> 2060667.2 | O14: =N14*IFERROR(VLOOKUP(J14,Tabla11[],3,0),0) -> 721233.53 | P14: =N14-O14 -> 1339433.7 | Q14: =IFERROR(G14/SUMIF(I:I,I14,G:G),0)*VLOOKUP(H14,Modelos[],14,0)+IFERROR(G14/SUMIF(I:I,I14,G:G),0)*VLOOKUP(I14,Tabla13[],2,0) -> 46336.658 | R14: =IFERROR(VLOOKUP(A14,Modelos[],IF(B14="EST",15,14),0),0)*C14 -> 204526.8 | S14: =IFERROR(VLOOKUP(D14,Modelos[],IF(E14="EST",15,14),0),0)*F14 -> 0 | T14: =IF($L14<0,0,IFERROR((T$2*IFERROR(VLOOKUP(J14,Tabla11[],2,0),0))*($L14/SUM($L$5:$L$46)),0)) -> 10750.261 | U14: =IF($L14<0,0,IFERROR((U$2*IFERROR(VLOOKUP(J14,Tabla11[],2,0),0))*($L14/SUM($L$5:$L$46)),0)) -> 2090.3286 | V14: =IF($L14<0,0,IFERROR((V$2*IFERROR(VLOOKUP(J14,Tabla11[],2,0),0))*($L14/SUM($L$5:$L$46)),0)) -> 10750.261 | W14: =IF($L14<0,0,IFERROR((W$2*IFERROR(VLOOKUP(J14,Tabla11[],2,0),0))*($L14/SUM($L$5:$L$46)),0)) -> 14930.919 | X14: =P14*$X$2 -> 535773.48 | Y14: =+X14*IFERROR(VLOOKUP(J14,Tabla11[],4,0),0) -> 80366.022 | Z14: =IF(L14>0,$Z$2/12,0) -> 25833.333 | AA14: =P14-SUM(Q14:Z14) -> 408075.64 | AB14: =IF($L14<0,0,IFERROR((AB$2*IFERROR(VLOOKUP(J14,Tabla11[],2,0),0))*($L14/SUM($L$5:$L$46)),0)) -> 17147.201 | AC14: =L14-L14*IFERROR(VLOOKUP(J14,Tabla11[],3,0),0)-Q14-T14-U14-V14-W14-L14*$X$2-(L14*$X$2)*IFERROR(VLOOKUP(J14,Tabla11[],4,0),0)-AB14-Z14 -> 228094.47 | AD14: =AA14-AB14 -> 390928.43 | AE14: =ROUND(AD14-AC14,9) -> 162833.97
A15: Vendedor 1/2 3 días | B15: Outsourcing | C15: 1 | E15: Outsourcing | G15: 3 | H15: Supervisor Regiones | I15: La Serena | J15: Ripley | K15: La Serena | L15: =IFERROR(VLOOKUP(CONCATENATE(J15,K15),Ventas!D:H,4,0),0) -> 1668596.9 | M15: =IF(SUM(C15,F15)>0,L15*0.1,0) -> 166859.69 | N15: =SUM(L15:M15) -> 1835456.6 | O15: =N15*IFERROR(VLOOKUP(J15,Tabla11[],3,0),0) -> 642409.82 | P15: =N15-O15 -> 1193046.8 | Q15: =IFERROR(G15/SUMIF(I:I,I15,G:G),0)*VLOOKUP(H15,Modelos[],14,0)+IFERROR(G15/SUMIF(I:I,I15,G:G),0)*VLOOKUP(I15,Tabla13[],2,0) -> 161601.88 | R15: =IFERROR(VLOOKUP(A15,Modelos[],IF(B15="EST",15,14),0),0)*C15 -> 204526.8 | S15: =IFERROR(VLOOKUP(D15,Modelos[],IF(E15="EST",15,14),0),0)*F15 -> 0 | T15: =IF($L15<0,0,IFERROR((T$2*IFERROR(VLOOKUP(J15,Tabla11[],2,0),0))*($L15/SUM($L$5:$L$46)),0)) -> 9575.3637 | U15: =IF($L15<0,0,IFERROR((U$2*IFERROR(VLOOKUP(J15,Tabla11[],2,0),0))*($L15/SUM($L$5:$L$46)),0)) -> 1861.8763 | V15: =IF($L15<0,0,IFERROR((V$2*IFERROR(VLOOKUP(J15,Tabla11[],2,0),0))*($L15/SUM($L$5:$L$46)),0)) -> 9575.3637 | W15: =IF($L15<0,0,IFERROR((W$2*IFERROR(VLOOKUP(J15,Tabla11[],2,0),0))*($L15/SUM($L$5:$L$46)),0)) -> 13299.116 | X15: =P15*$X$2 -> 477218.72 | Y15: =+X15*IFERROR(VLOOKUP(J15,Tabla11[],4,0),0) -> 71582.808 | Z15: =IF(L15>0,$Z$2/12,0) -> 25833.333 | AA15: =P15-SUM(Q15:Z15) -> 217971.54 | AB15: =IF($L15<0,0,IFERROR((AB$2*IFERROR(VLOOKUP(J15,Tabla11[],2,0),0))*($L15/SUM($L$5:$L$46)),0)) -> 15273.181 | AC15: =L15-L15*IFERROR(VLOOKUP(J15,Tabla11[],3,0),0)-Q15-T15-U15-V15-W15-L15*$X$2-(L15*$X$2)*IFERROR(VLOOKUP(J15,Tabla11[],4,0),0)-AB15-Z15 -> 80013.302 | AD15: =AA15-AB15 -> 202698.36 | AE15: =ROUND(AD15-AC15,9) -> 122685.06
B16: Outsourcing | E16: Outsourcing | G16: 3 | H16: Supervisor Part | I16: Iquique | J16: Ripley | K16: Iquique | L16: =IFERROR(VLOOKUP(CONCATENATE(J16,K16),Ventas!D:H,4,0),0) -> 1667378.5 | M16: =IF(SUM(C16,F16)>0,L16*0.1,0) -> 0 | N16: =SUM(L16:M16) -> 1667378.5 | O16: =N16*IFERROR(VLOOKUP(J16,Tabla11[],3,0),0) -> 583582.46 | P16: =N16-O16 -> 1083796 | Q16: =IFERROR(G16/SUMIF(I:I,I16,G:G),0)*VLOOKUP(H16,Modelos[],14,0)+IFERROR(G16/SUMIF(I:I,I16,G:G),0)*VLOOKUP(I16,Tabla13[],2,0) -> 134909.42 | R16: =IFERROR(VLOOKUP(A16,Modelos[],IF(B16="EST",15,14),0),0)*C16 -> 0 | S16: =IFERROR(VLOOKUP(D16,Modelos[],IF(E16="EST",15,14),0),0)*F16 -> 0 | T16: =IF($L16<0,0,IFERROR((T$2*IFERROR(VLOOKUP(J16,Tabla11[],2,0),0))*($L16/SUM($L$5:$L$46)),0)) -> 9568.3715 | U16: =IF($L16<0,0,IFERROR((U$2*IFERROR(VLOOKUP(J16,Tabla11[],2,0),0))*($L16/SUM($L$5:$L$46)),0)) -> 1860.5167 | V16: =IF($L16<0,0,IFERROR((V$2*IFERROR(VLOOKUP(J16,Tabla11[],2,0),0))*($L16/SUM($L$5:$L$46)),0)) -> 9568.3715 | W16: =IF($L16<0,0,IFERROR((W$2*IFERROR(VLOOKUP(J16,Tabla11[],2,0),0))*($L16/SUM($L$5:$L$46)),0)) -> 13289.405 | X16: =P16*$X$2 -> 433518.4 | Y16: =+X16*IFERROR(VLOOKUP(J16,Tabla11[],4,0),0) -> 65027.76 | Z16: =IF(L16>0,$Z$2/12,0) -> 25833.333 | AA16: =P16-SUM(Q16:Z16) -> 390220.42 | AB16: =IF($L16<0,0,IFERROR((AB$2*IFERROR(VLOOKUP(J16,Tabla11[],2,0),0))*($L16/SUM($L$5:$L$46)),0)) -> 15262.028 | AC16: =L16-L16*IFERROR(VLOOKUP(J16,Tabla11[],3,0),0)-Q16-T16-U16-V16-W16-L16*$X$2-(L16*$X$2)*IFERROR(VLOOKUP(J16,Tabla11[],4,0),0)-AB16-Z16 -> 106510.46 | AD16: =AA16-AB16 -> 374958.4 | AE16: =ROUND(AD16-AC16,9) -> 268447.93
A17: Vendedor 1/2 3 días | B17: Outsourcing | C17: 1 | E17: Outsourcing | G17: 3 | H17: Supervisor Santiago | I17: Santiago 02 | J17: Ripley | K17: Plaza Oeste | L17: =IFERROR(VLOOKUP(CONCATENATE(J17,K17),Ventas!D:H,4,0),0) -> 1665920 | M17: =IF(SUM(C17,F17)>0,L17*0.1,0) -> 166592 | N17: =SUM(L17:M17) -> 1832512 | O17: =N17*IFERROR(VLOOKUP(J17,Tabla11[],3,0),0) -> 641379.2 | P17: =N17-O17 -> 1191132.8 | Q17: =IFERROR(G17/SUMIF(I:I,I17,G:G),0)*VLOOKUP(H17,Modelos[],14,0)+IFERROR(G17/SUMIF(I:I,I17,G:G),0)*VLOOKUP(I17,Tabla13[],2,0) -> 69504.988 | R17: =IFERROR(VLOOKUP(A17,Modelos[],IF(B17="EST",15,14),0),0)*C17 -> 204526.8 | S17: =IFERROR(VLOOKUP(D17,Modelos[],IF(E17="EST",15,14),0),0)*F17 -> 0 | T17: =IF($L17<0,0,IFERROR((T$2*IFERROR(VLOOKUP(J17,Tabla11[],2,0),0))*($L17/SUM($L$5:$L$46)),0)) -> 9560.002 | U17: =IF($L17<0,0,IFERROR((U$2*IFERROR(VLOOKUP(J17,Tabla11[],2,0),0))*($L17/SUM($L$5:$L$46)),0)) -> 1858.8893 | V17: =IF($L17<0,0,IFERROR((V$2*IFERROR(VLOOKUP(J17,Tabla11[],2,0),0))*($L17/SUM($L$5:$L$46)),0)) -> 9560.002 | W17: =IF($L17<0,0,IFERROR((W$2*IFERROR(VLOOKUP(J17,Tabla11[],2,0),0))*($L17/SUM($L$5:$L$46)),0)) -> 13277.781 | X17: =P17*$X$2 -> 476453.12 | Y17: =+X17*IFERROR(VLOOKUP(J17,Tabla11[],4,0),0) -> 71467.968 | Z17: =IF(L17>0,$Z$2/12,0) -> 25833.333 | AA17: =P17-SUM(Q17:Z17) -> 309089.92 | AB17: =IF($L17<0,0,IFERROR((AB$2*IFERROR(VLOOKUP(J17,Tabla11[],2,0),0))*($L17/SUM($L$5:$L$46)),0)) -> 15248.678 | AC17: =L17-L17*IFERROR(VLOOKUP(J17,Tabla11[],3,0),0)-Q17-T17-U17-V17-W17-L17*$X$2-(L17*$X$2)*IFERROR(VLOOKUP(J17,Tabla11[],4,0),0)-AB17-Z17 -> 171681.13 | AD17: =AA17-AB17 -> 293841.24 | AE17: =ROUND(AD17-AC17,9) -> 122160.11
A18: Vendedor 1/2 Full | B18: Outsourcing | C18: 1 | D18: Vendedor 1/2 3 días | E18: Outsourcing | F18: 1 | G18: 3 | H18: Supervisor Santiago | I18: Santiago 02 | J18: Ripley | K18: Plaza Vespucio | L18: =IFERROR(VLOOKUP(CONCATENATE(J18,K18),Ventas!D:H,4,0),0) -> 1610832.3 | M18: =IF(SUM(C18,F18)>0,L18*0.1,0) -> 161083.23 | N18: =SUM(L18:M18) -> 1771915.5 | O18: =N18*IFERROR(VLOOKUP(J18,Tabla11[],3,0),0) -> 620170.44 | P18: =N18-O18 -> 1151745.1 | Q18: =IFERROR(G18/SUMIF(I:I,I18,G:G),0)*VLOOKUP(H18,Modelos[],14,0)+IFERROR(G18/SUMIF(I:I,I18,G:G),0)*VLOOKUP(I18,Tabla13[],2,0) -> 69504.988 | R18: =IFERROR(VLOOKUP(A18,Modelos[],IF(B18="EST",15,14),0),0)*C18 -> 310333.79 | S18: =IFERROR(VLOOKUP(D18,Modelos[],IF(E18="EST",15,14),0),0)*F18 -> 204526.8 | T18: =IF($L18<0,0,IFERROR((T$2*IFERROR(VLOOKUP(J18,Tabla11[],2,0),0))*($L18/SUM($L$5:$L$46)),0)) -> 9243.8773 | U18: =IF($L18<0,0,IFERROR((U$2*IFERROR(VLOOKUP(J18,Tabla11[],2,0),0))*($L18/SUM($L$5:$L$46)),0)) -> 1797.4206 | V18: =IF($L18<0,0,IFERROR((V$2*IFERROR(VLOOKUP(J18,Tabla11[],2,0),0))*($L18/SUM($L$5:$L$46)),0)) -> 9243.8773 | W18: =IF($L18<0,0,IFERROR((W$2*IFERROR(VLOOKUP(J18,Tabla11[],2,0),0))*($L18/SUM($L$5:$L$46)),0)) -> 12838.719 | X18: =P18*$X$2 -> 460698.04 | Y18: =+X18*IFERROR(VLOOKUP(J18,Tabla11[],4,0),0) -> 69104.706 | Z18: =IF(L18>0,$Z$2/12,0) -> 25833.333 | AA18: =P18-SUM(Q18:Z18) -> -21380.45 | AB18: =IF($L18<0,0,IFERROR((AB$2*IFERROR(VLOOKUP(J18,Tabla11[],2,0),0))*($L18/SUM($L$5:$L$46)),0)) -> 14744.444 | AC18: =L18-L18*IFERROR(VLOOKUP(J18,Tabla11[],3,0),0)-Q18-T18-U18-V18-W18-L18*$X$2-(L18*$X$2)*IFERROR(VLOOKUP(J18,Tabla11[],4,0),0)-AB18-Z18 -> 162851.48 | AD18: =AA18-AB18 -> -36124.894 | AE18: =ROUND(AD18-AC18,9) -> -198976.37
A19: Vendedor 1/2 2 días | B19: Outsourcing | C19: 1 | E19: Outsourcing | G19: 3 | H19: Supervisor Regiones | I19: VI-VII | J19: Ripley | K19: Rancagua | L19: =IFERROR(VLOOKUP(CONCATENATE(J19,K19),Ventas!D:H,4,0),0) -> 1504930.8 | M19: =IF(SUM(C19,F19)>0,L19*0.1,0) -> 150493.08 | N19: =SUM(L19:M19) -> 1655423.8 | O19: =N19*IFERROR(VLOOKUP(J19,Tabla11[],3,0),0) -> 579398.35 | P19: =N19-O19 -> 1076025.5 | Q19: =IFERROR(G19/SUMIF(I:I,I19,G:G),0)*VLOOKUP(H19,Modelos[],14,0)+IFERROR(G19/SUMIF(I:I,I19,G:G),0)*VLOOKUP(I19,Tabla13[],2,0) -> 154942.83 | R19: =IFERROR(VLOOKUP(A19,Modelos[],IF(B19="EST",15,14),0),0)*C19 -> 154393.47 | S19: =IFERROR(VLOOKUP(D19,Modelos[],IF(E19="EST",15,14),0),0)*F19 -> 0 | T19: =IF($L19<0,0,IFERROR((T$2*IFERROR(VLOOKUP(J19,Tabla11[],2,0),0))*($L19/SUM($L$5:$L$46)),0)) -> 8636.1537 | U19: =IF($L19<0,0,IFERROR((U$2*IFERROR(VLOOKUP(J19,Tabla11[],2,0),0))*($L19/SUM($L$5:$L$46)),0)) -> 1679.2521 | V19: =IF($L19<0,0,IFERROR((V$2*IFERROR(VLOOKUP(J19,Tabla11[],2,0),0))*($L19/SUM($L$5:$L$46)),0)) -> 8636.1537 | W19: =IF($L19<0,0,IFERROR((W$2*IFERROR(VLOOKUP(J19,Tabla11[],2,0),0))*($L19/SUM($L$5:$L$46)),0)) -> 11994.658 | X19: =P19*$X$2 -> 430410.2 | Y19: =+X19*IFERROR(VLOOKUP(J19,Tabla11[],4,0),0) -> 64561.53 | Z19: =IF(L19>0,$Z$2/12,0) -> 25833.333 | AA19: =P19-SUM(Q19:Z19) -> 214937.92 | AB19: =IF($L19<0,0,IFERROR((AB$2*IFERROR(VLOOKUP(J19,Tabla11[],2,0),0))*($L19/SUM($L$5:$L$46)),0)) -> 13775.094 | AC19: =L19-L19*IFERROR(VLOOKUP(J19,Tabla11[],3,0),0)-Q19-T19-U19-V19-W19-L19*$X$2-(L19*$X$2)*IFERROR(VLOOKUP(J19,Tabla11[],4,0),0)-AB19-Z19 -> 60439.366 | AD19: =AA19-AB19 -> 201162.82 | AE19: =ROUND(AD19-AC19,9) -> 140723.46
A20: Vendedor 1/2 2 días | B20: Outsourcing | C20: 0.5 | E20: Outsourcing | G20: 3 | H20: Supervisor Part | I20: Temuco | J20: Ripley | K20: Portal Temuco | L20: =IFERROR(VLOOKUP(CONCATENATE(J20,K20),Ventas!D:H,4,0),0) -> 1466126.2 | M20: =IF(SUM(C20,F20)>0,L20*0.1,0) -> 146612.62 | N20: =SUM(L20:M20) -> 1612738.8 | O20: =N20*IFERROR(VLOOKUP(J20,Tabla11[],3,0),0) -> 564458.57 | P20: =N20-O20 -> 1048280.2 | Q20: =IFERROR(G20/SUMIF(I:I,I20,G:G),0)*VLOOKUP(H20,Modelos[],14,0)+IFERROR(G20/SUMIF(I:I,I20,G:G),0)*VLOOKUP(I20,Tabla13[],2,0) -> 65246.163 | R20: =IFERROR(VLOOKUP(A20,Modelos[],IF(B20="EST",15,14),0),0)*C20 -> 77196.733 | S20: =IFERROR(VLOOKUP(D20,Modelos[],IF(E20="EST",15,14),0),0)*F20 -> 0 | T20: =IF($L20<0,0,IFERROR((T$2*IFERROR(VLOOKUP(J20,Tabla11[],2,0),0))*($L20/SUM($L$5:$L$46)),0)) -> 8413.4706 | U20: =IF($L20<0,0,IFERROR((U$2*IFERROR(VLOOKUP(J20,Tabla11[],2,0),0))*($L20/SUM($L$5:$L$46)),0)) -> 1635.9526 | V20: =IF($L20<0,0,IFERROR((V$2*IFERROR(VLOOKUP(J20,Tabla11[],2,0),0))*($L20/SUM($L$5:$L$46)),0)) -> 8413.4706 | W20: =IF($L20<0,0,IFERROR((W$2*IFERROR(VLOOKUP(J20,Tabla11[],2,0),0))*($L20/SUM($L$5:$L$46)),0)) -> 11685.376 | X20: =P20*$X$2 -> 419312.08 | Y20: =+X20*IFERROR(VLOOKUP(J20,Tabla11[],4,0),0) -> 62896.812 | Z20: =IF(L20>0,$Z$2/12,0) -> 25833.333 | AA20: =P20-SUM(Q20:Z20) -> 367646.81 | AB20: =IF($L20<0,0,IFERROR((AB$2*IFERROR(VLOOKUP(J20,Tabla11[],2,0),0))*($L20/SUM($L$5:$L$46)),0)) -> 13419.904 | AC20: =L20-L20*IFERROR(VLOOKUP(J20,Tabla11[],3,0),0)-Q20-T20-U20-V20-W20-L20*$X$2-(L20*$X$2)*IFERROR(VLOOKUP(J20,Tabla11[],4,0),0)-AB20-Z20 -> 143916.3 | AD20: =AA20-AB20 -> 354226.91 | AE20: =ROUND(AD20-AC20,9) -> 210310.61
A21: Vendedor 1/2 Full | B21: Outsourcing | C21: 1 | E21: Outsourcing | G21: 3 | H21: Supervisor Part | I21: Antofagasta | J21: Ripley | K21: Antofagasta | L21: =IFERROR(VLOOKUP(CONCATENATE(J21,K21),Ventas!D:H,4,0),0) -> 1413012.3 | M21: =IF(SUM(C21,F21)>0,L21*0.1,0) -> 141301.23 | N21: =SUM(L21:M21) -> 1554313.5 | O21: =N21*IFERROR(VLOOKUP(J21,Tabla11[],3,0),0) -> 544009.74 | P21: =N21-O21 -> 1010303.8 | Q21: =IFERROR(G21/SUMIF(I:I,I21,G:G),0)*VLOOKUP(H21,Modelos[],14,0)+IFERROR(G21/SUMIF(I:I,I21,G:G),0)*VLOOKUP(I21,Tabla13[],2,0) -> 121576.09 | R21: =IFERROR(VLOOKUP(A21,Modelos[],IF(B21="EST",15,14),0),0)*C21 -> 310333.79 | S21: =IFERROR(VLOOKUP(D21,Modelos[],IF(E21="EST",15,14),0),0)*F21 -> 0 | T21: =IF($L21<0,0,IFERROR((T$2*IFERROR(VLOOKUP(J21,Tabla11[],2,0),0))*($L21/SUM($L$5:$L$46)),0)) -> 8108.673 | U21: =IF($L21<0,0,IFERROR((U$2*IFERROR(VLOOKUP(J21,Tabla11[],2,0),0))*($L21/SUM($L$5:$L$46)),0)) -> 1576.6864 | V21: =IF($L21<0,0,IFERROR((V$2*IFERROR(VLOOKUP(J21,Tabla11[],2,0),0))*($L21/SUM($L$5:$L$46)),0)) -> 8108.673 | W21: =IF($L21<0,0,IFERROR((W$2*IFERROR(VLOOKUP(J21,Tabla11[],2,0),0))*($L21/SUM($L$5:$L$46)),0)) -> 11262.046 | X21: =P21*$X$2 -> 404121.52 | Y21: =+X21*IFERROR(VLOOKUP(J21,Tabla11[],4,0),0) -> 60618.228 | Z21: =IF(L21>0,$Z$2/12,0) -> 25833.333 | AA21: =P21-SUM(Q21:Z21) -> 58764.766 | AB21: =IF($L21<0,0,IFERROR((AB$2*IFERROR(VLOOKUP(J21,Tabla11[],2,0),0))*($L21/SUM($L$5:$L$46)),0)) -> 12933.736 | AC21: =L21-L21*IFERROR(VLOOKUP(J21,Tabla11[],3,0),0)-Q21-T21-U21-V21-W21-L21*$X$2-(L21*$X$2)*IFERROR(VLOOKUP(J21,Tabla11[],4,0),0)-AB21-Z21 -> 79073.105 | AD21: =AA21-AB21 -> 45831.03 | AE21: =ROUND(AD21-AC21,9) -> -33242.076
B22: Outsourcing | E22: Outsourcing | G22: 3 | H22: Supervisor Regiones | I22: Concepción | J22: Ripley | K22: El Trebol | L22: =IFERROR(VLOOKUP(CONCATENATE(J22,K22),Ventas!D:H,4,0),0) -> 1302190.8 | M22: =IF(SUM(C22,F22)>0,L22*0.1,0) -> 0 | N22: =SUM(L22:M22) -> 1302190.8 | O22: =N22*IFERROR(VLOOKUP(J22,Tabla11[],3,0),0) -> 455766.77 | P22: =N22-O22 -> 846424 | Q22: =IFERROR(G22/SUMIF(I:I,I22,G:G),0)*VLOOKUP(H22,Modelos[],14,0)+IFERROR(G22/SUMIF(I:I,I22,G:G),0)*VLOOKUP(I22,Tabla13[],2,0) -> 106001.17 | R22: =IFERROR(VLOOKUP(A22,Modelos[],IF(B22="EST",15,14),0),0)*C22 -> 0 | S22: =IFERROR(VLOOKUP(D22,Modelos[],IF(E22="EST",15,14),0),0)*F22 -> 0 | T22: =IF($L22<0,0,IFERROR((T$2*IFERROR(VLOOKUP(J22,Tabla11[],2,0),0))*($L22/SUM($L$5:$L$46)),0)) -> 7472.7156 | U22: =IF($L22<0,0,IFERROR((U$2*IFERROR(VLOOKUP(J22,Tabla11[],2,0),0))*($L22/SUM($L$5:$L$46)),0)) -> 1453.028 | V22: =IF($L22<0,0,IFERROR((V$2*IFERROR(VLOOKUP(J22,Tabla11[],2,0),0))*($L22/SUM($L$5:$L$46)),0)) -> 7472.7156 | W22: =IF($L22<0,0,IFERROR((W$2*IFERROR(VLOOKUP(J22,Tabla11[],2,0),0))*($L22/SUM($L$5:$L$46)),0)) -> 10378.772 | X22: =P22*$X$2 -> 338569.6 | Y22: =+X22*IFERROR(VLOOKUP(J22,Tabla11[],4,0),0) -> 50785.44 | Z22: =IF(L22>0,$Z$2/12,0) -> 25833.333 | AA22: =P22-SUM(Q22:Z22) -> 298457.22 | AB22: =IF($L22<0,0,IFERROR((AB$2*IFERROR(VLOOKUP(J22,Tabla11[],2,0),0))*($L22/SUM($L$5:$L$46)),0)) -> 11919.353 | AC22: =L22-L22*IFERROR(VLOOKUP(J22,Tabla11[],3,0),0)-Q22-T22-U22-V22-W22-L22*$X$2-(L22*$X$2)*IFERROR(VLOOKUP(J22,Tabla11[],4,0),0)-AB22-Z22 -> 76885.155 | AD22: =AA22-AB22 -> 286537.87 | AE22: =ROUND(AD22-AC22,9) -> 209652.71
B23: Outsourcing | E23: Outsourcing | G23: 3 | H23: Supervisor Santiago | I23: Santiago 03 | J23: Ripley | K23: San Bernardo | L23: =IFERROR(VLOOKUP(CONCATENATE(J23,K23),Ventas!D:H,4,0),0) -> 1170487.7 | M23: =IF(SUM(C23,F23)>0,L23*0.1,0) -> 0 | N23: =SUM(L23:M23) -> 1170487.7 | O23: =N23*IFERROR(VLOOKUP(J23,Tabla11[],3,0),0) -> 409670.69 | P23: =N23-O23 -> 760817 | Q23: =IFERROR(G23/SUMIF(I:I,I23,G:G),0)*VLOOKUP(H23,Modelos[],14,0)+IFERROR(G23/SUMIF(I:I,I23,G:G),0)*VLOOKUP(I23,Tabla13[],2,0) -> 73262.014 | R23: =IFERROR(VLOOKUP(A23,Modelos[],IF(B23="EST",15,14),0),0)*C23 -> 0 | S23: =IFERROR(VLOOKUP(D23,Modelos[],IF(E23="EST",15,14),0),0)*F23 -> 0 | T23: =IF($L23<0,0,IFERROR((T$2*IFERROR(VLOOKUP(J23,Tabla11[],2,0),0))*($L23/SUM($L$5:$L$46)),0)) -> 6716.928 | U23: =IF($L23<0,0,IFERROR((U$2*IFERROR(VLOOKUP(J23,Tabla11[],2,0),0))*($L23/SUM($L$5:$L$46)),0)) -> 1306.0693 | V23: =IF($L23<0,0,IFERROR((V$2*IFERROR(VLOOKUP(J23,Tabla11[],2,0),0))*($L23/SUM($L$5:$L$46)),0)) -> 6716.928 | W23: =IF($L23<0,0,IFERROR((W$2*IFERROR(VLOOKUP(J23,Tabla11[],2,0),0))*($L23/SUM($L$5:$L$46)),0)) -> 9329.0667 | X23: =P23*$X$2 -> 304326.8 | Y23: =+X23*IFERROR(VLOOKUP(J23,Tabla11[],4,0),0) -> 45649.02 | Z23: =IF(L23>0,$Z$2/12,0) -> 25833.333 | AA23: =P23-SUM(Q23:Z23) -> 287676.84 | AB23: =IF($L23<0,0,IFERROR((AB$2*IFERROR(VLOOKUP(J23,Tabla11[],2,0),0))*($L23/SUM($L$5:$L$46)),0)) -> 10713.834 | AC23: =L23-L23*IFERROR(VLOOKUP(J23,Tabla11[],3,0),0)-Q23-T23-U23-V23-W23-L23*$X$2-(L23*$X$2)*IFERROR(VLOOKUP(J23,Tabla11[],4,0),0)-AB23-Z23 -> 88514.488 | AD23: =AA23-AB23 -> 276963.01 | AE23: =ROUND(AD23-AC23,9) -> 188448.52
B24: Outsourcing | E24: Outsourcing | G24: 3 | H24: Supervisor Santiago | I24: Santiago 03 | J24: Ripley | K24: Puente | L24: =IFERROR(VLOOKUP(CONCATENATE(J24,K24),Ventas!D:H,4,0),0) -> 1122784.6 | M24: =IF(SUM(C24,F24)>0,L24*0.1,0) -> 0 | N24: =SUM(L24:M24) -> 1122784.6 | O24: =N24*IFERROR(VLOOKUP(J24,Tabla11[],3,0),0) -> 392974.62 | P24: =N24-O24 -> 729810 | Q24: =IFERROR(G24/SUMIF(I:I,I24,G:G),0)*VLOOKUP(H24,Modelos[],14,0)+IFERROR(G24/SUMIF(I:I,I24,G:G),0)*VLOOKUP(I24,Tabla13[],2,0) -> 73262.014 | R24: =IFERROR(VLOOKUP(A24,Modelos[],IF(B24="EST",15,14),0),0)*C24 -> 0 | S24: =IFERROR(VLOOKUP(D24,Modelos[],IF(E24="EST",15,14),0),0)*F24 -> 0 | T24: =IF($L24<0,0,IFERROR((T$2*IFERROR(VLOOKUP(J24,Tabla11[],2,0),0))*($L24/SUM($L$5:$L$46)),0)) -> 6443.1805 | U24: =IF($L24<0,0,IFERROR((U$2*IFERROR(VLOOKUP(J24,Tabla11[],2,0),0))*($L24/SUM($L$5:$L$46)),0)) -> 1252.8406 | V24: =IF($L24<0,0,IFERROR((V$2*IFERROR(VLOOKUP(J24,Tabla11[],2,0),0))*($L24/SUM($L$5:$L$46)),0)) -> 6443.1805 | W24: =IF($L24<0,0,IFERROR((W$2*IFERROR(VLOOKUP(J24,Tabla11[],2,0),0))*($L24/SUM($L$5:$L$46)),0)) -> 8948.8617 | X24: =P24*$X$2 -> 291924 | Y24: =+X24*IFERROR(VLOOKUP(J24,Tabla11[],4,0),0) -> 43788.6 | Z24: =IF(L24>0,$Z$2/12,0) -> 25833.333 | AA24: =P24-SUM(Q24:Z24) -> 271913.99 | AB24: =IF($L24<0,0,IFERROR((AB$2*IFERROR(VLOOKUP(J24,Tabla11[],2,0),0))*($L24/SUM($L$5:$L$46)),0)) -> 10277.193 | AC24: =L24-L24*IFERROR(VLOOKUP(J24,Tabla11[],3,0),0)-Q24-T24-U24-V24-W24-L24*$X$2-(L24*$X$2)*IFERROR(VLOOKUP(J24,Tabla11[],4,0),0)-AB24-Z24 -> 80868.473 | AD24: =AA24-AB24 -> 261636.8 | AE24: =ROUND(AD24-AC24,9) -> 180768.32
A25: Vendedor 1/2 2 días | B25: Outsourcing | C25: 1 | E25: Outsourcing | G25: 1 | H25: Supervisor Regiones | I25: VI-VII | J25: Ripley | K25: Curico | L25: =IFERROR(VLOOKUP(CONCATENATE(J25,K25),Ventas!D:H,4,0),0) -> 1109549.2 | M25: =IF(SUM(C25,F25)>0,L25*0.1,0) -> 110954.92 | N25: =SUM(L25:M25) -> 1220504.2 | O25: =N25*IFERROR(VLOOKUP(J25,Tabla11[],3,0),0) -> 427176.45 | P25: =N25-O25 -> 793327.7 | Q25: =IFERROR(G25/SUMIF(I:I,I25,G:G),0)*VLOOKUP(H25,Modelos[],14,0)+IFERROR(G25/SUMIF(I:I,I25,G:G),0)*VLOOKUP(I25,Tabla13[],2,0) -> 51647.612 | R25: =IFERROR(VLOOKUP(A25,Modelos[],IF(B25="EST",15,14),0),0)*C25 -> 154393.47 | S25: =IFERROR(VLOOKUP(D25,Modelos[],IF(E25="EST",15,14),0),0)*F25 -> 0 | T25: =IF($L25<0,0,IFERROR((T$2*IFERROR(VLOOKUP(J25,Tabla11[],2,0),0))*($L25/SUM($L$5:$L$46)),0)) -> 6367.2282 | U25: =IF($L25<0,0,IFERROR((U$2*IFERROR(VLOOKUP(J25,Tabla11[],2,0),0))*($L25/SUM($L$5:$L$46)),0)) -> 1238.0722 | V25: =IF($L25<0,0,IFERROR((V$2*IFERROR(VLOOKUP(J25,Tabla11[],2,0),0))*($L25/SUM($L$5:$L$46)),0)) -> 6367.2282 | W25: =IF($L25<0,0,IFERROR((W$2*IFERROR(VLOOKUP(J25,Tabla11[],2,0),0))*($L25/SUM($L$5:$L$46)),0)) -> 8843.3726 | X25: =P25*$X$2 -> 317331.08 | Y25: =+X25*IFERROR(VLOOKUP(J25,Tabla11[],4,0),0) -> 47599.662 | Z25: =IF(L25>0,$Z$2/12,0) -> 25833.333 | AA25: =P25-SUM(Q25:Z25) -> 173706.65 | AB25: =IF($L25<0,0,IFERROR((AB$2*IFERROR(VLOOKUP(J25,Tabla11[],2,0),0))*($L25/SUM($L$5:$L$46)),0)) -> 10156.046 | AC25: =L25-L25*IFERROR(VLOOKUP(J25,Tabla11[],3,0),0)-Q25-T25-U25-V25-W25-L25*$X$2-(L25*$X$2)*IFERROR(VLOOKUP(J25,Tabla11[],4,0),0)-AB25-Z25 -> 100361.46 | AD25: =AA25-AB25 -> 163550.6 | AE25: =ROUND(AD25-AC25,9) -> 63189.139
A26: Vendedor 1/2 2 días | B26: Outsourcing | C26: 1 | E26: Outsourcing | G26: 0 | H26: Supervisor Regiones | I26: Valdivia | J26: Ripley | K26: Nueva Valdivia Store | L26: =IFERROR(VLOOKUP(CONCATENATE(J26,K26),Ventas!D:H,4,0),0) -> 1106101.5 | M26: =IF(SUM(C26,F26)>0,L26*0.1,0) -> 110610.15 | N26: =SUM(L26:M26) -> 1216711.7 | O26: =N26*IFERROR(VLOOKUP(J26,Tabla11[],3,0),0) -> 425849.09 | P26: =N26-O26 -> 790862.6 | Q26: =IFERROR(G26/SUMIF(I:I,I26,G:G),0)*VLOOKUP(H26,Modelos[],14,0)+IFERROR(G26/SUMIF(I:I,I26,G:G),0)*VLOOKUP(I26,Tabla13[],2,0) -> 0 | R26: =IFERROR(VLOOKUP(A26,Modelos[],IF(B26="EST",15,14),0),0)*C26 -> 154393.47 | S26: =IFERROR(VLOOKUP(D26,Modelos[],IF(E26="EST",15,14),0),0)*F26 -> 0 | T26: =IF($L26<0,0,IFERROR((T$2*IFERROR(VLOOKUP(J26,Tabla11[],2,0),0))*($L26/SUM($L$5:$L$46)),0)) -> 6347.4434 | U26: =IF($L26<0,0,IFERROR((U$2*IFERROR(VLOOKUP(J26,Tabla11[],2,0),0))*($L26/SUM($L$5:$L$46)),0)) -> 1234.2251 | V26: =IF($L26<0,0,IFERROR((V$2*IFERROR(VLOOKUP(J26,Tabla11[],2,0),0))*($L26/SUM($L$5:$L$46)),0)) -> 6347.4434 | W26: =IF($L26<0,0,IFERROR((W$2*IFERROR(VLOOKUP(J26,Tabla11[],2,0),0))*($L26/SUM($L$5:$L$46)),0)) -> 8815.8936 | X26: =P26*$X$2 -> 316345.04 | Y26: =+X26*IFERROR(VLOOKUP(J26,Tabla11[],4,0),0) -> 47451.756 | Z26: =IF(L26>0,$Z$2/12,0) -> 25833.333 | AA26: =P26-SUM(Q26:Z26) -> 224094 | AB26: =IF($L26<0,0,IFERROR((AB$2*IFERROR(VLOOKUP(J26,Tabla11[],2,0),0))*($L26/SUM($L$5:$L$46)),0)) -> 10124.488 | AC26: =L26-L26*IFERROR(VLOOKUP(J26,Tabla11[],3,0),0)-Q26-T26-U26-V26-W26-L26*$X$2-(L26*$X$2)*IFERROR(VLOOKUP(J26,Tabla11[],4,0),0)-AB26-Z26 -> 151456.47 | AD26: =AA26-AB26 -> 213969.51 | AE26: =ROUND(AD26-AC26,9) -> 62513.046
A27: Vendedor 1/2 2 días | B27: Outsourcing | C27: 1 | E27: Outsourcing | G27: 2 | H27: Supervisor Regiones | I27: Concepción | J27: Ripley | K27: Los Angeles | L27: =IFERROR(VLOOKUP(CONCATENATE(J27,K27),Ventas!D:H,4,0),0) -> 1027076.9 | M27: =IF(SUM(C27,F27)>0,L27*0.1,0) -> 102707.69 | N27: =SUM(L27:M27) -> 1129784.6 | O27: =N27*IFERROR(VLOOKUP(J27,Tabla11[],3,0),0) -> 395424.62 | P27: =N27-O27 -> 734360 | Q27: =IFERROR(G27/SUMIF(I:I,I27,G:G),0)*VLOOKUP(H27,Modelos[],14,0)+IFERROR(G27/SUMIF(I:I,I27,G:G),0)*VLOOKUP(I27,Tabla13[],2,0) -> 70667.45 | R27: =IFERROR(VLOOKUP(A27,Modelos[],IF(B27="EST",15,14),0),0)*C27 -> 154393.47 | S27: =IFERROR(VLOOKUP(D27,Modelos[],IF(E27="EST",15,14),0),0)*F27 -> 0 | T27: =IF($L27<0,0,IFERROR((T$2*IFERROR(VLOOKUP(J27,Tabla11[],2,0),0))*($L27/SUM($L$5:$L$46)),0)) -> 5893.955 | U27: =IF($L27<0,0,IFERROR((U$2*IFERROR(VLOOKUP(J27,Tabla11[],2,0),0))*($L27/SUM($L$5:$L$46)),0)) -> 1146.0468 | V27: =IF($L27<0,0,IFERROR((V$2*IFERROR(VLOOKUP(J27,Tabla11[],2,0),0))*($L27/SUM($L$5:$L$46)),0)) -> 5893.955 | W27: =IF($L27<0,0,IFERROR((W$2*IFERROR(VLOOKUP(J27,Tabla11[],2,0),0))*($L27/SUM($L$5:$L$46)),0)) -> 8186.0486 | X27: =P27*$X$2 -> 293744 | Y27: =+X27*IFERROR(VLOOKUP(J27,Tabla11[],4,0),0) -> 44061.6 | Z27: =IF(L27>0,$Z$2/12,0) -> 25833.333 | AA27: =P27-SUM(Q27:Z27) -> 124540.15 | AB27: =IF($L27<0,0,IFERROR((AB$2*IFERROR(VLOOKUP(J27,Tabla11[],2,0),0))*($L27/SUM($L$5:$L$46)),0)) -> 9401.1511 | AC27: =L27-L27*IFERROR(VLOOKUP(J27,Tabla11[],3,0),0)-Q27-T27-U27-V27-W27-L27*$X$2-(L27*$X$2)*IFERROR(VLOOKUP(J27,Tabla11[],4,0),0)-AB27-Z27 -> 68122.676 | AD27: =AA27-AB27 -> 115138.99 | AE27: =ROUND(AD27-AC27,9) -> 47016.319
B28: Outsourcing | E28: Outsourcing | G28: 3 | H28: Supervisor Santiago | I28: Santiago 02 | J28: Ripley | K28: Maipu | L28: =IFERROR(VLOOKUP(CONCATENATE(J28,K28),Ventas!D:H,4,0),0) -> 977453.85 | M28: =IF(SUM(C28,F28)>0,L28*0.1,0) -> 0 | N28: =SUM(L28:M28) -> 977453.85 | O28: =N28*IFERROR(VLOOKUP(J28,Tabla11[],3,0),0) -> 342108.85 | P28: =N28-O28 -> 635345 | Q28: =IFERROR(G28/SUMIF(I:I,I28,G:G),0)*VLOOKUP(H28,Modelos[],14,0)+IFERROR(G28/SUMIF(I:I,I28,G:G),0)*VLOOKUP(I28,Tabla13[],2,0) -> 69504.988 | R28: =IFERROR(VLOOKUP(A28,Modelos[],IF(B28="EST",15,14),0),0)*C28 -> 0 | S28: =IFERROR(VLOOKUP(D28,Modelos[],IF(E28="EST",15,14),0),0)*F28 -> 0 | T28: =IF($L28<0,0,IFERROR((T$2*IFERROR(VLOOKUP(J28,Tabla11[],2,0),0))*($L28/SUM($L$5:$L$46)),0)) -> 5609.1894 | U28: =IF($L28<0,0,IFERROR((U$2*IFERROR(VLOOKUP(J28,Tabla11[],2,0),0))*($L28/SUM($L$5:$L$46)),0)) -> 1090.6757 | V28: =IF($L28<0,0,IFERROR((V$2*IFERROR(VLOOKUP(J28,Tabla11[],2,0),0))*($L28/SUM($L$5:$L$46)),0)) -> 5609.1894 | W28: =IF($L28<0,0,IFERROR((W$2*IFERROR(VLOOKUP(J28,Tabla11[],2,0),0))*($L28/SUM($L$5:$L$46)),0)) -> 7790.5408 | X28: =P28*$X$2 -> 254138 | Y28: =+X28*IFERROR(VLOOKUP(J28,Tabla11[],4,0),0) -> 38120.7 | Z28: =IF(L28>0,$Z$2/12,0) -> 25833.333 | AA28: =P28-SUM(Q28:Z28) -> 227648.38 | AB28: =IF($L28<0,0,IFERROR((AB$2*IFERROR(VLOOKUP(J28,Tabla11[],2,0),0))*($L28/SUM($L$5:$L$46)),0)) -> 8946.9359 | AC28: =L28-L28*IFERROR(VLOOKUP(J28,Tabla11[],3,0),0)-Q28-T28-U28-V28-W28-L28*$X$2-(L28*$X$2)*IFERROR(VLOOKUP(J28,Tabla11[],4,0),0)-AB28-Z28 -> 61331.379 | AD28: =AA28-AB28 -> 218701.45 | AE28: =ROUND(AD28-AC28,9) -> 157370.07
B29: Outsourcing | E29: Outsourcing | G29: 3 | H29: Supervisor Santiago | I29: Santiago 03 | J29: Ripley | K29: Nueva Alameda | L29: =IFERROR(VLOOKUP(CONCATENATE(J29,K29),Ventas!D:H,4,0),0) -> 965001.54 | M29: =IF(SUM(C29,F29)>0,L29*0.1,0) -> 0 | N29: =SUM(L29:M29) -> 965001.54 | O29: =N29*IFERROR(VLOOKUP(J29,Tabla11[],3,0),0) -> 337750.54 | P29: =N29-O29 -> 627251 | Q29: =IFERROR(G29/SUMIF(I:I,I29,G:G),0)*VLOOKUP(H29,Modelos[],14,0)+IFERROR(G29/SUMIF(I:I,I29,G:G),0)*VLOOKUP(I29,Tabla13[],2,0) -> 73262.014 | R29: =IFERROR(VLOOKUP(A29,Modelos[],IF(B29="EST",15,14),0),0)*C29 -> 0 | S29: =IFERROR(VLOOKUP(D29,Modelos[],IF(E29="EST",15,14),0),0)*F29 -> 0 | T29: =IF($L29<0,0,IFERROR((T$2*IFERROR(VLOOKUP(J29,Tabla11[],2,0),0))*($L29/SUM($L$5:$L$46)),0)) -> 5537.7309 | U29: =IF($L29<0,0,IFERROR((U$2*IFERROR(VLOOKUP(J29,Tabla11[],2,0),0))*($L29/SUM($L$5:$L$46)),0)) -> 1076.781 | V29: =IF($L29<0,0,IFERROR((V$2*IFERROR(VLOOKUP(J29,Tabla11[],2,0),0))*($L29/SUM($L$5:$L$46)),0)) -> 5537.7309 | W29: =IF($L29<0,0,IFERROR((W$2*IFERROR(VLOOKUP(J29,Tabla11[],2,0),0))*($L29/SUM($L$5:$L$46)),0)) -> 7691.2929 | X29: =P29*$X$2 -> 250900.4 | Y29: =+X29*IFERROR(VLOOKUP(J29,Tabla11[],4,0),0) -> 37635.06 | Z29: =IF(L29>0,$Z$2/12,0) -> 25833.333 | AA29: =P29-SUM(Q29:Z29) -> 219776.66 | AB29: =IF($L29<0,0,IFERROR((AB$2*IFERROR(VLOOKUP(J29,Tabla11[],2,0),0))*($L29/SUM($L$5:$L$46)),0)) -> 8832.956 | AC29: =L29-L29*IFERROR(VLOOKUP(J29,Tabla11[],3,0),0)-Q29-T29-U29-V29-W29-L29*$X$2-(L29*$X$2)*IFERROR(VLOOKUP(J29,Tabla11[],4,0),0)-AB29-Z29 -> 55578.453 | AD29: =AA29-AB29 -> 210943.7 | AE29: =ROUND(AD29-AC29,9) -> 155365.25
B30: Outsourcing | E30: Outsourcing | G30: 3 | H30: Supervisor Regiones | I30: Viña del Mar | J30: Ripley | K30: Valparaiso | L30: =IFERROR(VLOOKUP(CONCATENATE(J30,K30),Ventas!D:H,4,0),0) -> 928841.54 | M30: =IF(SUM(C30,F30)>0,L30*0.1,0) -> 0 | N30: =SUM(L30:M30) -> 928841.54 | O30: =N30*IFERROR(VLOOKUP(J30,Tabla11[],3,0),0) -> 325094.54 | P30: =N30-O30 -> 603747 | Q30: =IFERROR(G30/SUMIF(I:I,I30,G:G),0)*VLOOKUP(H30,Modelos[],14,0)+IFERROR(G30/SUMIF(I:I,I30,G:G),0)*VLOOKUP(I30,Tabla13[],2,0) -> 123633.06 | R30: =IFERROR(VLOOKUP(A30,Modelos[],IF(B30="EST",15,14),0),0)*C30 -> 0 | S30: =IFERROR(VLOOKUP(D30,Modelos[],IF(E30="EST",15,14),0),0)*F30 -> 0 | T30: =IF($L30<0,0,IFERROR((T$2*IFERROR(VLOOKUP(J30,Tabla11[],2,0),0))*($L30/SUM($L$5:$L$46)),0)) -> 5330.2241 | U30: =IF($L30<0,0,IFERROR((U$2*IFERROR(VLOOKUP(J30,Tabla11[],2,0),0))*($L30/SUM($L$5:$L$46)),0)) -> 1036.4325 | V30: =IF($L30<0,0,IFERROR((V$2*IFERROR(VLOOKUP(J30,Tabla11[],2,0),0))*($L30/SUM($L$5:$L$46)),0)) -> 5330.2241 | W30: =IF($L30<0,0,IFERROR((W$2*IFERROR(VLOOKUP(J30,Tabla11[],2,0),0))*($L30/SUM($L$5:$L$46)),0)) -> 7403.0891 | X30: =P30*$X$2 -> 241498.8 | Y30: =+X30*IFERROR(VLOOKUP(J30,Tabla11[],4,0),0) -> 36224.82 | Z30: =IF(L30>0,$Z$2/12,0) -> 25833.333 | AA30: =P30-SUM(Q30:Z30) -> 157457.01 | AB30: =IF($L30<0,0,IFERROR((AB$2*IFERROR(VLOOKUP(J30,Tabla11[],2,0),0))*($L30/SUM($L$5:$L$46)),0)) -> 8501.9724 | AC30: =L30-L30*IFERROR(VLOOKUP(J30,Tabla11[],3,0),0)-Q30-T30-U30-V30-W30-L30*$X$2-(L30*$X$2)*IFERROR(VLOOKUP(J30,Tabla11[],4,0),0)-AB30-Z30 -> -588.4458 | AD30: =AA30-AB30 -> 148955.04 | AE30: =ROUND(AD30-AC30,9) -> 149543.49
B31: Outsourcing | E31: Outsourcing | G31: 3 | H31: Supervisor Santiago | I31: Santiago 01 | J31: Ripley | K31: Parque Arauco | L31: =IFERROR(VLOOKUP(CONCATENATE(J31,K31),Ventas!D:H,4,0),0) -> 877984.62 | M31: =IF(SUM(C31,F31)>0,L31*0.1,0) -> 0 | N31: =SUM(L31:M31) -> 877984.62 | O31: =N31*IFERROR(VLOOKUP(J31,Tabla11[],3,0),0) -> 307294.62 | P31: =N31-O31 -> 570690 | Q31: =IFERROR(G31/SUMIF(I:I,I31,G:G),0)*VLOOKUP(H31,Modelos[],14,0)+IFERROR(G31/SUMIF(I:I,I31,G:G),0)*VLOOKUP(I31,Tabla13[],2,0) -> 69504.988 | R31: =IFERROR(VLOOKUP(A31,Modelos[],IF(B31="EST",15,14),0),0)*C31 -> 0 | S31: =IFERROR(VLOOKUP(D31,Modelos[],IF(E31="EST",15,14),0),0)*F31 -> 0 | T31: =IF($L31<0,0,IFERROR((T$2*IFERROR(VLOOKUP(J31,Tabla11[],2,0),0))*($L31/SUM($L$5:$L$46)),0)) -> 5038.378 | U31: =IF($L31<0,0,IFERROR((U$2*IFERROR(VLOOKUP(J31,Tabla11[],2,0),0))*($L31/SUM($L$5:$L$46)),0)) -> 979.68461 | V31: =IF($L31<0,0,IFERROR((V$2*IFERROR(VLOOKUP(J31,Tabla11[],2,0),0))*($L31/SUM($L$5:$L$46)),0)) -> 5038.378 | W31: =IF($L31<0,0,IFERROR((W$2*IFERROR(VLOOKUP(J31,Tabla11[],2,0),0))*($L31/SUM($L$5:$L$46)),0)) -> 6997.7472 | X31: =P31*$X$2 -> 228276 | Y31: =+X31*IFERROR(VLOOKUP(J31,Tabla11[],4,0),0) -> 34241.4 | Z31: =IF(L31>0,$Z$2/12,0) -> 25833.333 | AA31: =P31-SUM(Q31:Z31) -> 194780.09 | AB31: =IF($L31<0,0,IFERROR((AB$2*IFERROR(VLOOKUP(J31,Tabla11[],2,0),0))*($L31/SUM($L$5:$L$46)),0)) -> 8036.4634 | AC31: =L31-L31*IFERROR(VLOOKUP(J31,Tabla11[],3,0),0)-Q31-T31-U31-V31-W31-L31*$X$2-(L31*$X$2)*IFERROR(VLOOKUP(J31,Tabla11[],4,0),0)-AB31-Z31 -> 45388.105 | AD31: =AA31-AB31 -> 186743.63 | AE31: =ROUND(AD31-AC31,9) -> 141355.52
B32: Outsourcing | E32: Outsourcing | G32: 3 | H32: Supervisor Santiago | I32: Santiago 01 | J32: Ripley | K32: Huechuraba | L32: =IFERROR(VLOOKUP(CONCATENATE(J32,K32),Ventas!D:H,4,0),0) -> 850635.38 | M32: =IF(SUM(C32,F32)>0,L32*0.1,0) -> 0 | N32: =SUM(L32:M32) -> 850635.38 | O32: =N32*IFERROR(VLOOKUP(J32,Tabla11[],3,0),0) -> 297722.38 | P32: =N32-O32 -> 552913 | Q32: =IFERROR(G32/SUMIF(I:I,I32,G:G),0)*VLOOKUP(H32,Modelos[],14,0)+IFERROR(G32/SUMIF(I:I,I32,G:G),0)*VLOOKUP(I32,Tabla13[],2,0) -> 69504.988 | R32: =IFERROR(VLOOKUP(A32,Modelos[],IF(B32="EST",15,14),0),0)*C32 -> 0 | S32: =IFERROR(VLOOKUP(D32,Modelos[],IF(E32="EST",15,14),0),0)*F32 -> 0 | T32: =IF($L32<0,0,IFERROR((T$2*IFERROR(VLOOKUP(J32,Tabla11[],2,0),0))*($L32/SUM($L$5:$L$46)),0)) -> 4881.4325 | U32: =IF($L32<0,0,IFERROR((U$2*IFERROR(VLOOKUP(J32,Tabla11[],2,0),0))*($L32/SUM($L$5:$L$46)),0)) -> 949.16743 | V32: =IF($L32<0,0,IFERROR((V$2*IFERROR(VLOOKUP(J32,Tabla11[],2,0),0))*($L32/SUM($L$5:$L$46)),0)) -> 4881.4325 | W32: =IF($L32<0,0,IFERROR((W$2*IFERROR(VLOOKUP(J32,Tabla11[],2,0),0))*($L32/SUM($L$5:$L$46)),0)) -> 6779.7673 | X32: =P32*$X$2 -> 221165.2 | Y32: =+X32*IFERROR(VLOOKUP(J32,Tabla11[],4,0),0) -> 33174.78 | Z32: =IF(L32>0,$Z$2/12,0) -> 25833.333 | AA32: =P32-SUM(Q32:Z32) -> 185742.9 | AB32: =IF($L32<0,0,IFERROR((AB$2*IFERROR(VLOOKUP(J32,Tabla11[],2,0),0))*($L32/SUM($L$5:$L$46)),0)) -> 7786.1274 | AC32: =L32-L32*IFERROR(VLOOKUP(J32,Tabla11[],3,0),0)-Q32-T32-U32-V32-W32-L32*$X$2-(L32*$X$2)*IFERROR(VLOOKUP(J32,Tabla11[],4,0),0)-AB32-Z32 -> 41004.475 | AD32: =AA32-AB32 -> 177956.77 | AE32: =ROUND(AD32-AC32,9) -> 136952.3
B33: Outsourcing | E33: Outsourcing | G33: 3 | H33: Supervisor Part | I33: Copiapó | J33: Ripley | K33: Copiapo | L33: =IFERROR(VLOOKUP(CONCATENATE(J33,K33),Ventas!D:H,4,0),0) -> 827649.23 | M33: =IF(SUM(C33,F33)>0,L33*0.1,0) -> 0 | N33: =SUM(L33:M33) -> 827649.23 | O33: =N33*IFERROR(VLOOKUP(J33,Tabla11[],3,0),0) -> 289677.23 | P33: =N33-O33 -> 537972 | Q33: =IFERROR(G33/SUMIF(I:I,I33,G:G),0)*VLOOKUP(H33,Modelos[],14,0)+IFERROR(G33/SUMIF(I:I,I33,G:G),0)*VLOOKUP(I33,Tabla13[],2,0) -> 128242.75 | R33: =IFERROR(VLOOKUP(A33,Modelos[],IF(B33="EST",15,14),0),0)*C33 -> 0 | S33: =IFERROR(VLOOKUP(D33,Modelos[],IF(E33="EST",15,14),0),0)*F33 -> 0 | T33: =IF($L33<0,0,IFERROR((T$2*IFERROR(VLOOKUP(J33,Tabla11[],2,0),0))*($L33/SUM($L$5:$L$46)),0)) -> 4749.5248 | U33: =IF($L33<0,0,IFERROR((U$2*IFERROR(VLOOKUP(J33,Tabla11[],2,0),0))*($L33/SUM($L$5:$L$46)),0)) -> 923.51871 | V33: =IF($L33<0,0,IFERROR((V$2*IFERROR(VLOOKUP(J33,Tabla11[],2,0),0))*($L33/SUM($L$5:$L$46)),0)) -> 4749.5248 | W33: =IF($L33<0,0,IFERROR((W$2*IFERROR(VLOOKUP(J33,Tabla11[],2,0),0))*($L33/SUM($L$5:$L$46)),0)) -> 6596.5622 | X33: =P33*$X$2 -> 215188.8 | Y33: =+X33*IFERROR(VLOOKUP(J33,Tabla11[],4,0),0) -> 32278.32 | Z33: =IF(L33>0,$Z$2/12,0) -> 25833.333 | AA33: =P33-SUM(Q33:Z33) -> 119409.66 | AB33: =IF($L33<0,0,IFERROR((AB$2*IFERROR(VLOOKUP(J33,Tabla11[],2,0),0))*($L33/SUM($L$5:$L$46)),0)) -> 7575.7281 | AC33: =L33-L33*IFERROR(VLOOKUP(J33,Tabla11[],3,0),0)-Q33-T33-U33-V33-W33-L33*$X$2-(L33*$X$2)*IFERROR(VLOOKUP(J33,Tabla11[],4,0),0)-AB33-Z33 -> -21417.59 | AD33: =AA33-AB33 -> 111833.94 | AE33: =ROUND(AD33-AC33,9) -> 133251.53
B34: Outsourcing | E34: Outsourcing | G34: 3 | H34: Supervisor Regiones | I34: Concepción | J34: Ripley | K34: Concepcion 2 | L34: =IFERROR(VLOOKUP(CONCATENATE(J34,K34),Ventas!D:H,4,0),0) -> 459901.54 | M34: =IF(SUM(C34,F34)>0,L34*0.1,0) -> 0 | N34: =SUM(L34:M34) -> 459901.54 | O34: =N34*IFERROR(VLOOKUP(J34,Tabla11[],3,0),0) -> 160965.54 | P34: =N34-O34 -> 298936 | Q34: =IFERROR(G34/SUMIF(I:I,I34,G:G),0)*VLOOKUP(H34,Modelos[],14,0)+IFERROR(G34/SUMIF(I:I,I34,G:G),0)*VLOOKUP(I34,Tabla13[],2,0) -> 106001.17 | R34: =IFERROR(VLOOKUP(A34,Modelos[],IF(B34="EST",15,14),0),0)*C34 -> 0 | S34: =IFERROR(VLOOKUP(D34,Modelos[],IF(E34="EST",15,14),0),0)*F34 -> 0 | T34: =IF($L34<0,0,IFERROR((T$2*IFERROR(VLOOKUP(J34,Tabla11[],2,0),0))*($L34/SUM($L$5:$L$46)),0)) -> 2639.1781 | U34: =IF($L34<0,0,IFERROR((U$2*IFERROR(VLOOKUP(J34,Tabla11[],2,0),0))*($L34/SUM($L$5:$L$46)),0)) -> 513.17353 | V34: =IF($L34<0,0,IFERROR((V$2*IFERROR(VLOOKUP(J34,Tabla11[],2,0),0))*($L34/SUM($L$5:$L$46)),0)) -> 2639.1781 | W34: =IF($L34<0,0,IFERROR((W$2*IFERROR(VLOOKUP(J34,Tabla11[],2,0),0))*($L34/SUM($L$5:$L$46)),0)) -> 3665.5252 | X34: =P34*$X$2 -> 119574.4 | Y34: =+X34*IFERROR(VLOOKUP(J34,Tabla11[],4,0),0) -> 17936.16 | Z34: =IF(L34>0,$Z$2/12,0) -> 25833.333 | AA34: =P34-SUM(Q34:Z34) -> 20133.877 | AB34: =IF($L34<0,0,IFERROR((AB$2*IFERROR(VLOOKUP(J34,Tabla11[],2,0),0))*($L34/SUM($L$5:$L$46)),0)) -> 4209.6203 | AC34: =L34-L34*IFERROR(VLOOKUP(J34,Tabla11[],3,0),0)-Q34-T34-U34-V34-W34-L34*$X$2-(L34*$X$2)*IFERROR(VLOOKUP(J34,Tabla11[],4,0),0)-AB34-Z34 -> -58119.891 | AD34: =AA34-AB34 -> 15924.257 | AE34: =ROUND(AD34-AC34,9) -> 74044.148
B35: Outsourcing | E35: Outsourcing | G35: 3 | H35: Supervisor Regiones | I35: Viña del Mar | J35: Ripley | K35: Quilpue | L35: =IFERROR(VLOOKUP(CONCATENATE(J35,K35),Ventas!D:H,4,0),0) -> 375944.62 | M35: =IF(SUM(C35,F35)>0,L35*0.1,0) -> 0 | N35: =SUM(L35:M35) -> 375944.62 | O35: =N35*IFERROR(VLOOKUP(J35,Tabla11[],3,0),0) -> 131580.62 | P35: =N35-O35 -> 244364 | Q35: =IFERROR(G35/SUMIF(I:I,I35,G:G),0)*VLOOKUP(H35,Modelos[],14,0)+IFERROR(G35/SUMIF(I:I,I35,G:G),0)*VLOOKUP(I35,Tabla13[],2,0) -> 123633.06 | R35: =IFERROR(VLOOKUP(A35,Modelos[],IF(B35="EST",15,14),0),0)*C35 -> 0 | S35: =IFERROR(VLOOKUP(D35,Modelos[],IF(E35="EST",15,14),0),0)*F35 -> 0 | T35: =IF($L35<0,0,IFERROR((T$2*IFERROR(VLOOKUP(J35,Tabla11[],2,0),0))*($L35/SUM($L$5:$L$46)),0)) -> 2157.3853 | U35: =IF($L35<0,0,IFERROR((U$2*IFERROR(VLOOKUP(J35,Tabla11[],2,0),0))*($L35/SUM($L$5:$L$46)),0)) -> 419.49158 | V35: =IF($L35<0,0,IFERROR((V$2*IFERROR(VLOOKUP(J35,Tabla11[],2,0),0))*($L35/SUM($L$5:$L$46)),0)) -> 2157.3853 | W35: =IF($L35<0,0,IFERROR((W$2*IFERROR(VLOOKUP(J35,Tabla11[],2,0),0))*($L35/SUM($L$5:$L$46)),0)) -> 2996.3684 | X35: =P35*$X$2 -> 97745.6 | Y35: =+X35*IFERROR(VLOOKUP(J35,Tabla11[],4,0),0) -> 14661.84 | Z35: =IF(L35>0,$Z$2/12,0) -> 25833.333 | AA35: =P35-SUM(Q35:Z35) -> -25240.466 | AB35: =IF($L35<0,0,IFERROR((AB$2*IFERROR(VLOOKUP(J35,Tabla11[],2,0),0))*($L35/SUM($L$5:$L$46)),0)) -> 3441.1368 | AC35: =L35-L35*IFERROR(VLOOKUP(J35,Tabla11[],3,0),0)-Q35-T35-U35-V35-W35-L35*$X$2-(L35*$X$2)*IFERROR(VLOOKUP(J35,Tabla11[],4,0),0)-AB35-Z35 -> -89208.686 | AD35: =AA35-AB35 -> -28681.603 | AE35: =ROUND(AD35-AC35,9) -> 60527.083
B36: Outsourcing | E36: Outsourcing | G36: 0 | H36: Supervisor Santiago | I36: Santiago 02 | J36: Ripley | K36: Plaza Tobalaba | L36: =IFERROR(VLOOKUP(CONCATENATE(J36,K36),Ventas!D:H,4,0),0) -> 61570.769 | M36: =IF(SUM(C36,F36)>0,L36*0.1,0) -> 0 | N36: =SUM(L36:M36) -> 61570.769 | O36: =N36*IFERROR(VLOOKUP(J36,Tabla11[],3,0),0) -> 21549.769 | P36: =N36-O36 -> 40021 | Q36: =IFERROR(G36/SUMIF(I:I,I36,G:G),0)*VLOOKUP(H36,Modelos[],14,0)+IFERROR(G36/SUMIF(I:I,I36,G:G),0)*VLOOKUP(I36,Tabla13[],2,0) -> 0 | R36: =IFERROR(VLOOKUP(A36,Modelos[],IF(B36="EST",15,14),0),0)*C36 -> 0 | S36: =IFERROR(VLOOKUP(D36,Modelos[],IF(E36="EST",15,14),0),0)*F36 -> 0 | T36: =IF($L36<0,0,IFERROR((T$2*IFERROR(VLOOKUP(J36,Tabla11[],2,0),0))*($L36/SUM($L$5:$L$46)),0)) -> 353.3283 | U36: =IF($L36<0,0,IFERROR((U$2*IFERROR(VLOOKUP(J36,Tabla11[],2,0),0))*($L36/SUM($L$5:$L$46)),0)) -> 68.702725 | V36: =IF($L36<0,0,IFERROR((V$2*IFERROR(VLOOKUP(J36,Tabla11[],2,0),0))*($L36/SUM($L$5:$L$46)),0)) -> 353.3283 | W36: =IF($L36<0,0,IFERROR((W$2*IFERROR(VLOOKUP(J36,Tabla11[],2,0),0))*($L36/SUM($L$5:$L$46)),0)) -> 490.73375 | X36: =P36*$X$2 -> 16008.4 | Y36: =+X36*IFERROR(VLOOKUP(J36,Tabla11[],4,0),0) -> 2401.26 | Z36: =IF(L36>0,$Z$2/12,0) -> 25833.333 | AA36: =P36-SUM(Q36:Z36) -> -5488.0864 | AB36: =IF($L36<0,0,IFERROR((AB$2*IFERROR(VLOOKUP(J36,Tabla11[],2,0),0))*($L36/SUM($L$5:$L$46)),0)) -> 563.5762 | AC36: =L36-L36*IFERROR(VLOOKUP(J36,Tabla11[],3,0),0)-Q36-T36-U36-V36-W36-L36*$X$2-(L36*$X$2)*IFERROR(VLOOKUP(J36,Tabla11[],4,0),0)-AB36-Z36 -> -15964.556 | AD36: =AA36-AB36 -> -6051.6626 | AE36: =ROUND(AD36-AC36,9) -> 9912.8938
B37: Outsourcing | E37: Outsourcing | G37: 0 | H37: Supervisor Santiago | I37: Santiago 01 | J37: Ripley | K37: Alto las Condes | L37: =IFERROR(VLOOKUP(CONCATENATE(J37,K37),Ventas!D:H,4,0),0) -> 27861.538 | M37: =IF(SUM(C37,F37)>0,L37*0.1,0) -> 0 | N37: =SUM(L37:M37) -> 27861.538 | O37: =N37*IFERROR(VLOOKUP(J37,Tabla11[],3,0),0) -> 9751.5385 | P37: =N37-O37 -> 18110 | Q37: =IFERROR(G37/SUMIF(I:I,I37,G:G),0)*VLOOKUP(H37,Modelos[],14,0)+IFERROR(G37/SUMIF(I:I,I37,G:G),0)*VLOOKUP(I37,Tabla13[],2,0) -> 0 | R37: =IFERROR(VLOOKUP(A37,Modelos[],IF(B37="EST",15,14),0),0)*C37 -> 0 | S37: =IFERROR(VLOOKUP(D37,Modelos[],IF(E37="EST",15,14),0),0)*F37 -> 0 | T37: =IF($L37<0,0,IFERROR((T$2*IFERROR(VLOOKUP(J37,Tabla11[],2,0),0))*($L37/SUM($L$5:$L$46)),0)) -> 159.88545 | U37: =IF($L37<0,0,IFERROR((U$2*IFERROR(VLOOKUP(J37,Tabla11[],2,0),0))*($L37/SUM($L$5:$L$46)),0)) -> 31.088837 | V37: =IF($L37<0,0,IFERROR((V$2*IFERROR(VLOOKUP(J37,Tabla11[],2,0),0))*($L37/SUM($L$5:$L$46)),0)) -> 159.88545 | W37: =IF($L37<0,0,IFERROR((W$2*IFERROR(VLOOKUP(J37,Tabla11[],2,0),0))*($L37/SUM($L$5:$L$46)),0)) -> 222.06312 | X37: =P37*$X$2 -> 7244 | Y37: =+X37*IFERROR(VLOOKUP(J37,Tabla11[],4,0),0) -> 1086.6 | Z37: =IF(L37>0,$Z$2/12,0) -> 25833.333 | AA37: =P37-SUM(Q37:Z37) -> -16626.856 | AB37: =IF($L37<0,0,IFERROR((AB$2*IFERROR(VLOOKUP(J37,Tabla11[],2,0),0))*($L37/SUM($L$5:$L$46)),0)) -> 255.02524 | AC37: =L37-L37*IFERROR(VLOOKUP(J37,Tabla11[],3,0),0)-Q37-T37-U37-V37-W37-L37*$X$2-(L37*$X$2)*IFERROR(VLOOKUP(J37,Tabla11[],4,0),0)-AB37-Z37 -> -21367.589 | AD37: =AA37-AB37 -> -16881.881 | AE37: =ROUND(AD37-AC37,9) -> 4485.7077
A38: Vendedor 1/2 2 días | B38: Outsourcing | C38: 1 | E38: Outsourcing | G38: 3 | H38: Supervisor Regiones | I38: La Serena | J38: Ripley | K38: Coquimbo | L38: 1000000 | M38: =IF(SUM(C38,F38)>0,L38*0.1,0) -> 100000 | N38: =SUM(L38:M38) -> 1100000 | O38: =N38*IFERROR(VLOOKUP(J38,Tabla11[],3,0),0) -> 385000 | P38: =N38-O38 -> 715000 | Q38: =IFERROR(G38/SUMIF(I:I,I38,G:G),0)*VLOOKUP(H38,Modelos[],14,0)+IFERROR(G38/SUMIF(I:I,I38,G:G),0)*VLOOKUP(I38,Tabla13[],2,0) -> 161601.88 | R38: =IFERROR(VLOOKUP(A38,Modelos[],IF(B38="EST",15,14),0),0)*C38 -> 154393.47 | S38: =IFERROR(VLOOKUP(D38,Modelos[],IF(E38="EST",15,14),0),0)*F38 -> 0 | T38: =IF($L38<0,0,IFERROR((T$2*IFERROR(VLOOKUP(J38,Tabla11[],2,0),0))*($L38/SUM($L$5:$L$46)),0)) -> 5738.5721 | U38: =IF($L38<0,0,IFERROR((U$2*IFERROR(VLOOKUP(J38,Tabla11[],2,0),0))*($L38/SUM($L$5:$L$46)),0)) -> 1115.8335 | V38: =IF($L38<0,0,IFERROR((V$2*IFERROR(VLOOKUP(J38,Tabla11[],2,0),0))*($L38/SUM($L$5:$L$46)),0)) -> 5738.5721 | W38: =IF($L38<0,0,IFERROR((W$2*IFERROR(VLOOKUP(J38,Tabla11[],2,0),0))*($L38/SUM($L$5:$L$46)),0)) -> 7970.239 | X38: =P38*$X$2 -> 286000 | Y38: =+X38*IFERROR(VLOOKUP(J38,Tabla11[],4,0),0) -> 42900 | Z38: =IF(L38>0,$Z$2/12,0) -> 25833.333 | AA38: =P38-SUM(Q38:Z38) -> 23708.105 | AB38: =IF($L38<0,0,IFERROR((AB$2*IFERROR(VLOOKUP(J38,Tabla11[],2,0),0))*($L38/SUM($L$5:$L$46)),0)) -> 9153.3077 | AC38: =L38-L38*IFERROR(VLOOKUP(J38,Tabla11[],3,0),0)-Q38-T38-U38-V38-W38-L38*$X$2-(L38*$X$2)*IFERROR(VLOOKUP(J38,Tabla11[],4,0),0)-AB38-Z38 -> -27151.737 | AD38: =AA38-AB38 -> 14554.797 | AE38: =ROUND(AD38-AC38,9) -> 41706.534
A39: Vendedor 1/2 3 días | B39: Outsourcing | C39: 1 | E39: Outsourcing | G39: 3 | H39: Supervisor Part | I39: Arica | J39: Ripley | K39: Arica | L39: 1000000 | M39: =IF(SUM(C39,F39)>0,L39*0.1,0) -> 100000 | N39: =SUM(L39:M39) -> 1100000 | O39: =N39*IFERROR(VLOOKUP(J39,Tabla11[],3,0),0) -> 385000 | P39: =N39-O39 -> 715000 | Q39: =IFERROR(G39/SUMIF(I:I,I39,G:G),0)*VLOOKUP(H39,Modelos[],14,0)+IFERROR(G39/SUMIF(I:I,I39,G:G),0)*VLOOKUP(I39,Tabla13[],2,0) -> 121576.09 | R39: =IFERROR(VLOOKUP(A39,Modelos[],IF(B39="EST",15,14),0),0)*C39 -> 204526.8 | S39: =IFERROR(VLOOKUP(D39,Modelos[],IF(E39="EST",15,14),0),0)*F39 -> 0 | T39: =IF($L39<0,0,IFERROR((T$2*IFERROR(VLOOKUP(J39,Tabla11[],2,0),0))*($L39/SUM($L$5:$L$46)),0)) -> 5738.5721 | U39: =IF($L39<0,0,IFERROR((U$2*IFERROR(VLOOKUP(J39,Tabla11[],2,0),0))*($L39/SUM($L$5:$L$46)),0)) -> 1115.8335 | V39: =IF($L39<0,0,IFERROR((V$2*IFERROR(VLOOKUP(J39,Tabla11[],2,0),0))*($L39/SUM($L$5:$L$46)),0)) -> 5738.5721 | W39: =IF($L39<0,0,IFERROR((W$2*IFERROR(VLOOKUP(J39,Tabla11[],2,0),0))*($L39/SUM($L$5:$L$46)),0)) -> 7970.239 | X39: =P39*$X$2 -> 286000 | Y39: =+X39*IFERROR(VLOOKUP(J39,Tabla11[],4,0),0) -> 42900 | Z39: =IF(L39>0,$Z$2/12,0) -> 25833.333 | AA39: =P39-SUM(Q39:Z39) -> 13600.564 | AB39: =IF($L39<0,0,IFERROR((AB$2*IFERROR(VLOOKUP(J39,Tabla11[],2,0),0))*($L39/SUM($L$5:$L$46)),0)) -> 9153.3077 | AC39: =L39-L39*IFERROR(VLOOKUP(J39,Tabla11[],3,0),0)-Q39-T39-U39-V39-W39-L39*$X$2-(L39*$X$2)*IFERROR(VLOOKUP(J39,Tabla11[],4,0),0)-AB39-Z39 -> 12874.057 | AD39: =AA39-AB39 -> 4447.2565 | AE39: =ROUND(AD39-AC39,9) -> -8426.8004
B40: Outsourcing | E40: Outsourcing | G40: 3 | H40: Supervisor Santiago | I40: Santiago 01 | J40: Ripley | K40: Los Dominicos | L40: 1000000 | M40: =IF(SUM(C40,F40)>0,L40*0.1,0) -> 0 | N40: =SUM(L40:M40) -> 1000000 | O40: =N40*IFERROR(VLOOKUP(J40,Tabla11[],3,0),0) -> 350000 | P40: =N40-O40 -> 650000 | Q40: =IFERROR(G40/SUMIF(I:I,I40,G:G),0)*VLOOKUP(H40,Modelos[],14,0)+IFERROR(G40/SUMIF(I:I,I40,G:G),0)*VLOOKUP(I40,Tabla13[],2,0) -> 69504.988 | R40: =IFERROR(VLOOKUP(A40,Modelos[],IF(B40="EST",15,14),0),0)*C40 -> 0 | S40: =IFERROR(VLOOKUP(D40,Modelos[],IF(E40="EST",15,14),0),0)*F40 -> 0 | T40: =IF($L40<0,0,IFERROR((T$2*IFERROR(VLOOKUP(J40,Tabla11[],2,0),0))*($L40/SUM($L$5:$L$46)),0)) -> 5738.5721 | U40: =IF($L40<0,0,IFERROR((U$2*IFERROR(VLOOKUP(J40,Tabla11[],2,0),0))*($L40/SUM($L$5:$L$46)),0)) -> 1115.8335 | V40: =IF($L40<0,0,IFERROR((V$2*IFERROR(VLOOKUP(J40,Tabla11[],2,0),0))*($L40/SUM($L$5:$L$46)),0)) -> 5738.5721 | W40: =IF($L40<0,0,IFERROR((W$2*IFERROR(VLOOKUP(J40,Tabla11[],2,0),0))*($L40/SUM($L$5:$L$46)),0)) -> 7970.239 | X40: =P40*$X$2 -> 260000 | Y40: =+X40*IFERROR(VLOOKUP(J40,Tabla11[],4,0),0) -> 39000 | Z40: =IF(L40>0,$Z$2/12,0) -> 25833.333 | AA40: =P40-SUM(Q40:Z40) -> 235098.46 | AB40: =IF($L40<0,0,IFERROR((AB$2*IFERROR(VLOOKUP(J40,Tabla11[],2,0),0))*($L40/SUM($L$5:$L$46)),0)) -> 9153.3077 | AC40: =L40-L40*IFERROR(VLOOKUP(J40,Tabla11[],3,0),0)-Q40-T40-U40-V40-W40-L40*$X$2-(L40*$X$2)*IFERROR(VLOOKUP(J40,Tabla11[],4,0),0)-AB40-Z40 -> 64945.155 | AD40: =AA40-AB40 -> 225945.15 | AE40: =ROUND(AD40-AC40,9) -> 161000
A41: Vendedor Full | B41: Outsourcing | C41: 1 | D41: Vendedor 2 días | E41: Outsourcing | F41: 1 | G41: 2 | H41: Supervisor Santiago | I41: Santiago 01 | J41: París | K41: Costanera Center | L41: =IFERROR(VLOOKUP(CONCATENATE(J41,K41),Ventas!D:H,4,0),0) -> 4567765.4 | M41: =IF(SUM(C41,F41)>0,L41*0.1,0) -> 456776.54 | N41: =SUM(L41:M41) -> 5024541.9 | O41: =N41*IFERROR(VLOOKUP(J41,Tabla11[],3,0),0) -> 1758589.7 | P41: =N41-O41 -> 3265952.2 | Q41: =IFERROR(G41/SUMIF(I:I,I41,G:G),0)*VLOOKUP(H41,Modelos[],14,0)+IFERROR(G41/SUMIF(I:I,I41,G:G),0)*VLOOKUP(I41,Tabla13[],2,0) -> 46336.658 | R41: =IFERROR(VLOOKUP(A41,Modelos[],IF(B41="EST",15,14),0),0)*C41 -> 598680.59 | S41: =IFERROR(VLOOKUP(D41,Modelos[],IF(E41="EST",15,14),0),0)*F41 -> 281148.89 | T41: =IF($L41<0,0,IFERROR((T$2*IFERROR(VLOOKUP(J41,Tabla11[],2,0),0))*($L41/SUM($L$5:$L$46)),0)) -> 43123.71 | U41: =IF($L41<0,0,IFERROR((U$2*IFERROR(VLOOKUP(J41,Tabla11[],2,0),0))*($L41/SUM($L$5:$L$46)),0)) -> 8385.1658 | V41: =IF($L41<0,0,IFERROR((V$2*IFERROR(VLOOKUP(J41,Tabla11[],2,0),0))*($L41/SUM($L$5:$L$46)),0)) -> 43123.71 | W41: =IF($L41<0,0,IFERROR((W$2*IFERROR(VLOOKUP(J41,Tabla11[],2,0),0))*($L41/SUM($L$5:$L$46)),0)) -> 59894.041 | X41: =P41*$X$2 -> 1306380.9 | Y41: =+X41*IFERROR(VLOOKUP(J41,Tabla11[],4,0),0) -> 195957.14 | Z41: =IF(L41>0,$Z$2/12,0) -> 25833.333 | AA41: =P41-SUM(Q41:Z41) -> 657088.12 | AB41: =IF($L41<0,0,IFERROR((AB$2*IFERROR(VLOOKUP(J41,Tabla11[],2,0),0))*($L41/SUM($L$5:$L$46)),0)) -> 68784.46 | AC41: =L41-L41*IFERROR(VLOOKUP(J41,Tabla11[],3,0),0)-Q41-T41-U41-V41-W41-L41*$X$2-(L41*$X$2)*IFERROR(VLOOKUP(J41,Tabla11[],4,0),0)-AB41-Z41 -> 572394.34 | AD41: =AA41-AB41 -> 588303.66 | AE41: =ROUND(AD41-AC41,9) -> 15909.313
A42: Vendedor 1/2 Full | B42: Outsourcing | C42: 1 | E42: Outsourcing | G42: 3 | H42: Supervisor Part | I42: Temuco | J42: París | K42: Temuco Centro | L42: =IFERROR(VLOOKUP(CONCATENATE(J42,K42),Ventas!D:H,4,0),0) -> 3442858.7 | M42: =IF(SUM(C42,F42)>0,L42*0.1,0) -> 344285.87 | N42: =SUM(L42:M42) -> 3787144.5 | O42: =N42*IFERROR(VLOOKUP(J42,Tabla11[],3,0),0) -> 1325500.6 | P42: =N42-O42 -> 2461643.9 | Q42: =IFERROR(G42/SUMIF(I:I,I42,G:G),0)*VLOOKUP(H42,Modelos[],14,0)+IFERROR(G42/SUMIF(I:I,I42,G:G),0)*VLOOKUP(I42,Tabla13[],2,0) -> 65246.163 | R42: =IFERROR(VLOOKUP(A42,Modelos[],IF(B42="EST",15,14),0),0)*C42 -> 310333.79 | S42: =IFERROR(VLOOKUP(D42,Modelos[],IF(E42="EST",15,14),0),0)*F42 -> 0 | T42: =IF($L42<0,0,IFERROR((T$2*IFERROR(VLOOKUP(J42,Tabla11[],2,0),0))*($L42/SUM($L$5:$L$46)),0)) -> 32503.604 | U42: =IF($L42<0,0,IFERROR((U$2*IFERROR(VLOOKUP(J42,Tabla11[],2,0),0))*($L42/SUM($L$5:$L$46)),0)) -> 6320.1452 | V42: =IF($L42<0,0,IFERROR((V$2*IFERROR(VLOOKUP(J42,Tabla11[],2,0),0))*($L42/SUM($L$5:$L$46)),0)) -> 32503.604 | W42: =IF($L42<0,0,IFERROR((W$2*IFERROR(VLOOKUP(J42,Tabla11[],2,0),0))*($L42/SUM($L$5:$L$46)),0)) -> 45143.894 | X42: =P42*$X$2 -> 984657.58 | Y42: =+X42*IFERROR(VLOOKUP(J42,Tabla11[],4,0),0) -> 147698.64 | Z42: =IF(L42>0,$Z$2/12,0) -> 25833.333 | AA42: =P42-SUM(Q42:Z42) -> 811403.2 | AB42: =IF($L42<0,0,IFERROR((AB$2*IFERROR(VLOOKUP(J42,Tabla11[],2,0),0))*($L42/SUM($L$5:$L$46)),0)) -> 51844.864 | AC42: =L42-L42*IFERROR(VLOOKUP(J42,Tabla11[],3,0),0)-Q42-T42-U42-V42-W42-L42*$X$2-(L42*$X$2)*IFERROR(VLOOKUP(J42,Tabla11[],4,0),0)-AB42-Z42 -> 394747.54 | AD42: =AA42-AB42 -> 759558.33 | AE42: =ROUND(AD42-AC42,9) -> 364810.8
A43: Vendedor 1/2 3 días | B43: Outsourcing | C43: 1 | E43: Outsourcing | G43: 1 | H43: Supervisor Regiones | I43: VI-VII | J43: París | K43: Talca | L43: =IFERROR(VLOOKUP(CONCATENATE(J43,K43),Ventas!D:H,4,0),0) -> 3334663.2 | M43: =IF(SUM(C43,F43)>0,L43*0.1,0) -> 333466.32 | N43: =SUM(L43:M43) -> 3668129.5 | O43: =N43*IFERROR(VLOOKUP(J43,Tabla11[],3,0),0) -> 1283845.3 | P43: =N43-O43 -> 2384284.2 | Q43: =IFERROR(G43/SUMIF(I:I,I43,G:G),0)*VLOOKUP(H43,Modelos[],14,0)+IFERROR(G43/SUMIF(I:I,I43,G:G),0)*VLOOKUP(I43,Tabla13[],2,0) -> 51647.612 | R43: =IFERROR(VLOOKUP(A43,Modelos[],IF(B43="EST",15,14),0),0)*C43 -> 204526.8 | S43: =IFERROR(VLOOKUP(D43,Modelos[],IF(E43="EST",15,14),0),0)*F43 -> 0 | T43: =IF($L43<0,0,IFERROR((T$2*IFERROR(VLOOKUP(J43,Tabla11[],2,0),0))*($L43/SUM($L$5:$L$46)),0)) -> 31482.144 | U43: =IF($L43<0,0,IFERROR((U$2*IFERROR(VLOOKUP(J43,Tabla11[],2,0),0))*($L43/SUM($L$5:$L$46)),0)) -> 6121.528 | V43: =IF($L43<0,0,IFERROR((V$2*IFERROR(VLOOKUP(J43,Tabla11[],2,0),0))*($L43/SUM($L$5:$L$46)),0)) -> 31482.144 | W43: =IF($L43<0,0,IFERROR((W$2*IFERROR(VLOOKUP(J43,Tabla11[],2,0),0))*($L43/SUM($L$5:$L$46)),0)) -> 43725.2 | X43: =P43*$X$2 -> 953713.68 | Y43: =+X43*IFERROR(VLOOKUP(J43,Tabla11[],4,0),0) -> 143057.05 | Z43: =IF(L43>0,$Z$2/12,0) -> 25833.333 | AA43: =P43-SUM(Q43:Z43) -> 892694.71 | AB43: =IF($L43<0,0,IFERROR((AB$2*IFERROR(VLOOKUP(J43,Tabla11[],2,0),0))*($L43/SUM($L$5:$L$46)),0)) -> 50215.585 | AC43: =L43-L43*IFERROR(VLOOKUP(J43,Tabla11[],3,0),0)-Q43-T43-U43-V43-W43-L43*$X$2-(L43*$X$2)*IFERROR(VLOOKUP(J43,Tabla11[],4,0),0)-AB43-Z43 -> 393078.46 | AD43: =AA43-AB43 -> 842479.12 | AE43: =ROUND(AD43-AC43,9) -> 449400.66
A44: Vendedor 1/2 3 días | B44: Outsourcing | C44: 1 | E44: Outsourcing | G44: 3 | H44: Supervisor Regiones | I44: Viña del Mar | J44: París | K44: Portal Belloto | L44: =IFERROR(VLOOKUP(CONCATENATE(J44,K44),Ventas!D:H,4,0),0) -> 3341243.1 | M44: =IF(SUM(C44,F44)>0,L44*0.1,0) -> 334124.31 | N44: =SUM(L44:M44) -> 3675367.4 | O44: =N44*IFERROR(VLOOKUP(J44,Tabla11[],3,0),0) -> 1286378.6 | P44: =N44-O44 -> 2388988.8 | Q44: =IFERROR(G44/SUMIF(I:I,I44,G:G),0)*VLOOKUP(H44,Modelos[],14,0)+IFERROR(G44/SUMIF(I:I,I44,G:G),0)*VLOOKUP(I44,Tabla13[],2,0) -> 123633.06 | R44: =IFERROR(VLOOKUP(A44,Modelos[],IF(B44="EST",15,14),0),0)*C44 -> 204526.8 | S44: =IFERROR(VLOOKUP(D44,Modelos[],IF(E44="EST",15,14),0),0)*F44 -> 0 | T44: =IF($L44<0,0,IFERROR((T$2*IFERROR(VLOOKUP(J44,Tabla11[],2,0),0))*($L44/SUM($L$5:$L$46)),0)) -> 31544.264 | U44: =IF($L44<0,0,IFERROR((U$2*IFERROR(VLOOKUP(J44,Tabla11[],2,0),0))*($L44/SUM($L$5:$L$46)),0)) -> 6133.6068 | V44: =IF($L44<0,0,IFERROR((V$2*IFERROR(VLOOKUP(J44,Tabla11[],2,0),0))*($L44/SUM($L$5:$L$46)),0)) -> 31544.264 | W44: =IF($L44<0,0,IFERROR((W$2*IFERROR(VLOOKUP(J44,Tabla11[],2,0),0))*($L44/SUM($L$5:$L$46)),0)) -> 43811.477 | X44: =P44*$X$2 -> 955595.51 | Y44: =+X44*IFERROR(VLOOKUP(J44,Tabla11[],4,0),0) -> 143339.33 | Z44: =IF(L44>0,$Z$2/12,0) -> 25833.333 | AA44: =P44-SUM(Q44:Z44) -> 823027.14 | AB44: =IF($L44<0,0,IFERROR((AB$2*IFERROR(VLOOKUP(J44,Tabla11[],2,0),0))*($L44/SUM($L$5:$L$46)),0)) -> 50314.668 | AC44: =L44-L44*IFERROR(VLOOKUP(J44,Tabla11[],3,0),0)-Q44-T44-U44-V44-W44-L44*$X$2-(L44*$X$2)*IFERROR(VLOOKUP(J44,Tabla11[],4,0),0)-AB44-Z44 -> 322021.5 | AD44: =AA44-AB44 -> 772712.47 | AE44: =ROUND(AD44-AC44,9) -> 450690.96
A45: Vendedor 1/2 Full | B45: Outsourcing | C45: 1 | D45: Vendedor 1/2 3 días | E45: Outsourcing | F45: 1 | G45: 3 | H45: Supervisor Regiones | I45: La Serena | J45: París | K45: Plaza La Serena | L45: =IFERROR(VLOOKUP(CONCATENATE(J45,K45),Ventas!D:H,4,0),0) -> 2567354.6 | M45: =IF(SUM(C45,F45)>0,L45*0.1,0) -> 256735.46 | N45: =SUM(L45:M45) -> 2824090 | O45: =N45*IFERROR(VLOOKUP(J45,Tabla11[],3,0),0) -> 988431.51 | P45: =N45-O45 -> 1835658.5 | Q45: =IFERROR(G45/SUMIF(I:I,I45,G:G),0)*VLOOKUP(H45,Modelos[],14,0)+IFERROR(G45/SUMIF(I:I,I45,G:G),0)*VLOOKUP(I45,Tabla13[],2,0) -> 161601.88 | R45: =IFERROR(VLOOKUP(A45,Modelos[],IF(B45="EST",15,14),0),0)*C45 -> 310333.79 | S45: =IFERROR(VLOOKUP(D45,Modelos[],IF(E45="EST",15,14),0),0)*F45 -> 204526.8 | T45: =IF($L45<0,0,IFERROR((T$2*IFERROR(VLOOKUP(J45,Tabla11[],2,0),0))*($L45/SUM($L$5:$L$46)),0)) -> 24238.078 | U45: =IF($L45<0,0,IFERROR((U$2*IFERROR(VLOOKUP(J45,Tabla11[],2,0),0))*($L45/SUM($L$5:$L$46)),0)) -> 4712.9596 | V45: =IF($L45<0,0,IFERROR((V$2*IFERROR(VLOOKUP(J45,Tabla11[],2,0),0))*($L45/SUM($L$5:$L$46)),0)) -> 24238.078 | W45: =IF($L45<0,0,IFERROR((W$2*IFERROR(VLOOKUP(J45,Tabla11[],2,0),0))*($L45/SUM($L$5:$L$46)),0)) -> 33663.997 | X45: =P45*$X$2 -> 734263.41 | Y45: =+X45*IFERROR(VLOOKUP(J45,Tabla11[],4,0),0) -> 110139.51 | Z45: =IF(L45>0,$Z$2/12,0) -> 25833.333 | AA45: =P45-SUM(Q45:Z45) -> 202106.69 | AB45: =IF($L45<0,0,IFERROR((AB$2*IFERROR(VLOOKUP(J45,Tabla11[],2,0),0))*($L45/SUM($L$5:$L$46)),0)) -> 38660.939 | AC45: =L45-L45*IFERROR(VLOOKUP(J45,Tabla11[],3,0),0)-Q45-T45-U45-V45-W45-L45*$X$2-(L45*$X$2)*IFERROR(VLOOKUP(J45,Tabla11[],4,0),0)-AB45-Z45 -> 174848.11 | AD45: =AA45-AB45 -> 163445.75 | AE45: =ROUND(AD45-AC45,9) -> -11402.357
A46: Vendedor 1/2 Full | B46: Outsourcing | C46: 1 | D46: Vendedor 1/2 3 días | E46: Outsourcing | F46: 1 | G46: 2 | H46: Supervisor Regiones | I46: Viña del Mar | J46: París | K46: Marina Arauco | L46: =IFERROR(VLOOKUP(CONCATENATE(J46,K46),Ventas!D:H,4,0),0) -> 3054985.7 | M46: =IF(SUM(C46,F46)>0,L46*0.1,0) -> 305498.57 | N46: =SUM(L46:M46) -> 3360484.3 | O46: =N46*IFERROR(VLOOKUP(J46,Tabla11[],3,0),0) -> 1176169.5 | P46: =N46-O46 -> 2184314.8 | Q46: =IFERROR(G46/SUMIF(I:I,I46,G:G),0)*VLOOKUP(H46,Modelos[],14,0)+IFERROR(G46/SUMIF(I:I,I46,G:G),0)*VLOOKUP(I46,Tabla13[],2,0) -> 82422.042 | R46: =IFERROR(VLOOKUP(A46,Modelos[],IF(B46="EST",15,14),0),0)*C46 -> 310333.79 | S46: =IFERROR(VLOOKUP(D46,Modelos[],IF(E46="EST",15,14),0),0)*F46 -> 204526.8 | T46: =IF($L46<0,0,IFERROR((T$2*IFERROR(VLOOKUP(J46,Tabla11[],2,0),0))*($L46/SUM($L$5:$L$46)),0)) -> 28841.744 | U46: =IF($L46<0,0,IFERROR((U$2*IFERROR(VLOOKUP(J46,Tabla11[],2,0),0))*($L46/SUM($L$5:$L$46)),0)) -> 5608.1168 | V46: =IF($L46<0,0,IFERROR((V$2*IFERROR(VLOOKUP(J46,Tabla11[],2,0),0))*($L46/SUM($L$5:$L$46)),0)) -> 28841.744 | W46: =IF($L46<0,0,IFERROR((W$2*IFERROR(VLOOKUP(J46,Tabla11[],2,0),0))*($L46/SUM($L$5:$L$46)),0)) -> 40057.977 | X46: =P46*$X$2 -> 873725.92 | Y46: =+X46*IFERROR(VLOOKUP(J46,Tabla11[],4,0),0) -> 131058.89 | Z46: =IF(L46>0,$Z$2/12,0) -> 25833.333 | AA46: =P46-SUM(Q46:Z46) -> 453064.45 | AB46: =IF($L46<0,0,IFERROR((AB$2*IFERROR(VLOOKUP(J46,Tabla11[],2,0),0))*($L46/SUM($L$5:$L$46)),0)) -> 46004.015 | AC46: =L46-L46*IFERROR(VLOOKUP(J46,Tabla11[],3,0),0)-Q46-T46-U46-V46-W46-L46*$X$2-(L46*$X$2)*IFERROR(VLOOKUP(J46,Tabla11[],4,0),0)-AB46-Z46 -> 322838.32 | AD46: =AA46-AB46 -> 407060.43 | AE46: =ROUND(AD46-AC46,9) -> 84222.115
A47: Vendedor 1/2 3 días | B47: Outsourcing | C47: 1 | E47: Outsourcing | G47: 3 | H47: Supervisor Regiones | I47: Concepción | J47: París | K47: Barros Arana | L47: =IFERROR(VLOOKUP(CONCATENATE(J47,K47),Ventas!D:H,4,0),0) -> 1566761.7 | M47: =IF(SUM(C47,F47)>0,L47*0.1,0) -> 156676.17 | N47: =SUM(L47:M47) -> 1723437.8 | O47: =N47*IFERROR(VLOOKUP(J47,Tabla11[],3,0),0) -> 603203.24 | P47: =N47-O47 -> 1120234.6 | Q47: =IFERROR(G47/SUMIF(I:I,I47,G:G),0)*VLOOKUP(H47,Modelos[],14,0)+IFERROR(G47/SUMIF(I:I,I47,G:G),0)*VLOOKUP(I47,Tabla13[],2,0) -> 106001.17 | R47: =IFERROR(VLOOKUP(A47,Modelos[],IF(B47="EST",15,14),0),0)*C47 -> 204526.8 | S47: =IFERROR(VLOOKUP(D47,Modelos[],IF(E47="EST",15,14),0),0)*F47 -> 0 | T47: =IF($L47<0,0,IFERROR((T$2*IFERROR(VLOOKUP(J47,Tabla11[],2,0),0))*($L47/SUM($L$5:$L$46)),0)) -> 14791.604 | U47: =IF($L47<0,0,IFERROR((U$2*IFERROR(VLOOKUP(J47,Tabla11[],2,0),0))*($L47/SUM($L$5:$L$46)),0)) -> 2876.1451 | V47: =IF($L47<0,0,IFERROR((V$2*IFERROR(VLOOKUP(J47,Tabla11[],2,0),0))*($L47/SUM($L$5:$L$46)),0)) -> 14791.604 | W47: =IF($L47<0,0,IFERROR((W$2*IFERROR(VLOOKUP(J47,Tabla11[],2,0),0))*($L47/SUM($L$5:$L$46)),0)) -> 20543.894 | X47: =P47*$X$2 -> 448093.83 | Y47: =+X47*IFERROR(VLOOKUP(J47,Tabla11[],4,0),0) -> 67214.075 | Z47: =IF(L47>0,$Z$2/12,0) -> 25833.333 | AA47: =P47-SUM(Q47:Z47) -> 215562.12 | AB47: =IF($L47<0,0,IFERROR((AB$2*IFERROR(VLOOKUP(J47,Tabla11[],2,0),0))*($L47/SUM($L$5:$L$46)),0)) -> 23593.343 | AC47: =L47-L47*IFERROR(VLOOKUP(J47,Tabla11[],3,0),0)-Q47-T47-U47-V47-W47-L47*$X$2-(L47*$X$2)*IFERROR(VLOOKUP(J47,Tabla11[],4,0),0)-AB47-Z47 -> 89253.618 | AD47: =AA47-AB47 -> 191968.78 | AE47: =ROUND(AD47-AC47,9) -> 102715.16
A48: Vendedor 1/2 3 días | B48: Outsourcing | C48: 1 | E48: Outsourcing | G48: 3 | H48: Supervisor Santiago | I48: Santiago 02 | J48: París | K48: Arauco Maipu | L48: =IFERROR(VLOOKUP(CONCATENATE(J48,K48),Ventas!D:H,4,0),0) -> 1872861.2 | M48: =IF(SUM(C48,F48)>0,L48*0.1,0) -> 187286.12 | N48: =SUM(L48:M48) -> 2060147.4 | O48: =N48*IFERROR(VLOOKUP(J48,Tabla11[],3,0),0) -> 721051.57 | P48: =N48-O48 -> 1339095.8 | Q48: =IFERROR(G48/SUMIF(I:I,I48,G:G),0)*VLOOKUP(H48,Modelos[],14,0)+IFERROR(G48/SUMIF(I:I,I48,G:G),0)*VLOOKUP(I48,Tabla13[],2,0) -> 69504.988 | R48: =IFERROR(VLOOKUP(A48,Modelos[],IF(B48="EST",15,14),0),0)*C48 -> 204526.8 | S48: =IFERROR(VLOOKUP(D48,Modelos[],IF(E48="EST",15,14),0),0)*F48 -> 0 | T48: =IF($L48<0,0,IFERROR((T$2*IFERROR(VLOOKUP(J48,Tabla11[],2,0),0))*($L48/SUM($L$5:$L$46)),0)) -> 17681.452 | U48: =IF($L48<0,0,IFERROR((U$2*IFERROR(VLOOKUP(J48,Tabla11[],2,0),0))*($L48/SUM($L$5:$L$46)),0)) -> 3438.0601 | V48: =IF($L48<0,0,IFERROR((V$2*IFERROR(VLOOKUP(J48,Tabla11[],2,0),0))*($L48/SUM($L$5:$L$46)),0)) -> 17681.452 | W48: =IF($L48<0,0,IFERROR((W$2*IFERROR(VLOOKUP(J48,Tabla11[],2,0),0))*($L48/SUM($L$5:$L$46)),0)) -> 24557.572 | X48: =P48*$X$2 -> 535638.31 | Y48: =+X48*IFERROR(VLOOKUP(J48,Tabla11[],4,0),0) -> 80345.747 | Z48: =IF(L48>0,$Z$2/12,0) -> 25833.333 | AA48: =P48-SUM(Q48:Z48) -> 359888.06 | AB48: =IF($L48<0,0,IFERROR((AB$2*IFERROR(VLOOKUP(J48,Tabla11[],2,0),0))*($L48/SUM($L$5:$L$46)),0)) -> 28202.795 | AC48: =L48-L48*IFERROR(VLOOKUP(J48,Tabla11[],3,0),0)-Q48-T48-U48-V48-W48-L48*$X$2-(L48*$X$2)*IFERROR(VLOOKUP(J48,Tabla11[],4,0),0)-AB48-Z48 -> 168943.98 | AD48: =AA48-AB48 -> 331685.27 | AE48: =ROUND(AD48-AC48,9) -> 162741.29
A49: Vendedor 1/2 3 días | B49: Outsourcing | C49: 1 | E49: Outsourcing | G49: 3 | H49: Supervisor Santiago | I49: Santiago 02 | J49: París | K49: Plaza Oeste | L49: =IFERROR(VLOOKUP(CONCATENATE(J49,K49),Ventas!D:H,4,0),0) -> 2791786.7 | M49: =IF(SUM(C49,F49)>0,L49*0.1,0) -> 279178.67 | N49: =SUM(L49:M49) -> 3070965.4 | O49: =N49*IFERROR(VLOOKUP(J49,Tabla11[],3,0),0) -> 1074837.9 | P49: =N49-O49 -> 1996127.5 | Q49: =IFERROR(G49/SUMIF(I:I,I49,G:G),0)*VLOOKUP(H49,Modelos[],14,0)+IFERROR(G49/SUMIF(I:I,I49,G:G),0)*VLOOKUP(I49,Tabla13[],2,0) -> 69504.988 | R49: =IFERROR(VLOOKUP(A49,Modelos[],IF(B49="EST",15,14),0),0)*C49 -> 204526.8 | S49: =IFERROR(VLOOKUP(D49,Modelos[],IF(E49="EST",15,14),0),0)*F49 -> 0 | T49: =IF($L49<0,0,IFERROR((T$2*IFERROR(VLOOKUP(J49,Tabla11[],2,0),0))*($L49/SUM($L$5:$L$46)),0)) -> 26356.914 | U49: =IF($L49<0,0,IFERROR((U$2*IFERROR(VLOOKUP(J49,Tabla11[],2,0),0))*($L49/SUM($L$5:$L$46)),0)) -> 5124.9555 | V49: =IF($L49<0,0,IFERROR((V$2*IFERROR(VLOOKUP(J49,Tabla11[],2,0),0))*($L49/SUM($L$5:$L$46)),0)) -> 26356.914 | W49: =IF($L49<0,0,IFERROR((W$2*IFERROR(VLOOKUP(J49,Tabla11[],2,0),0))*($L49/SUM($L$5:$L$46)),0)) -> 36606.825 | X49: =P49*$X$2 -> 798451 | Y49: =+X49*IFERROR(VLOOKUP(J49,Tabla11[],4,0),0) -> 119767.65 | Z49: =IF(L49>0,$Z$2/12,0) -> 25833.333 | AA49: =P49-SUM(Q49:Z49) -> 683598.12 | AB49: =IF($L49<0,0,IFERROR((AB$2*IFERROR(VLOOKUP(J49,Tabla11[],2,0),0))*($L49/SUM($L$5:$L$46)),0)) -> 42040.588 | AC49: =L49-L49*IFERROR(VLOOKUP(J49,Tabla11[],3,0),0)-Q49-T49-U49-V49-W49-L49*$X$2-(L49*$X$2)*IFERROR(VLOOKUP(J49,Tabla11[],4,0),0)-AB49-Z49 -> 298614.96 | AD49: =AA49-AB49 -> 641557.53 | AE49: =ROUND(AD49-AC49,9) -> 342942.57
A50: Vendedor 1/2 3 días | B50: Outsourcing | C50: 1 | E50: Outsourcing | G50: 3 | H50: Supervisor Regiones | I50: VI-VII | J50: París | K50: Rancagua | L50: =IFERROR(VLOOKUP(CONCATENATE(J50,K50),Ventas!D:H,4,0),0) -> 1818867 | M50: =IF(SUM(C50,F50)>0,L50*0.1,0) -> 181886.7 | N50: =SUM(L50:M50) -> 2000753.7 | O50: =N50*IFERROR(VLOOKUP(J50,Tabla11[],3,0),0) -> 700263.81 | P50: =N50-O50 -> 1300489.9 | Q50: =IFERROR(G50/SUMIF(I:I,I50,G:G),0)*VLOOKUP(H50,Modelos[],14,0)+IFERROR(G50/SUMIF(I:I,I50,G:G),0)*VLOOKUP(I50,Tabla13[],2,0) -> 154942.83 | R50: =IFERROR(VLOOKUP(A50,Modelos[],IF(B50="EST",15,14),0),0)*C50 -> 204526.8 | S50: =IFERROR(VLOOKUP(D50,Modelos[],IF(E50="EST",15,14),0),0)*F50 -> 0 | T50: =IF($L50<0,0,IFERROR((T$2*IFERROR(VLOOKUP(J50,Tabla11[],2,0),0))*($L50/SUM($L$5:$L$46)),0)) -> 17171.699 | U50: =IF($L50<0,0,IFERROR((U$2*IFERROR(VLOOKUP(J50,Tabla11[],2,0),0))*($L50/SUM($L$5:$L$46)),0)) -> 3338.9416 | V50: =IF($L50<0,0,IFERROR((V$2*IFERROR(VLOOKUP(J50,Tabla11[],2,0),0))*($L50/SUM($L$5:$L$46)),0)) -> 17171.699 | W50: =IF($L50<0,0,IFERROR((W$2*IFERROR(VLOOKUP(J50,Tabla11[],2,0),0))*($L50/SUM($L$5:$L$46)),0)) -> 23849.583 | X50: =P50*$X$2 -> 520195.97 | Y50: =+X50*IFERROR(VLOOKUP(J50,Tabla11[],4,0),0) -> 78029.396 | Z50: =IF(L50>0,$Z$2/12,0) -> 25833.333 | AA50: =P50-SUM(Q50:Z50) -> 255429.67 | AB50: =IF($L50<0,0,IFERROR((AB$2*IFERROR(VLOOKUP(J50,Tabla11[],2,0),0))*($L50/SUM($L$5:$L$46)),0)) -> 27389.714 | AC50: =L50-L50*IFERROR(VLOOKUP(J50,Tabla11[],3,0),0)-Q50-T50-U50-V50-W50-L50*$X$2-(L50*$X$2)*IFERROR(VLOOKUP(J50,Tabla11[],4,0),0)-AB50-Z50 -> 75886.933 | AD50: =AA50-AB50 -> 228039.96 | AE50: =ROUND(AD50-AC50,9) -> 152153.03
A51: Vendedor 1/2 3 días | B51: Outsourcing | C51: 1 | E51: Outsourcing | G51: 3 | H51: Supervisor Santiago | I51: Santiago 01 | J51: París | K51: Parque Arauco | L51: =IFERROR(VLOOKUP(CONCATENATE(J51,K51),Ventas!D:H,4,0),0) -> 3194512.3 | M51: =IF(SUM(C51,F51)>0,L51*0.1,0) -> 319451.23 | N51: =SUM(L51:M51) -> 3513963.5 | O51: =N51*IFERROR(VLOOKUP(J51,Tabla11[],3,0),0) -> 1229887.2 | P51: =N51-O51 -> 2284076.3 | Q51: =IFERROR(G51/SUMIF(I:I,I51,G:G),0)*VLOOKUP(H51,Modelos[],14,0)+IFERROR(G51/SUMIF(I:I,I51,G:G),0)*VLOOKUP(I51,Tabla13[],2,0) -> 69504.988 | R51: =IFERROR(VLOOKUP(A51,Modelos[],IF(B51="EST",15,14),0),0)*C51 -> 204526.8 | S51: =IFERROR(VLOOKUP(D51,Modelos[],IF(E51="EST",15,14),0),0)*F51 -> 0 | T51: =IF($L51<0,0,IFERROR((T$2*IFERROR(VLOOKUP(J51,Tabla11[],2,0),0))*($L51/SUM($L$5:$L$46)),0)) -> 30158.996 | U51: =IF($L51<0,0,IFERROR((U$2*IFERROR(VLOOKUP(J51,Tabla11[],2,0),0))*($L51/SUM($L$5:$L$46)),0)) -> 5864.2493 | V51: =IF($L51<0,0,IFERROR((V$2*IFERROR(VLOOKUP(J51,Tabla11[],2,0),0))*($L51/SUM($L$5:$L$46)),0)) -> 30158.996 | W51: =IF($L51<0,0,IFERROR((W$2*IFERROR(VLOOKUP(J51,Tabla11[],2,0),0))*($L51/SUM($L$5:$L$46)),0)) -> 41887.495 | X51: =P51*$X$2 -> 913630.51 | Y51: =+X51*IFERROR(VLOOKUP(J51,Tabla11[],4,0),0) -> 137044.58 | Z51: =IF(L51>0,$Z$2/12,0) -> 25833.333 | AA51: =P51-SUM(Q51:Z51) -> 825466.33 | AB51: =IF($L51<0,0,IFERROR((AB$2*IFERROR(VLOOKUP(J51,Tabla11[],2,0),0))*($L51/SUM($L$5:$L$46)),0)) -> 48105.098 | AC51: =L51-L51*IFERROR(VLOOKUP(J51,Tabla11[],3,0),0)-Q51-T51-U51-V51-W51-L51*$X$2-(L51*$X$2)*IFERROR(VLOOKUP(J51,Tabla11[],4,0),0)-AB51-Z51 -> 355444.18 | AD51: =AA51-AB51 -> 777361.24 | AE51: =ROUND(AD51-AC51,9) -> 421917.06
B52: Outsourcing | E52: Outsourcing | G52: 3 | H52: Supervisor Part | I52: Copiapó | J52: París | K52: Copiapo | L52: =IFERROR(VLOOKUP(CONCATENATE(J52,K52),Ventas!D:H,4,0),0) -> 2835397.8 | M52: =IF(SUM(C52,F52)>0,L52*0.1,0) -> 0 | N52: =SUM(L52:M52) -> 2835397.8 | O52: =N52*IFERROR(VLOOKUP(J52,Tabla11[],3,0),0) -> 992389.23 | P52: =N52-O52 -> 1843008.6 | Q52: =IFERROR(G52/SUMIF(I:I,I52,G:G),0)*VLOOKUP(H52,Modelos[],14,0)+IFERROR(G52/SUMIF(I:I,I52,G:G),0)*VLOOKUP(I52,Tabla13[],2,0) -> 128242.75 | R52: =IFERROR(VLOOKUP(A52,Modelos[],IF(B52="EST",15,14),0),0)*C52 -> 0 | S52: =IFERROR(VLOOKUP(D52,Modelos[],IF(E52="EST",15,14),0),0)*F52 -> 0 | T52: =IF($L52<0,0,IFERROR((T$2*IFERROR(VLOOKUP(J52,Tabla11[],2,0),0))*($L52/SUM($L$5:$L$46)),0)) -> 26768.641 | U52: =IF($L52<0,0,IFERROR((U$2*IFERROR(VLOOKUP(J52,Tabla11[],2,0),0))*($L52/SUM($L$5:$L$46)),0)) -> 5205.0135 | V52: =IF($L52<0,0,IFERROR((V$2*IFERROR(VLOOKUP(J52,Tabla11[],2,0),0))*($L52/SUM($L$5:$L$46)),0)) -> 26768.641 | W52: =IF($L52<0,0,IFERROR((W$2*IFERROR(VLOOKUP(J52,Tabla11[],2,0),0))*($L52/SUM($L$5:$L$46)),0)) -> 37178.668 | X52: =P52*$X$2 -> 737203.43 | Y52: =+X52*IFERROR(VLOOKUP(J52,Tabla11[],4,0),0) -> 110580.51 | Z52: =IF(L52>0,$Z$2/12,0) -> 25833.333 | AA52: =P52-SUM(Q52:Z52) -> 745227.58 | AB52: =IF($L52<0,0,IFERROR((AB$2*IFERROR(VLOOKUP(J52,Tabla11[],2,0),0))*($L52/SUM($L$5:$L$46)),0)) -> 42697.313 | AC52: =L52-L52*IFERROR(VLOOKUP(J52,Tabla11[],3,0),0)-Q52-T52-U52-V52-W52-L52*$X$2-(L52*$X$2)*IFERROR(VLOOKUP(J52,Tabla11[],4,0),0)-AB52-Z52 -> 246031.22 | AD52: =AA52-AB52 -> 702530.26 | AE52: =ROUND(AD52-AC52,9) -> 456499.04
A53: Vendedor 1/2 3 días | B53: Outsourcing | C53: 0.67 | E53: Outsourcing | G53: 0 | H53: Supervisor Regiones | I53: Concepción | J53: París | K53: El Roble | L53: =IFERROR(VLOOKUP(CONCATENATE(J53,K53),Ventas!D:H,4,0),0) -> 1776096.1 | M53: =IF(SUM(C53,F53)>0,L53*0.1,0) -> 177609.61 | N53: =SUM(L53:M53) -> 1953705.7 | O53: =N53*IFERROR(VLOOKUP(J53,Tabla11[],3,0),0) -> 683797.01 | P53: =N53-O53 -> 1269908.7 | Q53: =IFERROR(G53/SUMIF(I:I,I53,G:G),0)*VLOOKUP(H53,Modelos[],14,0)+IFERROR(G53/SUMIF(I:I,I53,G:G),0)*VLOOKUP(I53,Tabla13[],2,0) -> 0 | R53: =IFERROR(VLOOKUP(A53,Modelos[],IF(B53="EST",15,14),0),0)*C53 -> 137032.96 | S53: =IFERROR(VLOOKUP(D53,Modelos[],IF(E53="EST",15,14),0),0)*F53 -> 0 | T53: =IF($L53<0,0,IFERROR((T$2*IFERROR(VLOOKUP(J53,Tabla11[],2,0),0))*($L53/SUM($L$5:$L$46)),0)) -> 16767.904 | U53: =IF($L53<0,0,IFERROR((U$2*IFERROR(VLOOKUP(J53,Tabla11[],2,0),0))*($L53/SUM($L$5:$L$46)),0)) -> 3260.4259 | V53: =IF($L53<0,0,IFERROR((V$2*IFERROR(VLOOKUP(J53,Tabla11[],2,0),0))*($L53/SUM($L$5:$L$46)),0)) -> 16767.904 | W53: =IF($L53<0,0,IFERROR((W$2*IFERROR(VLOOKUP(J53,Tabla11[],2,0),0))*($L53/SUM($L$5:$L$46)),0)) -> 23288.756 | X53: =P53*$X$2 -> 507963.49 | Y53: =+X53*IFERROR(VLOOKUP(J53,Tabla11[],4,0),0) -> 76194.524 | Z53: =IF(L53>0,$Z$2/12,0) -> 25833.333 | AA53: =P53-SUM(Q53:Z53) -> 462799.43 | AB53: =IF($L53<0,0,IFERROR((AB$2*IFERROR(VLOOKUP(J53,Tabla11[],2,0),0))*($L53/SUM($L$5:$L$46)),0)) -> 26745.641 | AC53: =L53-L53*IFERROR(VLOOKUP(J53,Tabla11[],3,0),0)-Q53-T53-U53-V53-W53-L53*$X$2-(L53*$X$2)*IFERROR(VLOOKUP(J53,Tabla11[],4,0),0)-AB53-Z53 -> 224794.3 | AD53: =AA53-AB53 -> 436053.79 | AE53: =ROUND(AD53-AC53,9) -> 211259.49
A54: Vendedor 1/2 2 días | B54: Outsourcing | C54: 1 | E54: Outsourcing | G54: 0 | H54: Supervisor Regiones | I54: Puerto Montt | J54: París | K54: Portal Osorno | L54: =IFERROR(VLOOKUP(CONCATENATE(J54,K54),Ventas!D:H,4,0),0) -> 604188.74 | M54: =IF(SUM(C54,F54)>0,L54*0.1,0) -> 60418.874 | N54: =SUM(L54:M54) -> 664607.61 | O54: =N54*IFERROR(VLOOKUP(J54,Tabla11[],3,0),0) -> 232612.66 | P54: =N54-O54 -> 431994.95 | Q54: =IFERROR(G54/SUMIF(I:I,I54,G:G),0)*VLOOKUP(H54,Modelos[],14,0)+IFERROR(G54/SUMIF(I:I,I54,G:G),0)*VLOOKUP(I54,Tabla13[],2,0) -> 0 | R54: =IFERROR(VLOOKUP(A54,Modelos[],IF(B54="EST",15,14),0),0)*C54 -> 154393.47 | S54: =IFERROR(VLOOKUP(D54,Modelos[],IF(E54="EST",15,14),0),0)*F54 -> 0 | T54: =IF($L54<0,0,IFERROR((T$2*IFERROR(VLOOKUP(J54,Tabla11[],2,0),0))*($L54/SUM($L$5:$L$46)),0)) -> 5704.0713 | U54: =IF($L54<0,0,IFERROR((U$2*IFERROR(VLOOKUP(J54,Tabla11[],2,0),0))*($L54/SUM($L$5:$L$46)),0)) -> 1109.125 | V54: =IF($L54<0,0,IFERROR((V$2*IFERROR(VLOOKUP(J54,Tabla11[],2,0),0))*($L54/SUM($L$5:$L$46)),0)) -> 5704.0713 | W54: =IF($L54<0,0,IFERROR((W$2*IFERROR(VLOOKUP(J54,Tabla11[],2,0),0))*($L54/SUM($L$5:$L$46)),0)) -> 7922.3213 | X54: =P54*$X$2 -> 172797.98 | Y54: =+X54*IFERROR(VLOOKUP(J54,Tabla11[],4,0),0) -> 25919.697 | Z54: =IF(L54>0,$Z$2/12,0) -> 25833.333 | AA54: =P54-SUM(Q54:Z54) -> 32610.883 | AB54: =IF($L54<0,0,IFERROR((AB$2*IFERROR(VLOOKUP(J54,Tabla11[],2,0),0))*($L54/SUM($L$5:$L$46)),0)) -> 9098.2773 | AC54: =L54-L54*IFERROR(VLOOKUP(J54,Tabla11[],3,0),0)-Q54-T54-U54-V54-W54-L54*$X$2-(L54*$X$2)*IFERROR(VLOOKUP(J54,Tabla11[],4,0),0)-AB54-Z54 -> 59424.66 | AD54: =AA54-AB54 -> 23512.606 | AE54: =ROUND(AD54-AC54,9) -> -35912.055
B55: Outsourcing | E55: Outsourcing | G55: 3 | H55: Supervisor Santiago | I55: Santiago 01 | J55: París | K55: Alto Las Condes | L55: =IFERROR(VLOOKUP(CONCATENATE(J55,K55),Ventas!D:H,4,0),0) -> 2826371.8 | M55: =IF(SUM(C55,F55)>0,L55*0.1,0) -> 0 | N55: =SUM(L55:M55) -> 2826371.8 | O55: =N55*IFERROR(VLOOKUP(J55,Tabla11[],3,0),0) -> 989230.12 | P55: =N55-O55 -> 1837141.6 | Q55: =IFERROR(G55/SUMIF(I:I,I55,G:G),0)*VLOOKUP(H55,Modelos[],14,0)+IFERROR(G55/SUMIF(I:I,I55,G:G),0)*VLOOKUP(I55,Tabla13[],2,0) -> 69504.988 | R55: =IFERROR(VLOOKUP(A55,Modelos[],IF(B55="EST",15,14),0),0)*C55 -> 0 | S55: =IFERROR(VLOOKUP(D55,Modelos[],IF(E55="EST",15,14),0),0)*F55 -> 0 | T55: =IF($L55<0,0,IFERROR((T$2*IFERROR(VLOOKUP(J55,Tabla11[],2,0),0))*($L55/SUM($L$5:$L$46)),0)) -> 26683.427 | U55: =IF($L55<0,0,IFERROR((U$2*IFERROR(VLOOKUP(J55,Tabla11[],2,0),0))*($L55/SUM($L$5:$L$46)),0)) -> 5188.4442 | V55: =IF($L55<0,0,IFERROR((V$2*IFERROR(VLOOKUP(J55,Tabla11[],2,0),0))*($L55/SUM($L$5:$L$46)),0)) -> 26683.427 | W55: =IF($L55<0,0,IFERROR((W$2*IFERROR(VLOOKUP(J55,Tabla11[],2,0),0))*($L55/SUM($L$5:$L$46)),0)) -> 37060.316 | X55: =P55*$X$2 -> 734856.66 | Y55: =+X55*IFERROR(VLOOKUP(J55,Tabla11[],4,0),0) -> 110228.5 | Z55: =IF(L55>0,$Z$2/12,0) -> 25833.333 | AA55: =P55-SUM(Q55:Z55) -> 801102.55 | AB55: =IF($L55<0,0,IFERROR((AB$2*IFERROR(VLOOKUP(J55,Tabla11[],2,0),0))*($L55/SUM($L$5:$L$46)),0)) -> 42561.393 | AC55: =L55-L55*IFERROR(VLOOKUP(J55,Tabla11[],3,0),0)-Q55-T55-U55-V55-W55-L55*$X$2-(L55*$X$2)*IFERROR(VLOOKUP(J55,Tabla11[],4,0),0)-AB55-Z55 -> 303495.31 | AD55: =AA55-AB55 -> 758541.16 | AE55: =ROUND(AD55-AC55,9) -> 455045.85
A56: Vendedor 1/2 2 días | B56: Outsourcing | C56: 1 | E56: Outsourcing | G56: 3 | H56: Supervisor Part | I56: Arica | J56: París | K56: Arica | L56: =IFERROR(VLOOKUP(CONCATENATE(J56,K56),Ventas!D:H,4,0),0) -> 3326239.4 | M56: =IF(SUM(C56,F56)>0,L56*0.1,0) -> 332623.94 | N56: =SUM(L56:M56) -> 3658863.4 | O56: =N56*IFERROR(VLOOKUP(J56,Tabla11[],3,0),0) -> 1280602.2 | P56: =N56-O56 -> 2378261.2 | Q56: =IFERROR(G56/SUMIF(I:I,I56,G:G),0)*VLOOKUP(H56,Modelos[],14,0)+IFERROR(G56/SUMIF(I:I,I56,G:G),0)*VLOOKUP(I56,Tabla13[],2,0) -> 121576.09 | R56: =IFERROR(VLOOKUP(A56,Modelos[],IF(B56="EST",15,14),0),0)*C56 -> 154393.47 | S56: =IFERROR(VLOOKUP(D56,Modelos[],IF(E56="EST",15,14),0),0)*F56 -> 0 | T56: =IF($L56<0,0,IFERROR((T$2*IFERROR(VLOOKUP(J56,Tabla11[],2,0),0))*($L56/SUM($L$5:$L$46)),0)) -> 31402.616 | U56: =IF($L56<0,0,IFERROR((U$2*IFERROR(VLOOKUP(J56,Tabla11[],2,0),0))*($L56/SUM($L$5:$L$46)),0)) -> 6106.0643 | V56: =IF($L56<0,0,IFERROR((V$2*IFERROR(VLOOKUP(J56,Tabla11[],2,0),0))*($L56/SUM($L$5:$L$46)),0)) -> 31402.616 | W56: =IF($L56<0,0,IFERROR((W$2*IFERROR(VLOOKUP(J56,Tabla11[],2,0),0))*($L56/SUM($L$5:$L$46)),0)) -> 43614.745 | X56: =P56*$X$2 -> 951304.48 | Y56: =+X56*IFERROR(VLOOKUP(J56,Tabla11[],4,0),0) -> 142695.67 | Z56: =IF(L56>0,$Z$2/12,0) -> 25833.333 | AA56: =P56-SUM(Q56:Z56) -> 869932.12 | AB56: =IF($L56<0,0,IFERROR((AB$2*IFERROR(VLOOKUP(J56,Tabla11[],2,0),0))*($L56/SUM($L$5:$L$46)),0)) -> 50088.734 | AC56: =L56-L56*IFERROR(VLOOKUP(J56,Tabla11[],3,0),0)-Q56-T56-U56-V56-W56-L56*$X$2-(L56*$X$2)*IFERROR(VLOOKUP(J56,Tabla11[],4,0),0)-AB56-Z56 -> 321961.3 | AD56: =AA56-AB56 -> 819843.39 | AE56: =ROUND(AD56-AC56,9) -> 497882.09
A57: Vendedor 1/2 3 días | B57: Outsourcing | C57: 1 | E57: Outsourcing | G57: 3 | H57: Supervisor Regiones | I57: Concepción | J57: París | K57: Plaza Del Trebol | L57: =IFERROR(VLOOKUP(CONCATENATE(J57,K57),Ventas!D:H,4,0),0) -> 1697412.3 | M57: =IF(SUM(C57,F57)>0,L57*0.1,0) -> 169741.23 | N57: =SUM(L57:M57) -> 1867153.6 | O57: =N57*IFERROR(VLOOKUP(J57,Tabla11[],3,0),0) -> 653503.75 | P57: =N57-O57 -> 1213649.8 | Q57: =IFERROR(G57/SUMIF(I:I,I57,G:G),0)*VLOOKUP(H57,Modelos[],14,0)+IFERROR(G57/SUMIF(I:I,I57,G:G),0)*VLOOKUP(I57,Tabla13[],2,0) -> 106001.17 | R57: =IFERROR(VLOOKUP(A57,Modelos[],IF(B57="EST",15,14),0),0)*C57 -> 204526.8 | S57: =IFERROR(VLOOKUP(D57,Modelos[],IF(E57="EST",15,14),0),0)*F57 -> 0 | T57: =IF($L57<0,0,IFERROR((T$2*IFERROR(VLOOKUP(J57,Tabla11[],2,0),0))*($L57/SUM($L$5:$L$46)),0)) -> 16025.06 | U57: =IF($L57<0,0,IFERROR((U$2*IFERROR(VLOOKUP(J57,Tabla11[],2,0),0))*($L57/SUM($L$5:$L$46)),0)) -> 3115.984 | V57: =IF($L57<0,0,IFERROR((V$2*IFERROR(VLOOKUP(J57,Tabla11[],2,0),0))*($L57/SUM($L$5:$L$46)),0)) -> 16025.06 | W57: =IF($L57<0,0,IFERROR((W$2*IFERROR(VLOOKUP(J57,Tabla11[],2,0),0))*($L57/SUM($L$5:$L$46)),0)) -> 22257.028 | X57: =P57*$X$2 -> 485459.93 | Y57: =+X57*IFERROR(VLOOKUP(J57,Tabla11[],4,0),0) -> 72818.989 | Z57: =IF(L57>0,$Z$2/12,0) -> 25833.333 | AA57: =P57-SUM(Q57:Z57) -> 261586.46 | AB57: =IF($L57<0,0,IFERROR((AB$2*IFERROR(VLOOKUP(J57,Tabla11[],2,0),0))*($L57/SUM($L$5:$L$46)),0)) -> 25560.768 | AC57: =L57-L57*IFERROR(VLOOKUP(J57,Tabla11[],3,0),0)-Q57-T57-U57-V57-W57-L57*$X$2-(L57*$X$2)*IFERROR(VLOOKUP(J57,Tabla11[],4,0),0)-AB57-Z57 -> 107689.93 | AD57: =AA57-AB57 -> 236025.69 | AE57: =ROUND(AD57-AC57,9) -> 128335.76
A58: Vendedor 1/2 2 días | B58: Outsourcing | C58: 1 | E58: Outsourcing | G58: 2 | H58: Supervisor Regiones | I58: Concepción | J58: París | K58: Los Angeles | L58: =IFERROR(VLOOKUP(CONCATENATE(J58,K58),Ventas!D:H,4,0),0) -> 1498375.6 | M58: =IF(SUM(C58,F58)>0,L58*0.1,0) -> 149837.56 | N58: =SUM(L58:M58) -> 1648213.2 | O58: =N58*IFERROR(VLOOKUP(J58,Tabla11[],3,0),0) -> 576874.61 | P58: =N58-O58 -> 1071338.6 | Q58: =IFERROR(G58/SUMIF(I:I,I58,G:G),0)*VLOOKUP(H58,Modelos[],14,0)+IFERROR(G58/SUMIF(I:I,I58,G:G),0)*VLOOKUP(I58,Tabla13[],2,0) -> 70667.45 | R58: =IFERROR(VLOOKUP(A58,Modelos[],IF(B58="EST",15,14),0),0)*C58 -> 154393.47 | S58: =IFERROR(VLOOKUP(D58,Modelos[],IF(E58="EST",15,14),0),0)*F58 -> 0 | T58: =IF($L58<0,0,IFERROR((T$2*IFERROR(VLOOKUP(J58,Tabla11[],2,0),0))*($L58/SUM($L$5:$L$46)),0)) -> 14145.979 | U58: =IF($L58<0,0,IFERROR((U$2*IFERROR(VLOOKUP(J58,Tabla11[],2,0),0))*($L58/SUM($L$5:$L$46)),0)) -> 2750.6071 | V58: =IF($L58<0,0,IFERROR((V$2*IFERROR(VLOOKUP(J58,Tabla11[],2,0),0))*($L58/SUM($L$5:$L$46)),0)) -> 14145.979 | W58: =IF($L58<0,0,IFERROR((W$2*IFERROR(VLOOKUP(J58,Tabla11[],2,0),0))*($L58/SUM($L$5:$L$46)),0)) -> 19647.193 | X58: =P58*$X$2 -> 428535.42 | Y58: =+X58*IFERROR(VLOOKUP(J58,Tabla11[],4,0),0) -> 64280.314 | Z58: =IF(L58>0,$Z$2/12,0) -> 25833.333 | AA58: =P58-SUM(Q58:Z58) -> 276938.81 | AB58: =IF($L58<0,0,IFERROR((AB$2*IFERROR(VLOOKUP(J58,Tabla11[],2,0),0))*($L58/SUM($L$5:$L$46)),0)) -> 22563.54 | AC58: =L58-L58*IFERROR(VLOOKUP(J58,Tabla11[],3,0),0)-Q58-T58-U58-V58-W58-L58*$X$2-(L58*$X$2)*IFERROR(VLOOKUP(J58,Tabla11[],4,0),0)-AB58-Z58 -> 114937.28 | AD58: =AA58-AB58 -> 254375.27 | AE58: =ROUND(AD58-AC58,9) -> 139437.99
A59: Vendedor 1/2 3 días | B59: Outsourcing | C59: 1 | E59: Outsourcing | G59: 0 | H59: Supervisor Regiones | I59: Puerto Montt | J59: París | K59: Puerto Montt | L59: =IFERROR(VLOOKUP(CONCATENATE(J59,K59),Ventas!D:H,4,0),0) -> 1811710.2 | M59: =IF(SUM(C59,F59)>0,L59*0.1,0) -> 181171.02 | N59: =SUM(L59:M59) -> 1992881.3 | O59: =N59*IFERROR(VLOOKUP(J59,Tabla11[],3,0),0) -> 697508.44 | P59: =N59-O59 -> 1295372.8 | Q59: =IFERROR(G59/SUMIF(I:I,I59,G:G),0)*VLOOKUP(H59,Modelos[],14,0)+IFERROR(G59/SUMIF(I:I,I59,G:G),0)*VLOOKUP(I59,Tabla13[],2,0) -> 0 | R59: =IFERROR(VLOOKUP(A59,Modelos[],IF(B59="EST",15,14),0),0)*C59 -> 204526.8 | S59: =IFERROR(VLOOKUP(D59,Modelos[],IF(E59="EST",15,14),0),0)*F59 -> 0 | T59: =IF($L59<0,0,IFERROR((T$2*IFERROR(VLOOKUP(J59,Tabla11[],2,0),0))*($L59/SUM($L$5:$L$46)),0)) -> 17104.133 | U59: =IF($L59<0,0,IFERROR((U$2*IFERROR(VLOOKUP(J59,Tabla11[],2,0),0))*($L59/SUM($L$5:$L$46)),0)) -> 3325.8036 | V59: =IF($L59<0,0,IFERROR((V$2*IFERROR(VLOOKUP(J59,Tabla11[],2,0),0))*($L59/SUM($L$5:$L$46)),0)) -> 17104.133 | W59: =IF($L59<0,0,IFERROR((W$2*IFERROR(VLOOKUP(J59,Tabla11[],2,0),0))*($L59/SUM($L$5:$L$46)),0)) -> 23755.74 | X59: =P59*$X$2 -> 518149.13 | Y59: =+X59*IFERROR(VLOOKUP(J59,Tabla11[],4,0),0) -> 77722.369 | Z59: =IF(L59>0,$Z$2/12,0) -> 25833.333 | AA59: =P59-SUM(Q59:Z59) -> 407851.38 | AB59: =IF($L59<0,0,IFERROR((AB$2*IFERROR(VLOOKUP(J59,Tabla11[],2,0),0))*($L59/SUM($L$5:$L$46)),0)) -> 27281.942 | AC59: =L59-L59*IFERROR(VLOOKUP(J59,Tabla11[],3,0),0)-Q59-T59-U59-V59-W59-L59*$X$2-(L59*$X$2)*IFERROR(VLOOKUP(J59,Tabla11[],4,0),0)-AB59-Z59 -> 229819.86 | AD59: =AA59-AB59 -> 380569.44 | AE59: =ROUND(AD59-AC59,9) -> 150749.58
A60: Vendedor 1/2 3 días | B60: Outsourcing | C60: 1 | E60: Outsourcing | G60: 3 | H60: Supervisor Part | I60: Antofagasta | J60: París | K60: Antofagasta | L60: =IFERROR(VLOOKUP(CONCATENATE(J60,K60),Ventas!D:H,4,0),0) -> 2263023.9 | M60: =IF(SUM(C60,F60)>0,L60*0.1,0) -> 226302.39 | N60: =SUM(L60:M60) -> 2489326.2 | O60: =N60*IFERROR(VLOOKUP(J60,Tabla11[],3,0),0) -> 871264.18 | P60: =N60-O60 -> 1618062.1 | Q60: =IFERROR(G60/SUMIF(I:I,I60,G:G),0)*VLOOKUP(H60,Modelos[],14,0)+IFERROR(G60/SUMIF(I:I,I60,G:G),0)*VLOOKUP(I60,Tabla13[],2,0) -> 121576.09 | R60: =IFERROR(VLOOKUP(A60,Modelos[],IF(B60="EST",15,14),0),0)*C60 -> 204526.8 | S60: =IFERROR(VLOOKUP(D60,Modelos[],IF(E60="EST",15,14),0),0)*F60 -> 0 | T60: =IF($L60<0,0,IFERROR((T$2*IFERROR(VLOOKUP(J60,Tabla11[],2,0),0))*($L60/SUM($L$5:$L$46)),0)) -> 21364.929 | U60: =IF($L60<0,0,IFERROR((U$2*IFERROR(VLOOKUP(J60,Tabla11[],2,0),0))*($L60/SUM($L$5:$L$46)),0)) -> 4154.2918 | V60: =IF($L60<0,0,IFERROR((V$2*IFERROR(VLOOKUP(J60,Tabla11[],2,0),0))*($L60/SUM($L$5:$L$46)),0)) -> 21364.929 | W60: =IF($L60<0,0,IFERROR((W$2*IFERROR(VLOOKUP(J60,Tabla11[],2,0),0))*($L60/SUM($L$5:$L$46)),0)) -> 29673.513 | X60: =P60*$X$2 -> 647224.82 | Y60: =+X60*IFERROR(VLOOKUP(J60,Tabla11[],4,0),0) -> 97083.723 | Z60: =IF(L60>0,$Z$2/12,0) -> 25833.333 | AA60: =P60-SUM(Q60:Z60) -> 445259.63 | AB60: =IF($L60<0,0,IFERROR((AB$2*IFERROR(VLOOKUP(J60,Tabla11[],2,0),0))*($L60/SUM($L$5:$L$46)),0)) -> 34078.124 | AC60: =L60-L60*IFERROR(VLOOKUP(J60,Tabla11[],3,0),0)-Q60-T60-U60-V60-W60-L60*$X$2-(L60*$X$2)*IFERROR(VLOOKUP(J60,Tabla11[],4,0),0)-AB60-Z60 -> 171929.33 | AD60: =AA60-AB60 -> 411181.51 | AE60: =ROUND(AD60-AC60,9) -> 239252.18
A61: Vendedor 1/2 2 días | B61: Outsourcing | C61: 1 | E61: Outsourcing | G61: 1 | H61: Supervisor Regiones | I61: VI-VII | J61: París | K61: Curico | L61: =IFERROR(VLOOKUP(CONCATENATE(J61,K61),Ventas!D:H,4,0),0) -> 1941595.8 | M61: =IF(SUM(C61,F61)>0,L61*0.1,0) -> 194159.58 | N61: =SUM(L61:M61) -> 2135755.4 | O61: =N61*IFERROR(VLOOKUP(J61,Tabla11[],3,0),0) -> 747514.4 | P61: =N61-O61 -> 1388241 | Q61: =IFERROR(G61/SUMIF(I:I,I61,G:G),0)*VLOOKUP(H61,Modelos[],14,0)+IFERROR(G61/SUMIF(I:I,I61,G:G),0)*VLOOKUP(I61,Tabla13[],2,0) -> 51647.612 | R61: =IFERROR(VLOOKUP(A61,Modelos[],IF(B61="EST",15,14),0),0)*C61 -> 154393.47 | S61: =IFERROR(VLOOKUP(D61,Modelos[],IF(E61="EST",15,14),0),0)*F61 -> 0 | T61: =IF($L61<0,0,IFERROR((T$2*IFERROR(VLOOKUP(J61,Tabla11[],2,0),0))*($L61/SUM($L$5:$L$46)),0)) -> 18330.367 | U61: =IF($L61<0,0,IFERROR((U$2*IFERROR(VLOOKUP(J61,Tabla11[],2,0),0))*($L61/SUM($L$5:$L$46)),0)) -> 3564.238 | V61: =IF($L61<0,0,IFERROR((V$2*IFERROR(VLOOKUP(J61,Tabla11[],2,0),0))*($L61/SUM($L$5:$L$46)),0)) -> 18330.367 | W61: =IF($L61<0,0,IFERROR((W$2*IFERROR(VLOOKUP(J61,Tabla11[],2,0),0))*($L61/SUM($L$5:$L$46)),0)) -> 25458.843 | X61: =P61*$X$2 -> 555296.41 | Y61: =+X61*IFERROR(VLOOKUP(J61,Tabla11[],4,0),0) -> 83294.461 | Z61: =IF(L61>0,$Z$2/12,0) -> 25833.333 | AA61: =P61-SUM(Q61:Z61) -> 452091.93 | AB61: =IF($L61<0,0,IFERROR((AB$2*IFERROR(VLOOKUP(J61,Tabla11[],2,0),0))*($L61/SUM($L$5:$L$46)),0)) -> 29237.846 | AC61: =L61-L61*IFERROR(VLOOKUP(J61,Tabla11[],3,0),0)-Q61-T61-U61-V61-W61-L61*$X$2-(L61*$X$2)*IFERROR(VLOOKUP(J61,Tabla11[],4,0),0)-AB61-Z61 -> 196500.6 | AD61: =AA61-AB61 -> 422854.08 | AE61: =ROUND(AD61-AC61,9) -> 226353.48
A62: Vendedor 1/2 2 días | B62: Outsourcing | C62: 0.5 | E62: Outsourcing | G62: 3 | H62: Supervisor Part | I62: Temuco | J62: París | K62: Portal Temuco | L62: =IFERROR(VLOOKUP(CONCATENATE(J62,K62),Ventas!D:H,4,0),0) -> 1494248.3 | M62: =IF(SUM(C62,F62)>0,L62*0.1,0) -> 149424.83 | N62: =SUM(L62:M62) -> 1643673.1 | O62: =N62*IFERROR(VLOOKUP(J62,Tabla11[],3,0),0) -> 575285.59 | P62: =N62-O62 -> 1068387.5 | Q62: =IFERROR(G62/SUMIF(I:I,I62,G:G),0)*VLOOKUP(H62,Modelos[],14,0)+IFERROR(G62/SUMIF(I:I,I62,G:G),0)*VLOOKUP(I62,Tabla13[],2,0) -> 65246.163 | R62: =IFERROR(VLOOKUP(A62,Modelos[],IF(B62="EST",15,14),0),0)*C62 -> 77196.733 | S62: =IFERROR(VLOOKUP(D62,Modelos[],IF(E62="EST",15,14),0),0)*F62 -> 0 | T62: =IF($L62<0,0,IFERROR((T$2*IFERROR(VLOOKUP(J62,Tabla11[],2,0),0))*($L62/SUM($L$5:$L$46)),0)) -> 14107.014 | U62: =IF($L62<0,0,IFERROR((U$2*IFERROR(VLOOKUP(J62,Tabla11[],2,0),0))*($L62/SUM($L$5:$L$46)),0)) -> 2743.0305 | V62: =IF($L62<0,0,IFERROR((V$2*IFERROR(VLOOKUP(J62,Tabla11[],2,0),0))*($L62/SUM($L$5:$L$46)),0)) -> 14107.014 | W62: =IF($L62<0,0,IFERROR((W$2*IFERROR(VLOOKUP(J62,Tabla11[],2,0),0))*($L62/SUM($L$5:$L$46)),0)) -> 19593.075 | X62: =P62*$X$2 -> 427355.01 | Y62: =+X62*IFERROR(VLOOKUP(J62,Tabla11[],4,0),0) -> 64103.252 | Z62: =IF(L62>0,$Z$2/12,0) -> 25833.333 | AA62: =P62-SUM(Q62:Z62) -> 358102.9 | AB62: =IF($L62<0,0,IFERROR((AB$2*IFERROR(VLOOKUP(J62,Tabla11[],2,0),0))*($L62/SUM($L$5:$L$46)),0)) -> 22501.388 | AC62: =L62-L62*IFERROR(VLOOKUP(J62,Tabla11[],3,0),0)-Q62-T62-U62-V62-W62-L62*$X$2-(L62*$X$2)*IFERROR(VLOOKUP(J62,Tabla11[],4,0),0)-AB62-Z62 -> 119776.16 | AD62: =AA62-AB62 -> 335601.52 | AE62: =ROUND(AD62-AC62,9) -> 215825.36
A63: Vendedor 1/2 3 días | B63: Outsourcing | C63: 1 | E63: Outsourcing | G63: 3 | H63: Supervisor Santiago | I63: Santiago 02 | J63: París | K63: Plaza Vespucio | L63: =IFERROR(VLOOKUP(CONCATENATE(J63,K63),Ventas!D:H,4,0),0) -> 1358193.9 | M63: =IF(SUM(C63,F63)>0,L63*0.1,0) -> 135819.39 | N63: =SUM(L63:M63) -> 1494013.2 | O63: =N63*IFERROR(VLOOKUP(J63,Tabla11[],3,0),0) -> 522904.63 | P63: =N63-O63 -> 971108.6 | Q63: =IFERROR(G63/SUMIF(I:I,I63,G:G),0)*VLOOKUP(H63,Modelos[],14,0)+IFERROR(G63/SUMIF(I:I,I63,G:G),0)*VLOOKUP(I63,Tabla13[],2,0) -> 69504.988 | R63: =IFERROR(VLOOKUP(A63,Modelos[],IF(B63="EST",15,14),0),0)*C63 -> 204526.8 | S63: =IFERROR(VLOOKUP(D63,Modelos[],IF(E63="EST",15,14),0),0)*F63 -> 0 | T63: =IF($L63<0,0,IFERROR((T$2*IFERROR(VLOOKUP(J63,Tabla11[],2,0),0))*($L63/SUM($L$5:$L$46)),0)) -> 12822.541 | U63: =IF($L63<0,0,IFERROR((U$2*IFERROR(VLOOKUP(J63,Tabla11[],2,0),0))*($L63/SUM($L$5:$L$46)),0)) -> 2493.2718 | V63: =IF($L63<0,0,IFERROR((V$2*IFERROR(VLOOKUP(J63,Tabla11[],2,0),0))*($L63/SUM($L$5:$L$46)),0)) -> 12822.541 | W63: =IF($L63<0,0,IFERROR((W$2*IFERROR(VLOOKUP(J63,Tabla11[],2,0),0))*($L63/SUM($L$5:$L$46)),0)) -> 17809.084 | X63: =P63*$X$2 -> 388443.44 | Y63: =+X63*IFERROR(VLOOKUP(J63,Tabla11[],4,0),0) -> 58266.516 | Z63: =IF(L63>0,$Z$2/12,0) -> 25833.333 | AA63: =P63-SUM(Q63:Z63) -> 178586.09 | AB63: =IF($L63<0,0,IFERROR((AB$2*IFERROR(VLOOKUP(J63,Tabla11[],2,0),0))*($L63/SUM($L$5:$L$46)),0)) -> 20452.59 | AC63: =L63-L63*IFERROR(VLOOKUP(J63,Tabla11[],3,0),0)-Q63-T63-U63-V63-W63-L63*$X$2-(L63*$X$2)*IFERROR(VLOOKUP(J63,Tabla11[],4,0),0)-AB63-Z63 -> 96318.484 | AD63: =AA63-AB63 -> 158133.5 | AE63: =ROUND(AD63-AC63,9) -> 61815.014
A64: Vendedor 1/2 3 días | B64: Outsourcing | C64: 1 | E64: Outsourcing | G64: 3 | H64: Supervisor Santiago | I64: Santiago 02 | J64: París | K64: Florida Center | L64: =IFERROR(VLOOKUP(CONCATENATE(J64,K64),Ventas!D:H,4,0),0) -> 1302181.8 | M64: =IF(SUM(C64,F64)>0,L64*0.1,0) -> 130218.18 | N64: =SUM(L64:M64) -> 1432400 | O64: =N64*IFERROR(VLOOKUP(J64,Tabla11[],3,0),0) -> 501340.01 | P64: =N64-O64 -> 931060.02 | Q64: =IFERROR(G64/SUMIF(I:I,I64,G:G),0)*VLOOKUP(H64,Modelos[],14,0)+IFERROR(G64/SUMIF(I:I,I64,G:G),0)*VLOOKUP(I64,Tabla13[],2,0) -> 69504.988 | R64: =IFERROR(VLOOKUP(A64,Modelos[],IF(B64="EST",15,14),0),0)*C64 -> 204526.8 | S64: =IFERROR(VLOOKUP(D64,Modelos[],IF(E64="EST",15,14),0),0)*F64 -> 0 | T64: =IF($L64<0,0,IFERROR((T$2*IFERROR(VLOOKUP(J64,Tabla11[],2,0),0))*($L64/SUM($L$5:$L$46)),0)) -> 12293.738 | U64: =IF($L64<0,0,IFERROR((U$2*IFERROR(VLOOKUP(J64,Tabla11[],2,0),0))*($L64/SUM($L$5:$L$46)),0)) -> 2390.4491 | V64: =IF($L64<0,0,IFERROR((V$2*IFERROR(VLOOKUP(J64,Tabla11[],2,0),0))*($L64/SUM($L$5:$L$46)),0)) -> 12293.738 | W64: =IF($L64<0,0,IFERROR((W$2*IFERROR(VLOOKUP(J64,Tabla11[],2,0),0))*($L64/SUM($L$5:$L$46)),0)) -> 17074.636 | X64: =P64*$X$2 -> 372424.01 | Y64: =+X64*IFERROR(VLOOKUP(J64,Tabla11[],4,0),0) -> 55863.601 | Z64: =IF(L64>0,$Z$2/12,0) -> 25833.333 | AA64: =P64-SUM(Q64:Z64) -> 158854.73 | AB64: =IF($L64<0,0,IFERROR((AB$2*IFERROR(VLOOKUP(J64,Tabla11[],2,0),0))*($L64/SUM($L$5:$L$46)),0)) -> 19609.124 | AC64: =L64-L64*IFERROR(VLOOKUP(J64,Tabla11[],3,0),0)-Q64-T64-U64-V64-W64-L64*$X$2-(L64*$X$2)*IFERROR(VLOOKUP(J64,Tabla11[],4,0),0)-AB64-Z64 -> 88414.545 | AD64: =AA64-AB64 -> 139245.6 | AE64: =ROUND(AD64-AC64,9) -> 50831.06
A65: Vendedor 1/2 2 días | B65: Outsourcing | C65: 1 | E65: Outsourcing | G65: 3 | H65: Supervisor Santiago | I65: Santiago 02 | J65: París | K65: Plaza Tobalaba | L65: =IFERROR(VLOOKUP(CONCATENATE(J65,K65),Ventas!D:H,4,0),0) -> 1817360.6 | M65: =IF(SUM(C65,F65)>0,L65*0.1,0) -> 181736.06 | N65: =SUM(L65:M65) -> 1999096.7 | O65: =N65*IFERROR(VLOOKUP(J65,Tabla11[],3,0),0) -> 699683.83 | P65: =N65-O65 -> 1299412.8 | Q65: =IFERROR(G65/SUMIF(I:I,I65,G:G),0)*VLOOKUP(H65,Modelos[],14,0)+IFERROR(G65/SUMIF(I:I,I65,G:G),0)*VLOOKUP(I65,Tabla13[],2,0) -> 69504.988 | R65: =IFERROR(VLOOKUP(A65,Modelos[],IF(B65="EST",15,14),0),0)*C65 -> 154393.47 | S65: =IFERROR(VLOOKUP(D65,Modelos[],IF(E65="EST",15,14),0),0)*F65 -> 0 | T65: =IF($L65<0,0,IFERROR((T$2*IFERROR(VLOOKUP(J65,Tabla11[],2,0),0))*($L65/SUM($L$5:$L$46)),0)) -> 17157.477 | U65: =IF($L65<0,0,IFERROR((U$2*IFERROR(VLOOKUP(J65,Tabla11[],2,0),0))*($L65/SUM($L$5:$L$46)),0)) -> 3336.1761 | V65: =IF($L65<0,0,IFERROR((V$2*IFERROR(VLOOKUP(J65,Tabla11[],2,0),0))*($L65/SUM($L$5:$L$46)),0)) -> 17157.477 | W65: =IF($L65<0,0,IFERROR((W$2*IFERROR(VLOOKUP(J65,Tabla11[],2,0),0))*($L65/SUM($L$5:$L$46)),0)) -> 23829.83 | X65: =P65*$X$2 -> 519765.13 | Y65: =+X65*IFERROR(VLOOKUP(J65,Tabla11[],4,0),0) -> 77964.77 | Z65: =IF(L65>0,$Z$2/12,0) -> 25833.333 | AA65: =P65-SUM(Q65:Z65) -> 390470.18 | AB65: =IF($L65<0,0,IFERROR((AB$2*IFERROR(VLOOKUP(J65,Tabla11[],2,0),0))*($L65/SUM($L$5:$L$46)),0)) -> 27367.029 | AC65: =L65-L65*IFERROR(VLOOKUP(J65,Tabla11[],3,0),0)-Q65-T65-U65-V65-W65-L65*$X$2-(L65*$X$2)*IFERROR(VLOOKUP(J65,Tabla11[],4,0),0)-AB65-Z65 -> 161112.2 | AD65: =AA65-AB65 -> 363103.15 | AE65: =ROUND(AD65-AC65,9) -> 201990.95
A66: Vendedor 1/2 2 días | B66: Outsourcing | C66: 1 | E66: Outsourcing | G66: 0 | H66: Supervisor Regiones | I66: La Serena | J66: París | K66: Ovalle | L66: =IFERROR(VLOOKUP(CONCATENATE(J66,K66),Ventas!D:H,4,0),0) -> 764264.13 | M66: =IF(SUM(C66,F66)>0,L66*0.1,0) -> 76426.413 | N66: =SUM(L66:M66) -> 840690.54 | O66: =N66*IFERROR(VLOOKUP(J66,Tabla11[],3,0),0) -> 294241.69 | P66: =N66-O66 -> 546448.85 | Q66: =IFERROR(G66/SUMIF(I:I,I66,G:G),0)*VLOOKUP(H66,Modelos[],14,0)+IFERROR(G66/SUMIF(I:I,I66,G:G),0)*VLOOKUP(I66,Tabla13[],2,0) -> 0 | R66: =IFERROR(VLOOKUP(A66,Modelos[],IF(B66="EST",15,14),0),0)*C66 -> 154393.47 | S66: =IFERROR(VLOOKUP(D66,Modelos[],IF(E66="EST",15,14),0),0)*F66 -> 0 | T66: =IF($L66<0,0,IFERROR((T$2*IFERROR(VLOOKUP(J66,Tabla11[],2,0),0))*($L66/SUM($L$5:$L$46)),0)) -> 7215.3234 | U66: =IF($L66<0,0,IFERROR((U$2*IFERROR(VLOOKUP(J66,Tabla11[],2,0),0))*($L66/SUM($L$5:$L$46)),0)) -> 1402.9795 | V66: =IF($L66<0,0,IFERROR((V$2*IFERROR(VLOOKUP(J66,Tabla11[],2,0),0))*($L66/SUM($L$5:$L$46)),0)) -> 7215.3234 | W66: =IF($L66<0,0,IFERROR((W$2*IFERROR(VLOOKUP(J66,Tabla11[],2,0),0))*($L66/SUM($L$5:$L$46)),0)) -> 10021.282 | X66: =P66*$X$2 -> 218579.54 | Y66: =+X66*IFERROR(VLOOKUP(J66,Tabla11[],4,0),0) -> 32786.931 | Z66: =IF(L66>0,$Z$2/12,0) -> 25833.333 | AA66: =P66-SUM(Q66:Z66) -> 89000.672 | AB66: =IF($L66<0,0,IFERROR((AB$2*IFERROR(VLOOKUP(J66,Tabla11[],2,0),0))*($L66/SUM($L$5:$L$46)),0)) -> 11508.799 | AC66: =L66-L66*IFERROR(VLOOKUP(J66,Tabla11[],3,0),0)-Q66-T66-U66-V66-W66-L66*$X$2-(L66*$X$2)*IFERROR(VLOOKUP(J66,Tabla11[],4,0),0)-AB66-Z66 -> 82013.143 | AD66: =AA66-AB66 -> 77491.873 | AE66: =ROUND(AD66-AC66,9) -> -4521.27
B67: Outsourcing | E67: Outsourcing | G67: 3 | H67: Supervisor Part | I67: Iquique | J67: París | K67: Iquique | L67: =IFERROR(VLOOKUP(CONCATENATE(J67,K67),Ventas!D:H,4,0),0) -> 1601137.3 | M67: =IF(SUM(C67,F67)>0,L67*0.1,0) -> 0 | N67: =SUM(L67:M67) -> 1601137.3 | O67: =N67*IFERROR(VLOOKUP(J67,Tabla11[],3,0),0) -> 560398.04 | P67: =N67-O67 -> 1040739.2 | Q67: =IFERROR(G67/SUMIF(I:I,I67,G:G),0)*VLOOKUP(H67,Modelos[],14,0)+IFERROR(G67/SUMIF(I:I,I67,G:G),0)*VLOOKUP(I67,Tabla13[],2,0) -> 134909.42 | R67: =IFERROR(VLOOKUP(A67,Modelos[],IF(B67="EST",15,14),0),0)*C67 -> 0 | S67: =IFERROR(VLOOKUP(D67,Modelos[],IF(E67="EST",15,14),0),0)*F67 -> 0 | T67: =IF($L67<0,0,IFERROR((T$2*IFERROR(VLOOKUP(J67,Tabla11[],2,0),0))*($L67/SUM($L$5:$L$46)),0)) -> 15116.139 | U67: =IF($L67<0,0,IFERROR((U$2*IFERROR(VLOOKUP(J67,Tabla11[],2,0),0))*($L67/SUM($L$5:$L$46)),0)) -> 2939.2493 | V67: =IF($L67<0,0,IFERROR((V$2*IFERROR(VLOOKUP(J67,Tabla11[],2,0),0))*($L67/SUM($L$5:$L$46)),0)) -> 15116.139 | W67: =IF($L67<0,0,IFERROR((W$2*IFERROR(VLOOKUP(J67,Tabla11[],2,0),0))*($L67/SUM($L$5:$L$46)),0)) -> 20994.638 | X67: =P67*$X$2 -> 416295.69 | Y67: =+X67*IFERROR(VLOOKUP(J67,Tabla11[],4,0),0) -> 62444.353 | Z67: =IF(L67>0,$Z$2/12,0) -> 25833.333 | AA67: =P67-SUM(Q67:Z67) -> 347090.26 | AB67: =IF($L67<0,0,IFERROR((AB$2*IFERROR(VLOOKUP(J67,Tabla11[],2,0),0))*($L67/SUM($L$5:$L$46)),0)) -> 24110.994 | AC67: =L67-L67*IFERROR(VLOOKUP(J67,Tabla11[],3,0),0)-Q67-T67-U67-V67-W67-L67*$X$2-(L67*$X$2)*IFERROR(VLOOKUP(J67,Tabla11[],4,0),0)-AB67-Z67 -> 65196.167 | AD67: =AA67-AB67 -> 322979.27 | AE67: =ROUND(AD67-AC67,9) -> 257783.1
B68: Outsourcing | E68: Outsourcing | G68: 3 | H68: Supervisor Regiones | I68: Viña del Mar | J68: París | K68: Valparaiso | L68: =IFERROR(VLOOKUP(CONCATENATE(J68,K68),Ventas!D:H,4,0),0) -> 1454547.2 | M68: =IF(SUM(C68,F68)>0,L68*0.1,0) -> 0 | N68: =SUM(L68:M68) -> 1454547.2 | O68: =N68*IFERROR(VLOOKUP(J68,Tabla11[],3,0),0) -> 509091.51 | P68: =N68-O68 -> 945455.66 | Q68: =IFERROR(G68/SUMIF(I:I,I68,G:G),0)*VLOOKUP(H68,Modelos[],14,0)+IFERROR(G68/SUMIF(I:I,I68,G:G),0)*VLOOKUP(I68,Tabla13[],2,0) -> 123633.06 | R68: =IFERROR(VLOOKUP(A68,Modelos[],IF(B68="EST",15,14),0),0)*C68 -> 0 | S68: =IFERROR(VLOOKUP(D68,Modelos[],IF(E68="EST",15,14),0),0)*F68 -> 0 | T68: =IF($L68<0,0,IFERROR((T$2*IFERROR(VLOOKUP(J68,Tabla11[],2,0),0))*($L68/SUM($L$5:$L$46)),0)) -> 13732.2 | U68: =IF($L68<0,0,IFERROR((U$2*IFERROR(VLOOKUP(J68,Tabla11[],2,0),0))*($L68/SUM($L$5:$L$46)),0)) -> 2670.1501 | V68: =IF($L68<0,0,IFERROR((V$2*IFERROR(VLOOKUP(J68,Tabla11[],2,0),0))*($L68/SUM($L$5:$L$46)),0)) -> 13732.2 | W68: =IF($L68<0,0,IFERROR((W$2*IFERROR(VLOOKUP(J68,Tabla11[],2,0),0))*($L68/SUM($L$5:$L$46)),0)) -> 19072.501 | X68: =P68*$X$2 -> 378182.26 | Y68: =+X68*IFERROR(VLOOKUP(J68,Tabla11[],4,0),0) -> 56727.34 | Z68: =IF(L68>0,$Z$2/12,0) -> 25833.333 | AA68: =P68-SUM(Q68:Z68) -> 311872.61 | AB68: =IF($L68<0,0,IFERROR((AB$2*IFERROR(VLOOKUP(J68,Tabla11[],2,0),0))*($L68/SUM($L$5:$L$46)),0)) -> 21903.542 | AC68: =L68-L68*IFERROR(VLOOKUP(J68,Tabla11[],3,0),0)-Q68-T68-U68-V68-W68-L68*$X$2-(L68*$X$2)*IFERROR(VLOOKUP(J68,Tabla11[],4,0),0)-AB68-Z68 -> 55786.973 | AD68: =AA68-AB68 -> 289969.07 | AE68: =ROUND(AD68-AC68,9) -> 234182.09
B69: Outsourcing | E69: Outsourcing | G69: 3 | H69: Supervisor Santiago | I69: Santiago 03 | J69: París | K69: Quilicura | L69: =IFERROR(VLOOKUP(CONCATENATE(J69,K69),Ventas!D:H,4,0),0) -> 1962162.9 | M69: =IF(SUM(C69,F69)>0,L69*0.1,0) -> 0 | N69: =SUM(L69:M69) -> 1962162.9 | O69: =N69*IFERROR(VLOOKUP(J69,Tabla11[],3,0),0) -> 686757 | P69: =N69-O69 -> 1275405.9 | Q69: =IFERROR(G69/SUMIF(I:I,I69,G:G),0)*VLOOKUP(H69,Modelos[],14,0)+IFERROR(G69/SUMIF(I:I,I69,G:G),0)*VLOOKUP(I69,Tabla13[],2,0) -> 73262.014 | R69: =IFERROR(VLOOKUP(A69,Modelos[],IF(B69="EST",15,14),0),0)*C69 -> 0 | S69: =IFERROR(VLOOKUP(D69,Modelos[],IF(E69="EST",15,14),0),0)*F69 -> 0 | T69: =IF($L69<0,0,IFERROR((T$2*IFERROR(VLOOKUP(J69,Tabla11[],2,0),0))*($L69/SUM($L$5:$L$46)),0)) -> 18524.538 | U69: =IF($L69<0,0,IFERROR((U$2*IFERROR(VLOOKUP(J69,Tabla11[],2,0),0))*($L69/SUM($L$5:$L$46)),0)) -> 3601.9934 | V69: =IF($L69<0,0,IFERROR((V$2*IFERROR(VLOOKUP(J69,Tabla11[],2,0),0))*($L69/SUM($L$5:$L$46)),0)) -> 18524.538 | W69: =IF($L69<0,0,IFERROR((W$2*IFERROR(VLOOKUP(J69,Tabla11[],2,0),0))*($L69/SUM($L$5:$L$46)),0)) -> 25728.524 | X69: =P69*$X$2 -> 510162.34 | Y69: =+X69*IFERROR(VLOOKUP(J69,Tabla11[],4,0),0) -> 76524.352 | Z69: =IF(L69>0,$Z$2/12,0) -> 25833.333 | AA69: =P69-SUM(Q69:Z69) -> 523244.22 | AB69: =IF($L69<0,0,IFERROR((AB$2*IFERROR(VLOOKUP(J69,Tabla11[],2,0),0))*($L69/SUM($L$5:$L$46)),0)) -> 29547.558 | AC69: =L69-L69*IFERROR(VLOOKUP(J69,Tabla11[],3,0),0)-Q69-T69-U69-V69-W69-L69*$X$2-(L69*$X$2)*IFERROR(VLOOKUP(J69,Tabla11[],4,0),0)-AB69-Z69 -> 177788.45 | AD69: =AA69-AB69 -> 493696.67 | AE69: =ROUND(AD69-AC69,9) -> 315908.22
B70: Outsourcing | E70: Outsourcing | G70: 3 | H70: Supervisor Santiago | I70: Santiago 01 | J70: París | K70: Quilin | L70: =IFERROR(VLOOKUP(CONCATENATE(J70,K70),Ventas!D:H,4,0),0) -> 1585349.6 | M70: =IF(SUM(C70,F70)>0,L70*0.1,0) -> 0 | N70: =SUM(L70:M70) -> 1585349.6 | O70: =N70*IFERROR(VLOOKUP(J70,Tabla11[],3,0),0) -> 554872.36 | P70: =N70-O70 -> 1030477.2 | Q70: =IFERROR(G70/SUMIF(I:I,I70,G:G),0)*VLOOKUP(H70,Modelos[],14,0)+IFERROR(G70/SUMIF(I:I,I70,G:G),0)*VLOOKUP(I70,Tabla13[],2,0) -> 69504.988 | R70: =IFERROR(VLOOKUP(A70,Modelos[],IF(B70="EST",15,14),0),0)*C70 -> 0 | S70: =IFERROR(VLOOKUP(D70,Modelos[],IF(E70="EST",15,14),0),0)*F70 -> 0 | T70: =IF($L70<0,0,IFERROR((T$2*IFERROR(VLOOKUP(J70,Tabla11[],2,0),0))*($L70/SUM($L$5:$L$46)),0)) -> 14967.09 | U70: =IF($L70<0,0,IFERROR((U$2*IFERROR(VLOOKUP(J70,Tabla11[],2,0),0))*($L70/SUM($L$5:$L$46)),0)) -> 2910.2675 | V70: =IF($L70<0,0,IFERROR((V$2*IFERROR(VLOOKUP(J70,Tabla11[],2,0),0))*($L70/SUM($L$5:$L$46)),0)) -> 14967.09 | W70: =IF($L70<0,0,IFERROR((W$2*IFERROR(VLOOKUP(J70,Tabla11[],2,0),0))*($L70/SUM($L$5:$L$46)),0)) -> 20787.625 | X70: =P70*$X$2 -> 412190.9 | Y70: =+X70*IFERROR(VLOOKUP(J70,Tabla11[],4,0),0) -> 61828.634 | Z70: =IF(L70>0,$Z$2/12,0) -> 25833.333 | AA70: =P70-SUM(Q70:Z70) -> 407487.32 | AB70: =IF($L70<0,0,IFERROR((AB$2*IFERROR(VLOOKUP(J70,Tabla11[],2,0),0))*($L70/SUM($L$5:$L$46)),0)) -> 23873.253 | AC70: =L70-L70*IFERROR(VLOOKUP(J70,Tabla11[],3,0),0)-Q70-T70-U70-V70-W70-L70*$X$2-(L70*$X$2)*IFERROR(VLOOKUP(J70,Tabla11[],4,0),0)-AB70-Z70 -> 128372.78 | AD70: =AA70-AB70 -> 383614.06 | AE70: =ROUND(AD70-AC70,9) -> 255241.29
B71: Outsourcing | E71: Outsourcing | G71: 3 | H71: Supervisor Santiago | I71: Santiago 01 | J71: París | K71: Portal Nunoa | L71: =IFERROR(VLOOKUP(CONCATENATE(J71,K71),Ventas!D:H,4,0),0) -> 1555424.6 | M71: =IF(SUM(C71,F71)>0,L71*0.1,0) -> 0 | N71: =SUM(L71:M71) -> 1555424.6 | O71: =N71*IFERROR(VLOOKUP(J71,Tabla11[],3,0),0) -> 544398.6 | P71: =N71-O71 -> 1011026 | Q71: =IFERROR(G71/SUMIF(I:I,I71,G:G),0)*VLOOKUP(H71,Modelos[],14,0)+IFERROR(G71/SUMIF(I:I,I71,G:G),0)*VLOOKUP(I71,Tabla13[],2,0) -> 69504.988 | R71: =IFERROR(VLOOKUP(A71,Modelos[],IF(B71="EST",15,14),0),0)*C71 -> 0 | S71: =IFERROR(VLOOKUP(D71,Modelos[],IF(E71="EST",15,14),0),0)*F71 -> 0 | T71: =IF($L71<0,0,IFERROR((T$2*IFERROR(VLOOKUP(J71,Tabla11[],2,0),0))*($L71/SUM($L$5:$L$46)),0)) -> 14684.572 | U71: =IF($L71<0,0,IFERROR((U$2*IFERROR(VLOOKUP(J71,Tabla11[],2,0),0))*($L71/SUM($L$5:$L$46)),0)) -> 2855.3334 | V71: =IF($L71<0,0,IFERROR((V$2*IFERROR(VLOOKUP(J71,Tabla11[],2,0),0))*($L71/SUM($L$5:$L$46)),0)) -> 14684.572 | W71: =IF($L71<0,0,IFERROR((W$2*IFERROR(VLOOKUP(J71,Tabla11[],2,0),0))*($L71/SUM($L$5:$L$46)),0)) -> 20395.238 | X71: =P71*$X$2 -> 404410.39 | Y71: =+X71*IFERROR(VLOOKUP(J71,Tabla11[],4,0),0) -> 60661.559 | Z71: =IF(L71>0,$Z$2/12,0) -> 25833.333 | AA71: =P71-SUM(Q71:Z71) -> 397995.99 | AB71: =IF($L71<0,0,IFERROR((AB$2*IFERROR(VLOOKUP(J71,Tabla11[],2,0),0))*($L71/SUM($L$5:$L$46)),0)) -> 23422.622 | AC71: =L71-L71*IFERROR(VLOOKUP(J71,Tabla11[],3,0),0)-Q71-T71-U71-V71-W71-L71*$X$2-(L71*$X$2)*IFERROR(VLOOKUP(J71,Tabla11[],4,0),0)-AB71-Z71 -> 124150.01 | AD71: =AA71-AB71 -> 374573.37 | AE71: =ROUND(AD71-AC71,9) -> 250423.36
B72: Outsourcing | E72: Outsourcing | G72: 3 | H72: Supervisor Santiago | I72: Santiago 03 | J72: París | K72: San Bernardo | L72: =IFERROR(VLOOKUP(CONCATENATE(J72,K72),Ventas!D:H,4,0),0) -> 1429348.6 | M72: =IF(SUM(C72,F72)>0,L72*0.1,0) -> 0 | N72: =SUM(L72:M72) -> 1429348.6 | O72: =N72*IFERROR(VLOOKUP(J72,Tabla11[],3,0),0) -> 500272 | P72: =N72-O72 -> 929076.57 | Q72: =IFERROR(G72/SUMIF(I:I,I72,G:G),0)*VLOOKUP(H72,Modelos[],14,0)+IFERROR(G72/SUMIF(I:I,I72,G:G),0)*VLOOKUP(I72,Tabla13[],2,0) -> 73262.014 | R72: =IFERROR(VLOOKUP(A72,Modelos[],IF(B72="EST",15,14),0),0)*C72 -> 0 | S72: =IFERROR(VLOOKUP(D72,Modelos[],IF(E72="EST",15,14),0),0)*F72 -> 0 | T72: =IF($L72<0,0,IFERROR((T$2*IFERROR(VLOOKUP(J72,Tabla11[],2,0),0))*($L72/SUM($L$5:$L$46)),0)) -> 13494.304 | U72: =IF($L72<0,0,IFERROR((U$2*IFERROR(VLOOKUP(J72,Tabla11[],2,0),0))*($L72/SUM($L$5:$L$46)),0)) -> 2623.8924 | V72: =IF($L72<0,0,IFERROR((V$2*IFERROR(VLOOKUP(J72,Tabla11[],2,0),0))*($L72/SUM($L$5:$L$46)),0)) -> 13494.304 | W72: =IF($L72<0,0,IFERROR((W$2*IFERROR(VLOOKUP(J72,Tabla11[],2,0),0))*($L72/SUM($L$5:$L$46)),0)) -> 18742.088 | X72: =P72*$X$2 -> 371630.63 | Y72: =+X72*IFERROR(VLOOKUP(J72,Tabla11[],4,0),0) -> 55744.594 | Z72: =IF(L72>0,$Z$2/12,0) -> 25833.333 | AA72: =P72-SUM(Q72:Z72) -> 354251.41 | AB72: =IF($L72<0,0,IFERROR((AB$2*IFERROR(VLOOKUP(J72,Tabla11[],2,0),0))*($L72/SUM($L$5:$L$46)),0)) -> 21524.085 | AC72: =L72-L72*IFERROR(VLOOKUP(J72,Tabla11[],3,0),0)-Q72-T72-U72-V72-W72-L72*$X$2-(L72*$X$2)*IFERROR(VLOOKUP(J72,Tabla11[],4,0),0)-AB72-Z72 -> 102602.21 | AD72: =AA72-AB72 -> 332727.33 | AE72: =ROUND(AD72-AC72,9) -> 230125.12
B73: Outsourcing | E73: Outsourcing | G73: 3 | H73: Supervisor Santiago | I73: Santiago 03 | J73: París | K73: Mall Paseo Estacion | L73: =IFERROR(VLOOKUP(CONCATENATE(J73,K73),Ventas!D:H,4,0),0) -> 1413315.9 | M73: =IF(SUM(C73,F73)>0,L73*0.1,0) -> 0 | N73: =SUM(L73:M73) -> 1413315.9 | O73: =N73*IFERROR(VLOOKUP(J73,Tabla11[],3,0),0) -> 494660.56 | P73: =N73-O73 -> 918655.33 | Q73: =IFERROR(G73/SUMIF(I:I,I73,G:G),0)*VLOOKUP(H73,Modelos[],14,0)+IFERROR(G73/SUMIF(I:I,I73,G:G),0)*VLOOKUP(I73,Tabla13[],2,0) -> 73262.014 | R73: =IFERROR(VLOOKUP(A73,Modelos[],IF(B73="EST",15,14),0),0)*C73 -> 0 | S73: =IFERROR(VLOOKUP(D73,Modelos[],IF(E73="EST",15,14),0),0)*F73 -> 0 | T73: =IF($L73<0,0,IFERROR((T$2*IFERROR(VLOOKUP(J73,Tabla11[],2,0),0))*($L73/SUM($L$5:$L$46)),0)) -> 13342.941 | U73: =IF($L73<0,0,IFERROR((U$2*IFERROR(VLOOKUP(J73,Tabla11[],2,0),0))*($L73/SUM($L$5:$L$46)),0)) -> 2594.4608 | V73: =IF($L73<0,0,IFERROR((V$2*IFERROR(VLOOKUP(J73,Tabla11[],2,0),0))*($L73/SUM($L$5:$L$46)),0)) -> 13342.941 | W73: =IF($L73<0,0,IFERROR((W$2*IFERROR(VLOOKUP(J73,Tabla11[],2,0),0))*($L73/SUM($L$5:$L$46)),0)) -> 18531.863 | X73: =P73*$X$2 -> 367462.13 | Y73: =+X73*IFERROR(VLOOKUP(J73,Tabla11[],4,0),0) -> 55119.32 | Z73: =IF(L73>0,$Z$2/12,0) -> 25833.333 | AA73: =P73-SUM(Q73:Z73) -> 349166.33 | AB73: =IF($L73<0,0,IFERROR((AB$2*IFERROR(VLOOKUP(J73,Tabla11[],2,0),0))*($L73/SUM($L$5:$L$46)),0)) -> 21282.654 | AC73: =L73-L73*IFERROR(VLOOKUP(J73,Tabla11[],3,0),0)-Q73-T73-U73-V73-W73-L73*$X$2-(L73*$X$2)*IFERROR(VLOOKUP(J73,Tabla11[],4,0),0)-AB73-Z73 -> 100339.81 | AD73: =AA73-AB73 -> 327883.67 | AE73: =ROUND(AD73-AC73,9) -> 227543.86
B74: Outsourcing | E74: Outsourcing | G74: 3 | H74: Supervisor Santiago | I74: Santiago 01 | J74: París | K74: La Dehesa | L74: =IFERROR(VLOOKUP(CONCATENATE(J74,K74),Ventas!D:H,4,0),0) -> 1632686.5 | M74: =IF(SUM(C74,F74)>0,L74*0.1,0) -> 0 | N74: =SUM(L74:M74) -> 1632686.5 | O74: =N74*IFERROR(VLOOKUP(J74,Tabla11[],3,0),0) -> 571440.27 | P74: =N74-O74 -> 1061246.2 | Q74: =IFERROR(G74/SUMIF(I:I,I74,G:G),0)*VLOOKUP(H74,Modelos[],14,0)+IFERROR(G74/SUMIF(I:I,I74,G:G),0)*VLOOKUP(I74,Tabla13[],2,0) -> 69504.988 | R74: =IFERROR(VLOOKUP(A74,Modelos[],IF(B74="EST",15,14),0),0)*C74 -> 0 | S74: =IFERROR(VLOOKUP(D74,Modelos[],IF(E74="EST",15,14),0),0)*F74 -> 0 | T74: =IF($L74<0,0,IFERROR((T$2*IFERROR(VLOOKUP(J74,Tabla11[],2,0),0))*($L74/SUM($L$5:$L$46)),0)) -> 15413.992 | U74: =IF($L74<0,0,IFERROR((U$2*IFERROR(VLOOKUP(J74,Tabla11[],2,0),0))*($L74/SUM($L$5:$L$46)),0)) -> 2997.1651 | V74: =IF($L74<0,0,IFERROR((V$2*IFERROR(VLOOKUP(J74,Tabla11[],2,0),0))*($L74/SUM($L$5:$L$46)),0)) -> 15413.992 | W74: =IF($L74<0,0,IFERROR((W$2*IFERROR(VLOOKUP(J74,Tabla11[],2,0),0))*($L74/SUM($L$5:$L$46)),0)) -> 21408.322 | X74: =P74*$X$2 -> 424498.49 | Y74: =+X74*IFERROR(VLOOKUP(J74,Tabla11[],4,0),0) -> 63674.773 | Z74: =IF(L74>0,$Z$2/12,0) -> 25833.333 | AA74: =P74-SUM(Q74:Z74) -> 422501.17 | AB74: =IF($L74<0,0,IFERROR((AB$2*IFERROR(VLOOKUP(J74,Tabla11[],2,0),0))*($L74/SUM($L$5:$L$46)),0)) -> 24586.083 | AC74: =L74-L74*IFERROR(VLOOKUP(J74,Tabla11[],3,0),0)-Q74-T74-U74-V74-W74-L74*$X$2-(L74*$X$2)*IFERROR(VLOOKUP(J74,Tabla11[],4,0),0)-AB74-Z74 -> 135052.56 | AD74: =AA74-AB74 -> 397915.08 | AE74: =ROUND(AD74-AC74,9) -> 262862.53
B75: Outsourcing | E75: Outsourcing | G75: 3 | H75: Supervisor Regiones | I75: VI-VII | J75: París | K75: Centrorex Rancagua | L75: =IFERROR(VLOOKUP(CONCATENATE(J75,K75),Ventas!D:H,4,0),0) -> 458982.59 | M75: =IF(SUM(C75,F75)>0,L75*0.1,0) -> 0 | N75: =SUM(L75:M75) -> 458982.59 | O75: =N75*IFERROR(VLOOKUP(J75,Tabla11[],3,0),0) -> 160643.91 | P75: =N75-O75 -> 298338.68 | Q75: =IFERROR(G75/SUMIF(I:I,I75,G:G),0)*VLOOKUP(H75,Modelos[],14,0)+IFERROR(G75/SUMIF(I:I,I75,G:G),0)*VLOOKUP(I75,Tabla13[],2,0) -> 154942.83 | R75: =IFERROR(VLOOKUP(A75,Modelos[],IF(B75="EST",15,14),0),0)*C75 -> 0 | S75: =IFERROR(VLOOKUP(D75,Modelos[],IF(E75="EST",15,14),0),0)*F75 -> 0 | T75: =IF($L75<0,0,IFERROR((T$2*IFERROR(VLOOKUP(J75,Tabla11[],2,0),0))*($L75/SUM($L$5:$L$46)),0)) -> 4333.198 | U75: =IF($L75<0,0,IFERROR((U$2*IFERROR(VLOOKUP(J75,Tabla11[],2,0),0))*($L75/SUM($L$5:$L$46)),0)) -> 842.56628 | V75: =IF($L75<0,0,IFERROR((V$2*IFERROR(VLOOKUP(J75,Tabla11[],2,0),0))*($L75/SUM($L$5:$L$46)),0)) -> 4333.198 | W75: =IF($L75<0,0,IFERROR((W$2*IFERROR(VLOOKUP(J75,Tabla11[],2,0),0))*($L75/SUM($L$5:$L$46)),0)) -> 6018.3306 | X75: =P75*$X$2 -> 119335.47 | Y75: =+X75*IFERROR(VLOOKUP(J75,Tabla11[],4,0),0) -> 17900.321 | Z75: =IF(L75>0,$Z$2/12,0) -> 25833.333 | AA75: =P75-SUM(Q75:Z75) -> -35200.572 | AB75: =IF($L75<0,0,IFERROR((AB$2*IFERROR(VLOOKUP(J75,Tabla11[],2,0),0))*($L75/SUM($L$5:$L$46)),0)) -> 6911.6662 | AC75: =L75-L75*IFERROR(VLOOKUP(J75,Tabla11[],3,0),0)-Q75-T75-U75-V75-W75-L75*$X$2-(L75*$X$2)*IFERROR(VLOOKUP(J75,Tabla11[],4,0),0)-AB75-Z75 -> -116008.43 | AD75: =AA75-AB75 -> -42112.238 | AE75: =ROUND(AD75-AC75,9) -> 73896.197
B76: Outsourcing | E76: Outsourcing | G76: 3 | H76: Supervisor Regiones | I76: La Serena | J76: París | K76: Coquimbo | L76: =IFERROR(VLOOKUP(CONCATENATE(J76,K76),Ventas!D:H,4,0),0) -> 630502.55 | M76: =IF(SUM(C76,F76)>0,L76*0.1,0) -> 0 | N76: =SUM(L76:M76) -> 630502.55 | O76: =N76*IFERROR(VLOOKUP(J76,Tabla11[],3,0),0) -> 220675.89 | P76: =N76-O76 -> 409826.66 | Q76: =IFERROR(G76/SUMIF(I:I,I76,G:G),0)*VLOOKUP(H76,Modelos[],14,0)+IFERROR(G76/SUMIF(I:I,I76,G:G),0)*VLOOKUP(I76,Tabla13[],2,0) -> 161601.88 | R76: =IFERROR(VLOOKUP(A76,Modelos[],IF(B76="EST",15,14),0),0)*C76 -> 0 | S76: =IFERROR(VLOOKUP(D76,Modelos[],IF(E76="EST",15,14),0),0)*F76 -> 0 | T76: =IF($L76<0,0,IFERROR((T$2*IFERROR(VLOOKUP(J76,Tabla11[],2,0),0))*($L76/SUM($L$5:$L$46)),0)) -> 5952.4968 | U76: =IF($L76<0,0,IFERROR((U$2*IFERROR(VLOOKUP(J76,Tabla11[],2,0),0))*($L76/SUM($L$5:$L$46)),0)) -> 1157.4299 | V76: =IF($L76<0,0,IFERROR((V$2*IFERROR(VLOOKUP(J76,Tabla11[],2,0),0))*($L76/SUM($L$5:$L$46)),0)) -> 5952.4968 | W76: =IF($L76<0,0,IFERROR((W$2*IFERROR(VLOOKUP(J76,Tabla11[],2,0),0))*($L76/SUM($L$5:$L$46)),0)) -> 8267.3567 | X76: =P76*$X$2 -> 163930.66 | Y76: =+X76*IFERROR(VLOOKUP(J76,Tabla11[],4,0),0) -> 24589.6 | Z76: =IF(L76>0,$Z$2/12,0) -> 25833.333 | AA76: =P76-SUM(Q76:Z76) -> 12541.403 | AB76: =IF($L76<0,0,IFERROR((AB$2*IFERROR(VLOOKUP(J76,Tabla11[],2,0),0))*($L76/SUM($L$5:$L$46)),0)) -> 9494.5283 | AC76: =L76-L76*IFERROR(VLOOKUP(J76,Tabla11[],3,0),0)-Q76-T76-U76-V76-W76-L76*$X$2-(L76*$X$2)*IFERROR(VLOOKUP(J76,Tabla11[],4,0),0)-AB76-Z76 -> -98464.036 | AD76: =AA76-AB76 -> 3046.8749 | AE76: =ROUND(AD76-AC76,9) -> 101510.91
B77: Outsourcing | E77: Outsourcing | G77: 3 | H77: Supervisor Santiago | I77: Santiago 01 | J77: París | K77: Huechuraba | L77: =IFERROR(VLOOKUP(CONCATENATE(J77,K77),Ventas!D:H,4,0),0) -> 1210110.8 | M77: =IF(SUM(C77,F77)>0,L77*0.1,0) -> 0 | N77: =SUM(L77:M77) -> 1210110.8 | O77: =N77*IFERROR(VLOOKUP(J77,Tabla11[],3,0),0) -> 423538.76 | P77: =N77-O77 -> 786571.99 | Q77: =IFERROR(G77/SUMIF(I:I,I77,G:G),0)*VLOOKUP(H77,Modelos[],14,0)+IFERROR(G77/SUMIF(I:I,I77,G:G),0)*VLOOKUP(I77,Tabla13[],2,0) -> 69504.988 | R77: =IFERROR(VLOOKUP(A77,Modelos[],IF(B77="EST",15,14),0),0)*C77 -> 0 | S77: =IFERROR(VLOOKUP(D77,Modelos[],IF(E77="EST",15,14),0),0)*F77 -> 0 | T77: =IF($L77<0,0,IFERROR((T$2*IFERROR(VLOOKUP(J77,Tabla11[],2,0),0))*($L77/SUM($L$5:$L$46)),0)) -> 11424.506 | U77: =IF($L77<0,0,IFERROR((U$2*IFERROR(VLOOKUP(J77,Tabla11[],2,0),0))*($L77/SUM($L$5:$L$46)),0)) -> 2221.4318 | V77: =IF($L77<0,0,IFERROR((V$2*IFERROR(VLOOKUP(J77,Tabla11[],2,0),0))*($L77/SUM($L$5:$L$46)),0)) -> 11424.506 | W77: =IF($L77<0,0,IFERROR((W$2*IFERROR(VLOOKUP(J77,Tabla11[],2,0),0))*($L77/SUM($L$5:$L$46)),0)) -> 15867.37 | X77: =P77*$X$2 -> 314628.8 | Y77: =+X77*IFERROR(VLOOKUP(J77,Tabla11[],4,0),0) -> 47194.319 | Z77: =IF(L77>0,$Z$2/12,0) -> 25833.333 | AA77: =P77-SUM(Q77:Z77) -> 288472.74 | AB77: =IF($L77<0,0,IFERROR((AB$2*IFERROR(VLOOKUP(J77,Tabla11[],2,0),0))*($L77/SUM($L$5:$L$46)),0)) -> 18222.656 | AC77: =L77-L77*IFERROR(VLOOKUP(J77,Tabla11[],3,0),0)-Q77-T77-U77-V77-W77-L77*$X$2-(L77*$X$2)*IFERROR(VLOOKUP(J77,Tabla11[],4,0),0)-AB77-Z77 -> 75422.252 | AD77: =AA77-AB77 -> 270250.08 | AE77: =ROUND(AD77-AC77,9) -> 194827.83
B78: Outsourcing | E78: Outsourcing | G78: 3 | H78: Supervisor Santiago | I78: Santiago 01 | J78: París | K78: Lyon | L78: =IFERROR(VLOOKUP(CONCATENATE(J78,K78),Ventas!D:H,4,0),0) -> 971037 | M78: =IF(SUM(C78,F78)>0,L78*0.1,0) -> 0 | N78: =SUM(L78:M78) -> 971037 | O78: =N78*IFERROR(VLOOKUP(J78,Tabla11[],3,0),0) -> 339862.95 | P78: =N78-O78 -> 631174.05 | Q78: =IFERROR(G78/SUMIF(I:I,I78,G:G),0)*VLOOKUP(H78,Modelos[],14,0)+IFERROR(G78/SUMIF(I:I,I78,G:G),0)*VLOOKUP(I78,Tabla13[],2,0) -> 69504.988 | R78: =IFERROR(VLOOKUP(A78,Modelos[],IF(B78="EST",15,14),0),0)*C78 -> 0 | S78: =IFERROR(VLOOKUP(D78,Modelos[],IF(E78="EST",15,14),0),0)*F78 -> 0 | T78: =IF($L78<0,0,IFERROR((T$2*IFERROR(VLOOKUP(J78,Tabla11[],2,0),0))*($L78/SUM($L$5:$L$46)),0)) -> 9167.4406 | U78: =IF($L78<0,0,IFERROR((U$2*IFERROR(VLOOKUP(J78,Tabla11[],2,0),0))*($L78/SUM($L$5:$L$46)),0)) -> 1782.5579 | V78: =IF($L78<0,0,IFERROR((V$2*IFERROR(VLOOKUP(J78,Tabla11[],2,0),0))*($L78/SUM($L$5:$L$46)),0)) -> 9167.4406 | W78: =IF($L78<0,0,IFERROR((W$2*IFERROR(VLOOKUP(J78,Tabla11[],2,0),0))*($L78/SUM($L$5:$L$46)),0)) -> 12732.556 | X78: =P78*$X$2 -> 252469.62 | Y78: =+X78*IFERROR(VLOOKUP(J78,Tabla11[],4,0),0) -> 37870.443 | Z78: =IF(L78>0,$Z$2/12,0) -> 25833.333 | AA78: =P78-SUM(Q78:Z78) -> 212645.67 | AB78: =IF($L78<0,0,IFERROR((AB$2*IFERROR(VLOOKUP(J78,Tabla11[],2,0),0))*($L78/SUM($L$5:$L$46)),0)) -> 14622.523 | AC78: =L78-L78*IFERROR(VLOOKUP(J78,Tabla11[],3,0),0)-Q78-T78-U78-V78-W78-L78*$X$2-(L78*$X$2)*IFERROR(VLOOKUP(J78,Tabla11[],4,0),0)-AB78-Z78 -> 41686.191 | AD78: =AA78-AB78 -> 198023.15 | AE78: =ROUND(AD78-AC78,9) -> 156336.96
... B91: Outsourcing | E91: Outsourcing | G91: 3 | H91: Supervisor Part | I91: Iquique | J91: Johnson | K91: Iquique | L91: =IFERROR(VLOOKUP(CONCATENATE(J91,K91),Ventas!D:H,4,0),0) -> 926874.07 | M91: =IF(SUM(C91,F91)>0,L91*0.1,0) -> 0 | N91: =SUM(L91:M91) -> 926874.07 | O91: =N91*IFERROR(VLOOKUP(J91,Tabla11[],3,0),0) -> 324405.92 | P91: =N91-O91 -> 602468.14 | Q91: =IFERROR(G91/SUMIF(I:I,I91,G:G),0)*VLOOKUP(H91,Modelos[],14,0)+IFERROR(G91/SUMIF(I:I,I91,G:G),0)*VLOOKUP(I91,Tabla13[],2,0) -> 134909.42 | R91: =IFERROR(VLOOKUP(A91,Modelos[],IF(B91="EST",15,14),0),0)*C91 -> 0 | S91: =IFERROR(VLOOKUP(D91,Modelos[],IF(E91="EST",15,14),0),0)*F91 -> 0 | T91: =IF($L91<0,0,IFERROR((T$2*IFERROR(VLOOKUP(J91,Tabla11[],2,0),0))*($L91/SUM($L$5:$L$46)),0)) -> 3088.4131 | U91: =IF($L91<0,0,IFERROR((U$2*IFERROR(VLOOKUP(J91,Tabla11[],2,0),0))*($L91/SUM($L$5:$L$46)),0)) -> 600.52477 | V91: =IF($L91<0,0,IFERROR((V$2*IFERROR(VLOOKUP(J91,Tabla11[],2,0),0))*($L91/SUM($L$5:$L$46)),0)) -> 3088.4131 | W91: =IF($L91<0,0,IFERROR((W$2*IFERROR(VLOOKUP(J91,Tabla11[],2,0),0))*($L91/SUM($L$5:$L$46)),0)) -> 4289.4626 | X91: =P91*$X$2 -> 240987.26 | Y91: =+X91*IFERROR(VLOOKUP(J91,Tabla11[],4,0),0) -> 36148.089 | Z91: =IF(L91>0,$Z$2/12,0) -> 25833.333 | AA91: =P91-SUM(Q91:Z91) -> 153523.23 | AB91: =IF($L91<0,0,IFERROR((AB$2*IFERROR(VLOOKUP(J91,Tabla11[],2,0),0))*($L91/SUM($L$5:$L$46)),0)) -> 4926.1724 | AC91: =L91-L91*IFERROR(VLOOKUP(J91,Tabla11[],3,0),0)-Q91-T91-U91-V91-W91-L91*$X$2-(L91*$X$2)*IFERROR(VLOOKUP(J91,Tabla11[],4,0),0)-AB91-Z91 -> -629.66545 | AD91: =AA91-AB91 -> 148597.06 | AE91: =ROUND(AD91-AC91,9) -> 149226.72
A92: Vendedor 1/2 3 días | B92: Outsourcing | C92: 0.33 | E92: Outsourcing | G92: 0 | H92: Supervisor Regiones | I92: Concepción | J92: Johnson | K92: Chillan | L92: =IFERROR(VLOOKUP(CONCATENATE(J92,K92),Ventas!D:H,4,0),0) -> 860007.03 | M92: =IF(SUM(C92,F92)>0,L92*0.1,0) -> 86000.703 | N92: =SUM(L92:M92) -> 946007.74 | O92: =N92*IFERROR(VLOOKUP(J92,Tabla11[],3,0),0) -> 331102.71 | P92: =N92-O92 -> 614905.03 | Q92: =IFERROR(G92/SUMIF(I:I,I92,G:G),0)*VLOOKUP(H92,Modelos[],14,0)+IFERROR(G92/SUMIF(I:I,I92,G:G),0)*VLOOKUP(I92,Tabla13[],2,0) -> 0 | R92: =IFERROR(VLOOKUP(A92,Modelos[],IF(B92="EST",15,14),0),0)*C92 -> 67493.844 | S92: =IFERROR(VLOOKUP(D92,Modelos[],IF(E92="EST",15,14),0),0)*F92 -> 0 | T92: =IF($L92<0,0,IFERROR((T$2*IFERROR(VLOOKUP(J92,Tabla11[],2,0),0))*($L92/SUM($L$5:$L$46)),0)) -> 2865.6072 | U92: =IF($L92<0,0,IFERROR((U$2*IFERROR(VLOOKUP(J92,Tabla11[],2,0),0))*($L92/SUM($L$5:$L$46)),0)) -> 557.2014 | V92: =IF($L92<0,0,IFERROR((V$2*IFERROR(VLOOKUP(J92,Tabla11[],2,0),0))*($L92/SUM($L$5:$L$46)),0)) -> 2865.6072 | W92: =IF($L92<0,0,IFERROR((W$2*IFERROR(VLOOKUP(J92,Tabla11[],2,0),0))*($L92/SUM($L$5:$L$46)),0)) -> 3980.01 | X92: =P92*$X$2 -> 245962.01 | Y92: =+X92*IFERROR(VLOOKUP(J92,Tabla11[],4,0),0) -> 36894.302 | Z92: =IF(L92>0,$Z$2/12,0) -> 25833.333 | AA92: =P92-SUM(Q92:Z92) -> 228453.11 | AB92: =IF($L92<0,0,IFERROR((AB$2*IFERROR(VLOOKUP(J92,Tabla11[],2,0),0))*($L92/SUM($L$5:$L$46)),0)) -> 4570.7859 | AC92: =L92-L92*IFERROR(VLOOKUP(J92,Tabla11[],3,0),0)-Q92-T92-U92-V92-W92-L92*$X$2-(L92*$X$2)*IFERROR(VLOOKUP(J92,Tabla11[],4,0),0)-AB92-Z92 -> 122728.79 | AD92: =AA92-AB92 -> 223882.33 | AE92: =ROUND(AD92-AC92,9) -> 101153.54
B93: Outsourcing | E93: Outsourcing | G93: 3 | H93: Supervisor Part | I93: Arica | J93: Johnson | K93: Arica | L93: =IFERROR(VLOOKUP(CONCATENATE(J93,K93),Ventas!D:H,4,0),0) -> 757061.76 | M93: =IF(SUM(C93,F93)>0,L93*0.1,0) -> 0 | N93: =SUM(L93:M93) -> 757061.76 | O93: =N93*IFERROR(VLOOKUP(J93,Tabla11[],3,0),0) -> 264971.62 | P93: =N93-O93 -> 492090.14 | Q93: =IFERROR(G93/SUMIF(I:I,I93,G:G),0)*VLOOKUP(H93,Modelos[],14,0)+IFERROR(G93/SUMIF(I:I,I93,G:G),0)*VLOOKUP(I93,Tabla13[],2,0) -> 121576.09 | R93: =IFERROR(VLOOKUP(A93,Modelos[],IF(B93="EST",15,14),0),0)*C93 -> 0 | S93: =IFERROR(VLOOKUP(D93,Modelos[],IF(E93="EST",15,14),0),0)*F93 -> 0 | T93: =IF($L93<0,0,IFERROR((T$2*IFERROR(VLOOKUP(J93,Tabla11[],2,0),0))*($L93/SUM($L$5:$L$46)),0)) -> 2522.5859 | U93: =IF($L93<0,0,IFERROR((U$2*IFERROR(VLOOKUP(J93,Tabla11[],2,0),0))*($L93/SUM($L$5:$L$46)),0)) -> 490.50281 | V93: =IF($L93<0,0,IFERROR((V$2*IFERROR(VLOOKUP(J93,Tabla11[],2,0),0))*($L93/SUM($L$5:$L$46)),0)) -> 2522.5859 | W93: =IF($L93<0,0,IFERROR((W$2*IFERROR(VLOOKUP(J93,Tabla11[],2,0),0))*($L93/SUM($L$5:$L$46)),0)) -> 3503.5915 | X93: =P93*$X$2 -> 196836.06 | Y93: =+X93*IFERROR(VLOOKUP(J93,Tabla11[],4,0),0) -> 29525.409 | Z93: =IF(L93>0,$Z$2/12,0) -> 25833.333 | AA93: =P93-SUM(Q93:Z93) -> 109279.99 | AB93: =IF($L93<0,0,IFERROR((AB$2*IFERROR(VLOOKUP(J93,Tabla11[],2,0),0))*($L93/SUM($L$5:$L$46)),0)) -> 4023.6499 | AC93: =L93-L93*IFERROR(VLOOKUP(J93,Tabla11[],3,0),0)-Q93-T93-U93-V93-W93-L93*$X$2-(L93*$X$2)*IFERROR(VLOOKUP(J93,Tabla11[],4,0),0)-AB93-Z93 -> -16630.601 | AD93: =AA93-AB93 -> 105256.34 | AE93: =ROUND(AD93-AC93,9) -> 121886.94
B94: Outsourcing | E94: Outsourcing | G94: 3 | H94: Supervisor Part | I94: Copiapó | J94: Johnson | K94: Copiapo | L94: =IFERROR(VLOOKUP(CONCATENATE(J94,K94),Ventas!D:H,4,0),0) -> 734687.91 | M94: =IF(SUM(C94,F94)>0,L94*0.1,0) -> 0 | N94: =SUM(L94:M94) -> 734687.91 | O94: =N94*IFERROR(VLOOKUP(J94,Tabla11[],3,0),0) -> 257140.77 | P94: =N94-O94 -> 477547.14 | Q94: =IFERROR(G94/SUMIF(I:I,I94,G:G),0)*VLOOKUP(H94,Modelos[],14,0)+IFERROR(G94/SUMIF(I:I,I94,G:G),0)*VLOOKUP(I94,Tabla13[],2,0) -> 128242.75 | R94: =IFERROR(VLOOKUP(A94,Modelos[],IF(B94="EST",15,14),0),0)*C94 -> 0 | S94: =IFERROR(VLOOKUP(D94,Modelos[],IF(E94="EST",15,14),0),0)*F94 -> 0 | T94: =IF($L94<0,0,IFERROR((T$2*IFERROR(VLOOKUP(J94,Tabla11[],2,0),0))*($L94/SUM($L$5:$L$46)),0)) -> 2448.0346 | U94: =IF($L94<0,0,IFERROR((U$2*IFERROR(VLOOKUP(J94,Tabla11[],2,0),0))*($L94/SUM($L$5:$L$46)),0)) -> 476.00672 | V94: =IF($L94<0,0,IFERROR((V$2*IFERROR(VLOOKUP(J94,Tabla11[],2,0),0))*($L94/SUM($L$5:$L$46)),0)) -> 2448.0346 | W94: =IF($L94<0,0,IFERROR((W$2*IFERROR(VLOOKUP(J94,Tabla11[],2,0),0))*($L94/SUM($L$5:$L$46)),0)) -> 3400.048 | X94: =P94*$X$2 -> 191018.86 | Y94: =+X94*IFERROR(VLOOKUP(J94,Tabla11[],4,0),0) -> 28652.829 | Z94: =IF(L94>0,$Z$2/12,0) -> 25833.333 | AA94: =P94-SUM(Q94:Z94) -> 95027.248 | AB94: =IF($L94<0,0,IFERROR((AB$2*IFERROR(VLOOKUP(J94,Tabla11[],2,0),0))*($L94/SUM($L$5:$L$46)),0)) -> 3904.7368 | AC94: =L94-L94*IFERROR(VLOOKUP(J94,Tabla11[],3,0),0)-Q94-T94-U94-V94-W94-L94*$X$2-(L94*$X$2)*IFERROR(VLOOKUP(J94,Tabla11[],4,0),0)-AB94-Z94 -> -27162.243 | AD94: =AA94-AB94 -> 91122.511 | AE94: =ROUND(AD94-AC94,9) -> 118284.75
B95: Outsourcing | E95: Outsourcing | G95: 3 | H95: Supervisor Regiones | I95: V° Interior | J95: Johnson | K95: San Felipe | L95: =IFERROR(VLOOKUP(CONCATENATE(J95,K95),Ventas!D:H,4,0),0) -> 682280.44 | M95: =IF(SUM(C95,F95)>0,L95*0.1,0) -> 0 | N95: =SUM(L95:M95) -> 682280.44 | O95: =N95*IFERROR(VLOOKUP(J95,Tabla11[],3,0),0) -> 238798.15 | P95: =N95-O95 -> 443482.29 | Q95: =IFERROR(G95/SUMIF(I:I,I95,G:G),0)*VLOOKUP(H95,Modelos[],14,0)+IFERROR(G95/SUMIF(I:I,I95,G:G),0)*VLOOKUP(I95,Tabla13[],2,0) -> 179573.44 | R95: =IFERROR(VLOOKUP(A95,Modelos[],IF(B95="EST",15,14),0),0)*C95 -> 0 | S95: =IFERROR(VLOOKUP(D95,Modelos[],IF(E95="EST",15,14),0),0)*F95 -> 0 | T95: =IF($L95<0,0,IFERROR((T$2*IFERROR(VLOOKUP(J95,Tabla11[],2,0),0))*($L95/SUM($L$5:$L$46)),0)) -> 2273.409 | U95: =IF($L95<0,0,IFERROR((U$2*IFERROR(VLOOKUP(J95,Tabla11[],2,0),0))*($L95/SUM($L$5:$L$46)),0)) -> 442.05175 | V95: =IF($L95<0,0,IFERROR((V$2*IFERROR(VLOOKUP(J95,Tabla11[],2,0),0))*($L95/SUM($L$5:$L$46)),0)) -> 2273.409 | W95: =IF($L95<0,0,IFERROR((W$2*IFERROR(VLOOKUP(J95,Tabla11[],2,0),0))*($L95/SUM($L$5:$L$46)),0)) -> 3157.5125 | X95: =P95*$X$2 -> 177392.91 | Y95: =+X95*IFERROR(VLOOKUP(J95,Tabla11[],4,0),0) -> 26608.937 | Z95: =IF(L95>0,$Z$2/12,0) -> 25833.333 | AA95: =P95-SUM(Q95:Z95) -> 25927.277 | AB95: =IF($L95<0,0,IFERROR((AB$2*IFERROR(VLOOKUP(J95,Tabla11[],2,0),0))*($L95/SUM($L$5:$L$46)),0)) -> 3626.2003 | AC95: =L95-L95*IFERROR(VLOOKUP(J95,Tabla11[],3,0),0)-Q95-T95-U95-V95-W95-L95*$X$2-(L95*$X$2)*IFERROR(VLOOKUP(J95,Tabla11[],4,0),0)-AB95-Z95 -> -87546.074 | AD95: =AA95-AB95 -> 22301.076 | AE95: =ROUND(AD95-AC95,9) -> 109847.15
B96: Outsourcing | E96: Outsourcing | G96: 3 | H96: Supervisor Santiago | I96: Santiago 03 | J96: Mega Johnson | K96: San Bernardo | L96: =IFERROR(VLOOKUP(CONCATENATE(J96,K96),Ventas!D:H,4,0),0) -> 726045.71 | M96: =IF(SUM(C96,F96)>0,L96*0.1,0) -> 0 | N96: =SUM(L96:M96) -> 726045.71 | O96: =N96*IFERROR(VLOOKUP(J96,Tabla11[],3,0),0) -> 254116 | P96: =N96-O96 -> 471929.71 | Q96: =IFERROR(G96/SUMIF(I:I,I96,G:G),0)*VLOOKUP(H96,Modelos[],14,0)+IFERROR(G96/SUMIF(I:I,I96,G:G),0)*VLOOKUP(I96,Tabla13[],2,0) -> 73262.014 | R96: =IFERROR(VLOOKUP(A96,Modelos[],IF(B96="EST",15,14),0),0)*C96 -> 0 | S96: =IFERROR(VLOOKUP(D96,Modelos[],IF(E96="EST",15,14),0),0)*F96 -> 0 | T96: =IF($L96<0,0,IFERROR((T$2*IFERROR(VLOOKUP(J96,Tabla11[],2,0),0))*($L96/SUM($L$5:$L$46)),0)) -> 2419.2381 | U96: =IF($L96<0,0,IFERROR((U$2*IFERROR(VLOOKUP(J96,Tabla11[],2,0),0))*($L96/SUM($L$5:$L$46)),0)) -> 470.40741 | V96: =IF($L96<0,0,IFERROR((V$2*IFERROR(VLOOKUP(J96,Tabla11[],2,0),0))*($L96/SUM($L$5:$L$46)),0)) -> 2419.2381 | W96: =IF($L96<0,0,IFERROR((W$2*IFERROR(VLOOKUP(J96,Tabla11[],2,0),0))*($L96/SUM($L$5:$L$46)),0)) -> 3360.053 | X96: =P96*$X$2 -> 188771.89 | Y96: =+X96*IFERROR(VLOOKUP(J96,Tabla11[],4,0),0) -> 28315.783 | Z96: =IF(L96>0,$Z$2/12,0) -> 25833.333 | AA96: =P96-SUM(Q96:Z96) -> 147077.76 | AB96: =IF($L96<0,0,IFERROR((AB$2*IFERROR(VLOOKUP(J96,Tabla11[],2,0),0))*($L96/SUM($L$5:$L$46)),0)) -> 3858.8051 | AC96: =L96-L96*IFERROR(VLOOKUP(J96,Tabla11[],3,0),0)-Q96-T96-U96-V96-W96-L96*$X$2-(L96*$X$2)*IFERROR(VLOOKUP(J96,Tabla11[],4,0),0)-AB96-Z96 -> 26325.597 | AD96: =AA96-AB96 -> 143218.96 | AE96: =ROUND(AD96-AC96,9) -> 116893.36
B97: Outsourcing | E97: Outsourcing | G97: 3 | H97: Supervisor Santiago | I97: Santiago 02 | J97: Mega Johnson | K97: Puente Alto | L97: =IFERROR(VLOOKUP(CONCATENATE(J97,K97),Ventas!D:H,4,0),0) -> 604836.04 | M97: =IF(SUM(C97,F97)>0,L97*0.1,0) -> 0 | N97: =SUM(L97:M97) -> 604836.04 | O97: =N97*IFERROR(VLOOKUP(J97,Tabla11[],3,0),0) -> 211692.62 | P97: =N97-O97 -> 393143.43 | Q97: =IFERROR(G97/SUMIF(I:I,I97,G:G),0)*VLOOKUP(H97,Modelos[],14,0)+IFERROR(G97/SUMIF(I:I,I97,G:G),0)*VLOOKUP(I97,Tabla13[],2,0) -> 69504.988 | R97: =IFERROR(VLOOKUP(A97,Modelos[],IF(B97="EST",15,14),0),0)*C97 -> 0 | S97: =IFERROR(VLOOKUP(D97,Modelos[],IF(E97="EST",15,14),0),0)*F97 -> 0 | T97: =IF($L97<0,0,IFERROR((T$2*IFERROR(VLOOKUP(J97,Tabla11[],2,0),0))*($L97/SUM($L$5:$L$46)),0)) -> 2015.3585 | U97: =IF($L97<0,0,IFERROR((U$2*IFERROR(VLOOKUP(J97,Tabla11[],2,0),0))*($L97/SUM($L$5:$L$46)),0)) -> 391.87527 | V97: =IF($L97<0,0,IFERROR((V$2*IFERROR(VLOOKUP(J97,Tabla11[],2,0),0))*($L97/SUM($L$5:$L$46)),0)) -> 2015.3585 | W97: =IF($L97<0,0,IFERROR((W$2*IFERROR(VLOOKUP(J97,Tabla11[],2,0),0))*($L97/SUM($L$5:$L$46)),0)) -> 2799.1091 | X97: =P97*$X$2 -> 157257.37 | Y97: =+X97*IFERROR(VLOOKUP(J97,Tabla11[],4,0),0) -> 23588.606 | Z97: =IF(L97>0,$Z$2/12,0) -> 25833.333 | AA97: =P97-SUM(Q97:Z97) -> 109737.43 | AB97: =IF($L97<0,0,IFERROR((AB$2*IFERROR(VLOOKUP(J97,Tabla11[],2,0),0))*($L97/SUM($L$5:$L$46)),0)) -> 3214.597 | AC97: =L97-L97*IFERROR(VLOOKUP(J97,Tabla11[],3,0),0)-Q97-T97-U97-V97-W97-L97*$X$2-(L97*$X$2)*IFERROR(VLOOKUP(J97,Tabla11[],4,0),0)-AB97-Z97 -> 9144.229 | AD97: =AA97-AB97 -> 106522.83 | AE97: =ROUND(AD97-AC97,9) -> 97378.603
B98: Outsourcing | E98: Outsourcing | G98: 1 | H98: Supervisor Regiones | I98: VI-VII | J98: Johnson | K98: Talca | L98: =IFERROR(VLOOKUP(CONCATENATE(J98,K98),Ventas!D:H,4,0),0) -> 636723.52 | M98: =IF(SUM(C98,F98)>0,L98*0.1,0) -> 0 | N98: =SUM(L98:M98) -> 636723.52 | O98: =N98*IFERROR(VLOOKUP(J98,Tabla11[],3,0),0) -> 222853.23 | P98: =N98-O98 -> 413870.29 | Q98: =IFERROR(G98/SUMIF(I:I,I98,G:G),0)*VLOOKUP(H98,Modelos[],14,0)+IFERROR(G98/SUMIF(I:I,I98,G:G),0)*VLOOKUP(I98,Tabla13[],2,0) -> 51647.612 | R98: =IFERROR(VLOOKUP(A98,Modelos[],IF(B98="EST",15,14),0),0)*C98 -> 0 | S98: =IFERROR(VLOOKUP(D98,Modelos[],IF(E98="EST",15,14),0),0)*F98 -> 0 | T98: =IF($L98<0,0,IFERROR((T$2*IFERROR(VLOOKUP(J98,Tabla11[],2,0),0))*($L98/SUM($L$5:$L$46)),0)) -> 2121.6099 | U98: =IF($L98<0,0,IFERROR((U$2*IFERROR(VLOOKUP(J98,Tabla11[],2,0),0))*($L98/SUM($L$5:$L$46)),0)) -> 412.53527 | V98: =IF($L98<0,0,IFERROR((V$2*IFERROR(VLOOKUP(J98,Tabla11[],2,0),0))*($L98/SUM($L$5:$L$46)),0)) -> 2121.6099 | W98: =IF($L98<0,0,IFERROR((W$2*IFERROR(VLOOKUP(J98,Tabla11[],2,0),0))*($L98/SUM($L$5:$L$46)),0)) -> 2946.6805 | X98: =P98*$X$2 -> 165548.11 | Y98: =+X98*IFERROR(VLOOKUP(J98,Tabla11[],4,0),0) -> 24832.217 | Z98: =IF(L98>0,$Z$2/12,0) -> 25833.333 | AA98: =P98-SUM(Q98:Z98) -> 138406.57 | AB98: =IF($L98<0,0,IFERROR((AB$2*IFERROR(VLOOKUP(J98,Tabla11[],2,0),0))*($L98/SUM($L$5:$L$46)),0)) -> 3384.0733 | AC98: =L98-L98*IFERROR(VLOOKUP(J98,Tabla11[],3,0),0)-Q98-T98-U98-V98-W98-L98*$X$2-(L98*$X$2)*IFERROR(VLOOKUP(J98,Tabla11[],4,0),0)-AB98-Z98 -> 32510.014 | AD98: =AA98-AB98 -> 135022.5 | AE98: =ROUND(AD98-AC98,9) -> 102512.49
B99: Outsourcing | E99: Outsourcing | G99: 3 | H99: Supervisor Regiones | I99: Concepción | J99: Johnson | K99: Concepcion | L99: =IFERROR(VLOOKUP(CONCATENATE(J99,K99),Ventas!D:H,4,0),0) -> 691485.49 | M99: =IF(SUM(C99,F99)>0,L99*0.1,0) -> 0 | N99: =SUM(L99:M99) -> 691485.49 | O99: =N99*IFERROR(VLOOKUP(J99,Tabla11[],3,0),0) -> 242019.92 | P99: =N99-O99 -> 449465.57 | Q99: =IFERROR(G99/SUMIF(I:I,I99,G:G),0)*VLOOKUP(H99,Modelos[],14,0)+IFERROR(G99/SUMIF(I:I,I99,G:G),0)*VLOOKUP(I99,Tabla13[],2,0) -> 106001.17 | R99: =IFERROR(VLOOKUP(A99,Modelos[],IF(B99="EST",15,14),0),0)*C99 -> 0 | S99: =IFERROR(VLOOKUP(D99,Modelos[],IF(E99="EST",15,14),0),0)*F99 -> 0 | T99: =IF($L99<0,0,IFERROR((T$2*IFERROR(VLOOKUP(J99,Tabla11[],2,0),0))*($L99/SUM($L$5:$L$46)),0)) -> 2304.0809 | U99: =IF($L99<0,0,IFERROR((U$2*IFERROR(VLOOKUP(J99,Tabla11[],2,0),0))*($L99/SUM($L$5:$L$46)),0)) -> 448.01573 | V99: =IF($L99<0,0,IFERROR((V$2*IFERROR(VLOOKUP(J99,Tabla11[],2,0),0))*($L99/SUM($L$5:$L$46)),0)) -> 2304.0809 | W99: =IF($L99<0,0,IFERROR((W$2*IFERROR(VLOOKUP(J99,Tabla11[],2,0),0))*($L99/SUM($L$5:$L$46)),0)) -> 3200.1124 | X99: =P99*$X$2 -> 179786.23 | Y99: =+X99*IFERROR(VLOOKUP(J99,Tabla11[],4,0),0) -> 26967.934 | Z99: =IF(L99>0,$Z$2/12,0) -> 25833.333 | AA99: =P99-SUM(Q99:Z99) -> 102620.61 | AB99: =IF($L99<0,0,IFERROR((AB$2*IFERROR(VLOOKUP(J99,Tabla11[],2,0),0))*($L99/SUM($L$5:$L$46)),0)) -> 3675.1236 | AC99: =L99-L99*IFERROR(VLOOKUP(J99,Tabla11[],3,0),0)-Q99-T99-U99-V99-W99-L99*$X$2-(L99*$X$2)*IFERROR(VLOOKUP(J99,Tabla11[],4,0),0)-AB99-Z99 -> -12383.677 | AD99: =AA99-AB99 -> 98945.487 | AE99: =ROUND(AD99-AC99,9) -> 111329.16
B100: Outsourcing | E100: Outsourcing | G100: 3 | H100: Supervisor Santiago | I100: Santiago 03 | J100: Johnson | K100: Puente | L100: =IFERROR(VLOOKUP(CONCATENATE(J100,K100),Ventas!D:H,4,0),0) -> 653922.2 | M100: =IF(SUM(C100,F100)>0,L100*0.1,0) -> 0 | N100: =SUM(L100:M100) -> 653922.2 | O100: =N100*IFERROR(VLOOKUP(J100,Tabla11[],3,0),0) -> 228872.77 | P100: =N100-O100 -> 425049.43 | Q100: =IFERROR(G100/SUMIF(I:I,I100,G:G),0)*VLOOKUP(H100,Modelos[],14,0)+IFERROR(G100/SUMIF(I:I,I100,G:G),0)*VLOOKUP(I100,Tabla13[],2,0) -> 73262.014 | R100: =IFERROR(VLOOKUP(A100,Modelos[],IF(B100="EST",15,14),0),0)*C100 -> 0 | S100: =IFERROR(VLOOKUP(D100,Modelos[],IF(E100="EST",15,14),0),0)*F100 -> 0 | T100: =IF($L100<0,0,IFERROR((T$2*IFERROR(VLOOKUP(J100,Tabla11[],2,0),0))*($L100/SUM($L$5:$L$46)),0)) -> 2178.9172 | U100: =IF($L100<0,0,IFERROR((U$2*IFERROR(VLOOKUP(J100,Tabla11[],2,0),0))*($L100/SUM($L$5:$L$46)),0)) -> 423.67835 | V100: =IF($L100<0,0,IFERROR((V$2*IFERROR(VLOOKUP(J100,Tabla11[],2,0),0))*($L100/SUM($L$5:$L$46)),0)) -> 2178.9172 | W100: =IF($L100<0,0,IFERROR((W$2*IFERROR(VLOOKUP(J100,Tabla11[],2,0),0))*($L100/SUM($L$5:$L$46)),0)) -> 3026.2739 | X100: =P100*$X$2 -> 170019.77 | Y100: =+X100*IFERROR(VLOOKUP(J100,Tabla11[],4,0),0) -> 25502.966 | Z100: =IF(L100>0,$Z$2/12,0) -> 25833.333 | AA100: =P100-SUM(Q100:Z100) -> 122623.56 | AB100: =IF($L100<0,0,IFERROR((AB$2*IFERROR(VLOOKUP(J100,Tabla11[],2,0),0))*($L100/SUM($L$5:$L$46)),0)) -> 3475.4813 | AC100: =L100-L100*IFERROR(VLOOKUP(J100,Tabla11[],3,0),0)-Q100-T100-U100-V100-W100-L100*$X$2-(L100*$X$2)*IFERROR(VLOOKUP(J100,Tabla11[],4,0),0)-AB100-Z100 -> 13866.602 | AD100: =AA100-AB100 -> 119148.08 | AE100: =ROUND(AD100-AC100,9) -> 105281.47
B101: Outsourcing | E101: Outsourcing | G101: 2 | H101: Supervisor Regiones | I101: VI-VII | J101: Johnson | K101: Rancagua | L101: =IFERROR(VLOOKUP(CONCATENATE(J101,K101),Ventas!D:H,4,0),0) -> 662225.71 | M101: =IF(SUM(C101,F101)>0,L101*0.1,0) -> 0 | N101: =SUM(L101:M101) -> 662225.71 | O101: =N101*IFERROR(VLOOKUP(J101,Tabla11[],3,0),0) -> 231779 | P101: =N101-O101 -> 430446.71 | Q101: =IFERROR(G101/SUMIF(I:I,I101,G:G),0)*VLOOKUP(H101,Modelos[],14,0)+IFERROR(G101/SUMIF(I:I,I101,G:G),0)*VLOOKUP(I101,Tabla13[],2,0) -> 103295.22 | R101: =IFERROR(VLOOKUP(A101,Modelos[],IF(B101="EST",15,14),0),0)*C101 -> 0 | S101: =IFERROR(VLOOKUP(D101,Modelos[],IF(E101="EST",15,14),0),0)*F101 -> 0 | T101: =IF($L101<0,0,IFERROR((T$2*IFERROR(VLOOKUP(J101,Tabla11[],2,0),0))*($L101/SUM($L$5:$L$46)),0)) -> 2206.5852 | U101: =IF($L101<0,0,IFERROR((U$2*IFERROR(VLOOKUP(J101,Tabla11[],2,0),0))*($L101/SUM($L$5:$L$46)),0)) -> 429.05823 | V101: =IF($L101<0,0,IFERROR((V$2*IFERROR(VLOOKUP(J101,Tabla11[],2,0),0))*($L101/SUM($L$5:$L$46)),0)) -> 2206.5852 | W101: =IF($L101<0,0,IFERROR((W$2*IFERROR(VLOOKUP(J101,Tabla11[],2,0),0))*($L101/SUM($L$5:$L$46)),0)) -> 3064.7016 | X101: =P101*$X$2 -> 172178.69 | Y101: =+X101*IFERROR(VLOOKUP(J101,Tabla11[],4,0),0) -> 25826.803 | Z101: =IF(L101>0,$Z$2/12,0) -> 25833.333 | AA101: =P101-SUM(Q101:Z101) -> 95405.739 | AB101: =IF($L101<0,0,IFERROR((AB$2*IFERROR(VLOOKUP(J101,Tabla11[],2,0),0))*($L101/SUM($L$5:$L$46)),0)) -> 3519.613 | AC101: =L101-L101*IFERROR(VLOOKUP(J101,Tabla11[],3,0),0)-Q101-T101-U101-V101-W101-L101*$X$2-(L101*$X$2)*IFERROR(VLOOKUP(J101,Tabla11[],4,0),0)-AB101-Z101 -> -14732.214 | AD101: =AA101-AB101 -> 91886.126 | AE101: =ROUND(AD101-AC101,9) -> 106618.34
B102: Outsourcing | E102: Outsourcing | G102: 2 | H102: Supervisor Part | I102: Temuco | J102: Johnson | K102: Coronel | L102: =IFERROR(VLOOKUP(CONCATENATE(J102,K102),Ventas!D:H,4,0),0) -> 557030.77 | M102: =IF(SUM(C102,F102)>0,L102*0.1,0) -> 0 | N102: =SUM(L102:M102) -> 557030.77 | O102: =N102*IFERROR(VLOOKUP(J102,Tabla11[],3,0),0) -> 194960.77 | P102: =N102-O102 -> 362070 | Q102: =IFERROR(G102/SUMIF(I:I,I102,G:G),0)*VLOOKUP(H102,Modelos[],14,0)+IFERROR(G102/SUMIF(I:I,I102,G:G),0)*VLOOKUP(I102,Tabla13[],2,0) -> 43497.442 | R102: =IFERROR(VLOOKUP(A102,Modelos[],IF(B102="EST",15,14),0),0)*C102 -> 0 | S102: =IFERROR(VLOOKUP(D102,Modelos[],IF(E102="EST",15,14),0),0)*F102 -> 0 | T102: =IF($L102<0,0,IFERROR((T$2*IFERROR(VLOOKUP(J102,Tabla11[],2,0),0))*($L102/SUM($L$5:$L$46)),0)) -> 1856.0678 | U102: =IF($L102<0,0,IFERROR((U$2*IFERROR(VLOOKUP(J102,Tabla11[],2,0),0))*($L102/SUM($L$5:$L$46)),0)) -> 360.90207 | V102: =IF($L102<0,0,IFERROR((V$2*IFERROR(VLOOKUP(J102,Tabla11[],2,0),0))*($L102/SUM($L$5:$L$46)),0)) -> 1856.0678 | W102: =IF($L102<0,0,IFERROR((W$2*IFERROR(VLOOKUP(J102,Tabla11[],2,0),0))*($L102/SUM($L$5:$L$46)),0)) -> 2577.872 | X102: =P102*$X$2 -> 144828 | Y102: =+X102*IFERROR(VLOOKUP(J102,Tabla11[],4,0),0) -> 21724.2 | Z102: =IF(L102>0,$Z$2/12,0) -> 25833.333 | AA102: =P102-SUM(Q102:Z102) -> 119536.12 | AB102: =IF($L102<0,0,IFERROR((AB$2*IFERROR(VLOOKUP(J102,Tabla11[],2,0),0))*($L102/SUM($L$5:$L$46)),0)) -> 2960.5204 | AC102: =L102-L102*IFERROR(VLOOKUP(J102,Tabla11[],3,0),0)-Q102-T102-U102-V102-W102-L102*$X$2-(L102*$X$2)*IFERROR(VLOOKUP(J102,Tabla11[],4,0),0)-AB102-Z102 -> 26893.641 | AD102: =AA102-AB102 -> 116575.59 | AE102: =ROUND(AD102-AC102,9) -> 89681.954
B103: Outsourcing | E103: Outsourcing | G103: 3 | H103: Supervisor Part | I103: Temuco | J103: Johnson | K103: Temuco | L103: =IFERROR(VLOOKUP(CONCATENATE(J103,K103),Ventas!D:H,4,0),0) -> 547716.26 | M103: =IF(SUM(C103,F103)>0,L103*0.1,0) -> 0 | N103: =SUM(L103:M103) -> 547716.26 | O103: =N103*IFERROR(VLOOKUP(J103,Tabla11[],3,0),0) -> 191700.69 | P103: =N103-O103 -> 356015.57 | Q103: =IFERROR(G103/SUMIF(I:I,I103,G:G),0)*VLOOKUP(H103,Modelos[],14,0)+IFERROR(G103/SUMIF(I:I,I103,G:G),0)*VLOOKUP(I103,Tabla13[],2,0) -> 65246.163 | R103: =IFERROR(VLOOKUP(A103,Modelos[],IF(B103="EST",15,14),0),0)*C103 -> 0 | S103: =IFERROR(VLOOKUP(D103,Modelos[],IF(E103="EST",15,14),0),0)*F103 -> 0 | T103: =IF($L103<0,0,IFERROR((T$2*IFERROR(VLOOKUP(J103,Tabla11[],2,0),0))*($L103/SUM($L$5:$L$46)),0)) -> 1825.0312 | U103: =IF($L103<0,0,IFERROR((U$2*IFERROR(VLOOKUP(J103,Tabla11[],2,0),0))*($L103/SUM($L$5:$L$46)),0)) -> 354.86718 | V103: =IF($L103<0,0,IFERROR((V$2*IFERROR(VLOOKUP(J103,Tabla11[],2,0),0))*($L103/SUM($L$5:$L$46)),0)) -> 1825.0312 | W103: =IF($L103<0,0,IFERROR((W$2*IFERROR(VLOOKUP(J103,Tabla11[],2,0),0))*($L103/SUM($L$5:$L$46)),0)) -> 2534.7655 | X103: =P103*$X$2 -> 142406.23 | Y103: =+X103*IFERROR(VLOOKUP(J103,Tabla11[],4,0),0) -> 21360.934 | Z103: =IF(L103>0,$Z$2/12,0) -> 25833.333 | AA103: =P103-SUM(Q103:Z103) -> 94629.217 | AB103: =IF($L103<0,0,IFERROR((AB$2*IFERROR(VLOOKUP(J103,Tabla11[],2,0),0))*($L103/SUM($L$5:$L$46)),0)) -> 2911.0155 | AC103: =L103-L103*IFERROR(VLOOKUP(J103,Tabla11[],3,0),0)-Q103-T103-U103-V103-W103-L103*$X$2-(L103*$X$2)*IFERROR(VLOOKUP(J103,Tabla11[],4,0),0)-AB103-Z103 -> 3535.8834 | AD103: =AA103-AB103 -> 91718.202 | AE103: =ROUND(AD103-AC103,9) -> 88182.318
B104: Outsourcing | E104: Outsourcing | G104: 1 | H104: Supervisor Santiago | I104: Santiago 03 | J104: Johnson | K104: Melipilla | L104: =IFERROR(VLOOKUP(CONCATENATE(J104,K104),Ventas!D:H,4,0),0) -> 445859.56 | M104: =IF(SUM(C104,F104)>0,L104*0.1,0) -> 0 | N104: =SUM(L104:M104) -> 445859.56 | O104: =N104*IFERROR(VLOOKUP(J104,Tabla11[],3,0),0) -> 156050.85 | P104: =N104-O104 -> 289808.71 | Q104: =IFERROR(G104/SUMIF(I:I,I104,G:G),0)*VLOOKUP(H104,Modelos[],14,0)+IFERROR(G104/SUMIF(I:I,I104,G:G),0)*VLOOKUP(I104,Tabla13[],2,0) -> 24420.671 | R104: =IFERROR(VLOOKUP(A104,Modelos[],IF(B104="EST",15,14),0),0)*C104 -> 0 | S104: =IFERROR(VLOOKUP(D104,Modelos[],IF(E104="EST",15,14),0),0)*F104 -> 0 | T104: =IF($L104<0,0,IFERROR((T$2*IFERROR(VLOOKUP(J104,Tabla11[],2,0),0))*($L104/SUM($L$5:$L$46)),0)) -> 1485.6371 | U104: =IF($L104<0,0,IFERROR((U$2*IFERROR(VLOOKUP(J104,Tabla11[],2,0),0))*($L104/SUM($L$5:$L$46)),0)) -> 288.87388 | V104: =IF($L104<0,0,IFERROR((V$2*IFERROR(VLOOKUP(J104,Tabla11[],2,0),0))*($L104/SUM($L$5:$L$46)),0)) -> 1485.6371 | W104: =IF($L104<0,0,IFERROR((W$2*IFERROR(VLOOKUP(J104,Tabla11[],2,0),0))*($L104/SUM($L$5:$L$46)),0)) -> 2063.3849 | X104: =P104*$X$2 -> 115923.49 | Y104: =+X104*IFERROR(VLOOKUP(J104,Tabla11[],4,0),0) -> 17388.523 | Z104: =IF(L104>0,$Z$2/12,0) -> 25833.333 | AA104: =P104-SUM(Q104:Z104) -> 100919.17 | AB104: =IF($L104<0,0,IFERROR((AB$2*IFERROR(VLOOKUP(J104,Tabla11[],2,0),0))*($L104/SUM($L$5:$L$46)),0)) -> 2369.665 | AC104: =L104-L104*IFERROR(VLOOKUP(J104,Tabla11[],3,0),0)-Q104-T104-U104-V104-W104-L104*$X$2-(L104*$X$2)*IFERROR(VLOOKUP(J104,Tabla11[],4,0),0)-AB104-Z104 -> 26766.114 | AD104: =AA104-AB104 -> 98549.503 | AE104: =ROUND(AD104-AC104,9) -> 71783.389
... B115: Outsourcing | E115: Outsourcing | G115: 0 | H115: Supervisor Santiago | I115: Santiago 01 | J115: Johnson | K115: San Antonio | L115: =IFERROR(VLOOKUP(CONCATENATE(J115,K115),Ventas!D:H,4,0),0) -> -1438.2418 | M115: =IF(SUM(C115,F115)>0,L115*0.1,0) -> 0 | N115: =SUM(L115:M115) -> -1438.2418 | O115: =N115*IFERROR(VLOOKUP(J115,Tabla11[],3,0),0) -> -503.38462 | P115: =N115-O115 -> -934.85714 | Q115: =IFERROR(G115/SUMIF(I:I,I115,G:G),0)*VLOOKUP(H115,Modelos[],14,0)+IFERROR(G115/SUMIF(I:I,I115,G:G),0)*VLOOKUP(I115,Tabla13[],2,0) -> 0 | R115: =IFERROR(VLOOKUP(A115,Modelos[],IF(B115="EST",15,14),0),0)*C115 -> 0 | S115: =IFERROR(VLOOKUP(D115,Modelos[],IF(E115="EST",15,14),0),0)*F115 -> 0 | T115: =IF($L115<0,0,IFERROR((T$2*IFERROR(VLOOKUP(J115,Tabla11[],2,0),0))*($L115/SUM($L$5:$L$46)),0)) -> 0 | U115: =IF($L115<0,0,IFERROR((U$2*IFERROR(VLOOKUP(J115,Tabla11[],2,0),0))*($L115/SUM($L$5:$L$46)),0)) -> 0 | V115: =IF($L115<0,0,IFERROR((V$2*IFERROR(VLOOKUP(J115,Tabla11[],2,0),0))*($L115/SUM($L$5:$L$46)),0)) -> 0 | W115: =IF($L115<0,0,IFERROR((W$2*IFERROR(VLOOKUP(J115,Tabla11[],2,0),0))*($L115/SUM($L$5:$L$46)),0)) -> 0 | X115: =P115*$X$2 -> -373.94286 | Y115: =+X115*IFERROR(VLOOKUP(J115,Tabla11[],4,0),0) -> -56.091429 | Z115: =IF(L115>0,$Z$2/12,0) -> 0 | AA115: =P115-SUM(Q115:Z115) -> -504.82286 | AB115: =IF($L115<0,0,IFERROR((AB$2*IFERROR(VLOOKUP(J115,Tabla11[],2,0),0))*($L115/SUM($L$5:$L$46)),0)) -> 0 | AC115: =L115-L115*IFERROR(VLOOKUP(J115,Tabla11[],3,0),0)-Q115-T115-U115-V115-W115-L115*$X$2-(L115*$X$2)*IFERROR(VLOOKUP(J115,Tabla11[],4,0),0)-AB115-Z115 -> -273.26593 | AD115: =AA115-AB115 -> -504.82286 | AE115: =ROUND(AD115-AC115,9) -> -231.55692

Sheet Temporada Baja PPT
N2: 1393548.4 | O2: 270967.74 | P2: 1393548.4 | Q2: 1935483.9 | R2: 0.4 | S2: 0.15 | T2: 310000 | V2: 3519400
A4: Modelo PDV | B4: Tipo | C4: Q Tiendas | D4: Sup. | E4: Cadena | F4: Sucursal | G4: Venta Promedio | H4: Incremento de Venta | I4: Venta Total | J4: Comisión Retail | K4: Margen Tienda | L4: Supervisión | M4: Vendedor / Reposición | N4: Bodegaje | O4: Packing | P4: Picking | Q4: Transporte | R4: Costo Mercadería | S4: Merma | T4: Muebles | U4: Margen Operacional | V4: Gastos de Administración | W4: Resultado Actual | X4: Resultado Modelo | Y4: Diferencial
B5: EST | C5: 1 | D5: 1 | E5: Ripley | F5: Marina Arauco | G5: =IFERROR(VLOOKUP(CONCATENATE(E5,F5),Ventas!D:H,5,0),0) -> 1199044.6 | H5: =IFERROR(VLOOKUP(A5,Modelos[],18,0),0)*G5/C5 -> 0 | I5: =SUM(G5:H5) -> 1199044.6 | J5: =I5*IFERROR(VLOOKUP(E5,Tabla11[],3,0),0) -> 419665.62 | K5: =I5-J5 -> 779379 | L5: =Sup!$A$2*D5 -> 6775.4474 | M5: =IFERROR(VLOOKUP(A5,Modelos[],IF(B5="EST",15,14),0),0)/C5 -> 0 | N5: =IF($G5<0,0,IFERROR((N$2*IFERROR(VLOOKUP(E5,Tabla11[],2,0),0))*($G5/SUM($G$5:$G$43)),0)) -> 13546.918 | O5: =IF($G5<0,0,IFERROR((O$2*IFERROR(VLOOKUP(E5,Tabla11[],2,0),0))*($G5/SUM($G$5:$G$43)),0)) -> 2634.1229 | P5: =IF($G5<0,0,IFERROR((P$2*IFERROR(VLOOKUP(E5,Tabla11[],2,0),0))*($G5/SUM($G$5:$G$43)),0)) -> 13546.918 | Q5: =IF($G5<0,0,IFERROR((Q$2*IFERROR(VLOOKUP(E5,Tabla11[],2,0),0))*($G5/SUM($G$5:$G$43)),0)) -> 18815.163 | R5: =K5*$R$2 -> 311751.6 | S5: =+R5*IFERROR(VLOOKUP(E5,Tabla11[],4,0),0) -> 46762.74 | T5: =IF(G5>0,$T$2/12,0) -> 25833.333 | U5: =K5-SUM(L5:T5) -> 339712.76 | V5: =IF($G5<0,0,IFERROR((V$2*IFERROR(VLOOKUP(E5,Tabla11[],2,0),0))*($G5/SUM($G$5:$G$43)),0)) -> 34212.678 | W5: =G5-G5*IFERROR(VLOOKUP(E5,Tabla11[],3,0),0)-L5-N5-O5-P5-Q5-G5*$R$2-(G5*$R$2)*IFERROR(VLOOKUP(E5,Tabla11[],4,0),0)-V5-T5 -> 112453.9 | X5: =U5-V5 -> 305500.08 | Y5: =ROUND(X5-W5,9) -> 193046.18
B6: EST | C6: 1 | D6: 1 | E6: Ripley | F6: M.Costanera P.Montt | G6: =IFERROR(VLOOKUP(CONCATENATE(E6,F6),Ventas!D:H,5,0),0) -> 724821.54 | H6: =IFERROR(VLOOKUP(A6,Modelos[],18,0),0)*G6/C6 -> 0 | I6: =SUM(G6:H6) -> 724821.54 | J6: =I6*IFERROR(VLOOKUP(E6,Tabla11[],3,0),0) -> 253687.54 | K6: =I6-J6 -> 471134 | L6: =Sup!$A$2*D6 -> 6775.4474 | M6: =IFERROR(VLOOKUP(A6,Modelos[],IF(B6="EST",15,14),0),0)/C6 -> 0 | N6: =IF($G6<0,0,IFERROR((N$2*IFERROR(VLOOKUP(E6,Tabla11[],2,0),0))*($G6/SUM($G$5:$G$43)),0)) -> 8189.1011 | O6: =IF($G6<0,0,IFERROR((O$2*IFERROR(VLOOKUP(E6,Tabla11[],2,0),0))*($G6/SUM($G$5:$G$43)),0)) -> 1592.3252 | P6: =IF($G6<0,0,IFERROR((P$2*IFERROR(VLOOKUP(E6,Tabla11[],2,0),0))*($G6/SUM($G$5:$G$43)),0)) -> 8189.1011 | Q6: =IF($G6<0,0,IFERROR((Q$2*IFERROR(VLOOKUP(E6,Tabla11[],2,0),0))*($G6/SUM($G$5:$G$43)),0)) -> 11373.752 | R6: =K6*$R$2 -> 188453.6 | S6: =+R6*IFERROR(VLOOKUP(E6,Tabla11[],4,0),0) -> 28268.04 | T6: =IF(G6>0,$T$2/12,0) -> 25833.333 | U6: =K6-SUM(L6:T6) -> 192459.3 | V6: =IF($G6<0,0,IFERROR((V$2*IFERROR(VLOOKUP(E6,Tabla11[],2,0),0))*($G6/SUM($G$5:$G$43)),0)) -> 20681.537 | W6: =G6-G6*IFERROR(VLOOKUP(E6,Tabla11[],3,0),0)-L6-N6-O6-P6-Q6-G6*$R$2-(G6*$R$2)*IFERROR(VLOOKUP(E6,Tabla11[],4,0),0)-V6-T6 -> 55081.495 | X6: =U6-V6 -> 171777.76 | Y6: =ROUND(X6-W6,9) -> 116696.27
B7: EST | C7: 1 | D7: 1 | E7: Ripley | F7: Talca | G7: =IFERROR(VLOOKUP(CONCATENATE(E7,F7),Ventas!D:H,5,0),0) -> 812932.31 | H7: =IFERROR(VLOOKUP(A7,Modelos[],18,0),0)*G7/C7 -> 0 | I7: =SUM(G7:H7) -> 812932.31 | J7: =I7*IFERROR(VLOOKUP(E7,Tabla11[],3,0),0) -> 284526.31 | K7: =I7-J7 -> 528406 | L7: =Sup!$A$2*D7 -> 6775.4474 | M7: =IFERROR(VLOOKUP(A7,Modelos[],IF(B7="EST",15,14),0),0)/C7 -> 0 | N7: =IF($G7<0,0,IFERROR((N$2*IFERROR(VLOOKUP(E7,Tabla11[],2,0),0))*($G7/SUM($G$5:$G$43)),0)) -> 9184.5848 | O7: =IF($G7<0,0,IFERROR((O$2*IFERROR(VLOOKUP(E7,Tabla11[],2,0),0))*($G7/SUM($G$5:$G$43)),0)) -> 1785.8915 | P7: =IF($G7<0,0,IFERROR((P$2*IFERROR(VLOOKUP(E7,Tabla11[],2,0),0))*($G7/SUM($G$5:$G$43)),0)) -> 9184.5848 | Q7: =IF($G7<0,0,IFERROR((Q$2*IFERROR(VLOOKUP(E7,Tabla11[],2,0),0))*($G7/SUM($G$5:$G$43)),0)) -> 12756.368 | R7: =K7*$R$2 -> 211362.4 | S7: =+R7*IFERROR(VLOOKUP(E7,Tabla11[],4,0),0) -> 31704.36 | T7: =IF(G7>0,$T$2/12,0) -> 25833.333 | U7: =K7-SUM(L7:T7) -> 219819.03 | V7: =IF($G7<0,0,IFERROR((V$2*IFERROR(VLOOKUP(E7,Tabla11[],2,0),0))*($G7/SUM($G$5:$G$43)),0)) -> 23195.626 | W7: =G7-G7*IFERROR(VLOOKUP(E7,Tabla11[],3,0),0)-L7-N7-O7-P7-Q7-G7*$R$2-(G7*$R$2)*IFERROR(VLOOKUP(E7,Tabla11[],4,0),0)-V7-T7 -> 65741.302 | X7: =U7-V7 -> 196623.4 | Y7: =ROUND(X7-W7,9) -> 130882.1
B8: EST | C8: 1 | D8: 1 | E8: Ripley | F8: Temuco | G8: =IFERROR(VLOOKUP(CONCATENATE(E8,F8),Ventas!D:H,5,0),0) -> 697984.62 | H8: =IFERROR(VLOOKUP(A8,Modelos[],18,0),0)*G8/C8 -> 0 | I8: =SUM(G8:H8) -> 697984.62 | J8: =I8*IFERROR(VLOOKUP(E8,Tabla11[],3,0),0) -> 244294.62 | K8: =I8-J8 -> 453690 | L8: =Sup!$A$2*D8 -> 6775.4474 | M8: =IFERROR(VLOOKUP(A8,Modelos[],IF(B8="EST",15,14),0),0)/C8 -> 0 | N8: =IF($G8<0,0,IFERROR((N$2*IFERROR(VLOOKUP(E8,Tabla11[],2,0),0))*($G8/SUM($G$5:$G$43)),0)) -> 7885.8951 | O8: =IF($G8<0,0,IFERROR((O$2*IFERROR(VLOOKUP(E8,Tabla11[],2,0),0))*($G8/SUM($G$5:$G$43)),0)) -> 1533.3685 | P8: =IF($G8<0,0,IFERROR((P$2*IFERROR(VLOOKUP(E8,Tabla11[],2,0),0))*($G8/SUM($G$5:$G$43)),0)) -> 7885.8951 | Q8: =IF($G8<0,0,IFERROR((Q$2*IFERROR(VLOOKUP(E8,Tabla11[],2,0),0))*($G8/SUM($G$5:$G$43)),0)) -> 10952.632 | R8: =K8*$R$2 -> 181476 | S8: =+R8*IFERROR(VLOOKUP(E8,Tabla11[],4,0),0) -> 27221.4 | T8: =IF(G8>0,$T$2/12,0) -> 25833.333 | U8: =K8-SUM(L8:T8) -> 184126.03 | V8: =IF($G8<0,0,IFERROR((V$2*IFERROR(VLOOKUP(E8,Tabla11[],2,0),0))*($G8/SUM($G$5:$G$43)),0)) -> 19915.792 | W8: =G8-G8*IFERROR(VLOOKUP(E8,Tabla11[],3,0),0)-L8-N8-O8-P8-Q8-G8*$R$2-(G8*$R$2)*IFERROR(VLOOKUP(E8,Tabla11[],4,0),0)-V8-T8 -> 51834.714 | X8: =U8-V8 -> 164210.24 | Y8: =ROUND(X8-W8,9) -> 112375.52
B9: EST | C9: 1 | D9: 1 | E9: Ripley | F9: La Calera | G9: =IFERROR(VLOOKUP(CONCATENATE(E9,F9),Ventas!D:H,5,0),0) -> 1138507.7 | H9: =IFERROR(VLOOKUP(A9,Modelos[],18,0),0)*G9/C9 -> 0 | I9: =SUM(G9:H9) -> 1138507.7 | J9: =I9*IFERROR(VLOOKUP(E9,Tabla11[],3,0),0) -> 398477.69 | K9: =I9-J9 -> 740030 | L9: =Sup!$A$2*D9 -> 6775.4474 | M9: =IFERROR(VLOOKUP(A9,Modelos[],IF(B9="EST",15,14),0),0)/C9 -> 0 | N9: =IF($G9<0,0,IFERROR((N$2*IFERROR(VLOOKUP(E9,Tabla11[],2,0),0))*($G9/SUM($G$5:$G$43)),0)) -> 12862.966 | O9: =IF($G9<0,0,IFERROR((O$2*IFERROR(VLOOKUP(E9,Tabla11[],2,0),0))*($G9/SUM($G$5:$G$43)),0)) -> 2501.1322 | P9: =IF($G9<0,0,IFERROR((P$2*IFERROR(VLOOKUP(E9,Tabla11[],2,0),0))*($G9/SUM($G$5:$G$43)),0)) -> 12862.966 | Q9: =IF($G9<0,0,IFERROR((Q$2*IFERROR(VLOOKUP(E9,Tabla11[],2,0),0))*($G9/SUM($G$5:$G$43)),0)) -> 17865.23 | R9: =K9*$R$2 -> 296012 | S9: =+R9*IFERROR(VLOOKUP(E9,Tabla11[],4,0),0) -> 44401.8 | T9: =IF(G9>0,$T$2/12,0) -> 25833.333 | U9: =K9-SUM(L9:T9) -> 320915.13 | V9: =IF($G9<0,0,IFERROR((V$2*IFERROR(VLOOKUP(E9,Tabla11[],2,0),0))*($G9/SUM($G$5:$G$43)),0)) -> 32485.361 | W9: =G9-G9*IFERROR(VLOOKUP(E9,Tabla11[],3,0),0)-L9-N9-O9-P9-Q9-G9*$R$2-(G9*$R$2)*IFERROR(VLOOKUP(E9,Tabla11[],4,0),0)-V9-T9 -> 105130.03 | X9: =U9-V9 -> 288429.76 | Y9: =ROUND(X9-W9,9) -> 183299.74
B10: EST | C10: 1 | D10: 1 | E10: Ripley | F10: Mall Concepcion | G10: =IFERROR(VLOOKUP(CONCATENATE(E10,F10),Ventas!D:H,5,0),0) -> 709386.15 | H10: =IFERROR(VLOOKUP(A10,Modelos[],18,0),0)*G10/C10 -> 0 | I10: =SUM(G10:H10) -> 709386.15 | J10: =I10*IFERROR(VLOOKUP(E10,Tabla11[],3,0),0) -> 248285.15 | K10: =I10-J10 -> 461101 | L10: =Sup!$A$2*D10 -> 6775.4474 | M10: =IFERROR(VLOOKUP(A10,Modelos[],IF(B10="EST",15,14),0),0)/C10 -> 0 | N10: =IF($G10<0,0,IFERROR((N$2*IFERROR(VLOOKUP(E10,Tabla11[],2,0),0))*($G10/SUM($G$5:$G$43)),0)) -> 8014.7107 | O10: =IF($G10<0,0,IFERROR((O$2*IFERROR(VLOOKUP(E10,Tabla11[],2,0),0))*($G10/SUM($G$5:$G$43)),0)) -> 1558.416 | P10: =IF($G10<0,0,IFERROR((P$2*IFERROR(VLOOKUP(E10,Tabla11[],2,0),0))*($G10/SUM($G$5:$G$43)),0)) -> 8014.7107 | Q10: =IF($G10<0,0,IFERROR((Q$2*IFERROR(VLOOKUP(E10,Tabla11[],2,0),0))*($G10/SUM($G$5:$G$43)),0)) -> 11131.543 | R10: =K10*$R$2 -> 184440.4 | S10: =+R10*IFERROR(VLOOKUP(E10,Tabla11[],4,0),0) -> 27666.06 | T10: =IF(G10>0,$T$2/12,0) -> 25833.333 | U10: =K10-SUM(L10:T10) -> 187666.38 | V10: =IF($G10<0,0,IFERROR((V$2*IFERROR(VLOOKUP(E10,Tabla11[],2,0),0))*($G10/SUM($G$5:$G$43)),0)) -> 20241.115 | W10: =G10-G10*IFERROR(VLOOKUP(E10,Tabla11[],3,0),0)-L10-N10-O10-P10-Q10-G10*$R$2-(G10*$R$2)*IFERROR(VLOOKUP(E10,Tabla11[],4,0),0)-V10-T10 -> 53214.093 | X10: =U10-V10 -> 167425.26 | Y10: =ROUND(X10-W10,9) -> 114211.17
B11: EST | C11: 1 | D11: 1 | E11: Ripley | F11: Los Andes | G11: =IFERROR(VLOOKUP(CONCATENATE(E11,F11),Ventas!D:H,5,0),0) -> 814123.08 | H11: =IFERROR(VLOOKUP(A11,Modelos[],18,0),0)*G11/C11 -> 0 | I11: =SUM(G11:H11) -> 814123.08 | J11: =I11*IFERROR(VLOOKUP(E11,Tabla11[],3,0),0) -> 284943.08 | K11: =I11-J11 -> 529180 | L11: =Sup!$A$2*D11 -> 6775.4474 | M11: =IFERROR(VLOOKUP(A11,Modelos[],IF(B11="EST",15,14),0),0)/C11 -> 0 | N11: =IF($G11<0,0,IFERROR((N$2*IFERROR(VLOOKUP(E11,Tabla11[],2,0),0))*($G11/SUM($G$5:$G$43)),0)) -> 9198.0382 | O11: =IF($G11<0,0,IFERROR((O$2*IFERROR(VLOOKUP(E11,Tabla11[],2,0),0))*($G11/SUM($G$5:$G$43)),0)) -> 1788.5074 | P11: =IF($G11<0,0,IFERROR((P$2*IFERROR(VLOOKUP(E11,Tabla11[],2,0),0))*($G11/SUM($G$5:$G$43)),0)) -> 9198.0382 | Q11: =IF($G11<0,0,IFERROR((Q$2*IFERROR(VLOOKUP(E11,Tabla11[],2,0),0))*($G11/SUM($G$5:$G$43)),0)) -> 12775.053 | R11: =K11*$R$2 -> 211672 | S11: =+R11*IFERROR(VLOOKUP(E11,Tabla11[],4,0),0) -> 31750.8 | T11: =IF(G11>0,$T$2/12,0) -> 25833.333 | U11: =K11-SUM(L11:T11) -> 220188.78 | V11: =IF($G11<0,0,IFERROR((V$2*IFERROR(VLOOKUP(E11,Tabla11[],2,0),0))*($G11/SUM($G$5:$G$43)),0)) -> 23229.603 | W11: =G11-G11*IFERROR(VLOOKUP(E11,Tabla11[],3,0),0)-L11-N11-O11-P11-Q11-G11*$R$2-(G11*$R$2)*IFERROR(VLOOKUP(E11,Tabla11[],4,0),0)-V11-T11 -> 65885.364 | X11: =U11-V11 -> 196959.18 | Y11: =ROUND(X11-W11,9) -> 131073.82
B12: EST | C12: 1 | D12: 1 | E12: Ripley | F12: Costanera Center | G12: =IFERROR(VLOOKUP(CONCATENATE(E12,F12),Ventas!D:H,5,0),0) -> 1234780 | H12: =IFERROR(VLOOKUP(A12,Modelos[],18,0),0)*G12/C12 -> 0 | I12: =SUM(G12:H12) -> 1234780 | J12: =I12*IFERROR(VLOOKUP(E12,Tabla11[],3,0),0) -> 432173 | K12: =I12-J12 -> 802607 | L12: =Sup!$A$2*D12 -> 6775.4474 | M12: =IFERROR(VLOOKUP(A12,Modelos[],IF(B12="EST",15,14),0),0)/C12 -> 0 | N12: =IF($G12<0,0,IFERROR((N$2*IFERROR(VLOOKUP(E12,Tabla11[],2,0),0))*($G12/SUM($G$5:$G$43)),0)) -> 13950.659 | O12: =IF($G12<0,0,IFERROR((O$2*IFERROR(VLOOKUP(E12,Tabla11[],2,0),0))*($G12/SUM($G$5:$G$43)),0)) -> 2712.6282 | P12: =IF($G12<0,0,IFERROR((P$2*IFERROR(VLOOKUP(E12,Tabla11[],2,0),0))*($G12/SUM($G$5:$G$43)),0)) -> 13950.659 | Q12: =IF($G12<0,0,IFERROR((Q$2*IFERROR(VLOOKUP(E12,Tabla11[],2,0),0))*($G12/SUM($G$5:$G$43)),0)) -> 19375.916 | R12: =K12*$R$2 -> 321042.8 | S12: =+R12*IFERROR(VLOOKUP(E12,Tabla11[],4,0),0) -> 48156.42 | T12: =IF(G12>0,$T$2/12,0) -> 25833.333 | U12: =K12-SUM(L12:T12) -> 350809.14 | V12: =IF($G12<0,0,IFERROR((V$2*IFERROR(VLOOKUP(E12,Tabla11[],2,0),0))*($G12/SUM($G$5:$G$43)),0)) -> 35232.325 | W12: =G12-G12*IFERROR(VLOOKUP(E12,Tabla11[],3,0),0)-L12-N12-O12-P12-Q12-G12*$R$2-(G12*$R$2)*IFERROR(VLOOKUP(E12,Tabla11[],4,0),0)-V12-T12 -> 116777.23 | X12: =U12-V12 -> 315576.81 | Y12: =ROUND(X12-W12,9) -> 198799.58
B13: EST | C13: 1 | D13: 1 | E13: Ripley | F13: Florida Center | G13: =IFERROR(VLOOKUP(CONCATENATE(E13,F13),Ventas!D:H,5,0),0) -> 898778.46 | H13: =IFERROR(VLOOKUP(A13,Modelos[],18,0),0)*G13/C13 -> 0 | I13: =SUM(G13:H13) -> 898778.46 | J13: =I13*IFERROR(VLOOKUP(E13,Tabla11[],3,0),0) -> 314572.46 | K13: =I13-J13 -> 584206 | L13: =Sup!$A$2*D13 -> 6775.4474 | M13: =IFERROR(VLOOKUP(A13,Modelos[],IF(B13="EST",15,14),0),0)/C13 -> 0 | N13: =IF($G13<0,0,IFERROR((N$2*IFERROR(VLOOKUP(E13,Tabla11[],2,0),0))*($G13/SUM($G$5:$G$43)),0)) -> 10154.483 | O13: =IF($G13<0,0,IFERROR((O$2*IFERROR(VLOOKUP(E13,Tabla11[],2,0),0))*($G13/SUM($G$5:$G$43)),0)) -> 1974.4827 | P13: =IF($G13<0,0,IFERROR((P$2*IFERROR(VLOOKUP(E13,Tabla11[],2,0),0))*($G13/SUM($G$5:$G$43)),0)) -> 10154.483 | Q13: =IF($G13<0,0,IFERROR((Q$2*IFERROR(VLOOKUP(E13,Tabla11[],2,0),0))*($G13/SUM($G$5:$G$43)),0)) -> 14103.448 | R13: =K13*$R$2 -> 233682.4 | S13: =+R13*IFERROR(VLOOKUP(E13,Tabla11[],4,0),0) -> 35052.36 | T13: =IF(G13>0,$T$2/12,0) -> 25833.333 | U13: =K13-SUM(L13:T13) -> 246475.56 | V13: =IF($G13<0,0,IFERROR((V$2*IFERROR(VLOOKUP(E13,Tabla11[],2,0),0))*($G13/SUM($G$5:$G$43)),0)) -> 25645.099 | W13: =G13-G13*IFERROR(VLOOKUP(E13,Tabla11[],3,0),0)-L13-N13-O13-P13-Q13-G13*$R$2-(G13*$R$2)*IFERROR(VLOOKUP(E13,Tabla11[],4,0),0)-V13-T13 -> 76127.132 | X13: =U13-V13 -> 220830.46 | Y13: =ROUND(X13-W13,9) -> 144703.33
B14: EST | C14: 1 | D14: 1 | E14: Ripley | F14: Plaza Egana | G14: =IFERROR(VLOOKUP(CONCATENATE(E14,F14),Ventas!D:H,5,0),0) -> 667295.38 | H14: =IFERROR(VLOOKUP(A14,Modelos[],18,0),0)*G14/C14 -> 0 | I14: =SUM(G14:H14) -> 667295.38 | J14: =I14*IFERROR(VLOOKUP(E14,Tabla11[],3,0),0) -> 233553.38 | K14: =I14-J14 -> 433742 | L14: =Sup!$A$2*D14 -> 6775.4474 | M14: =IFERROR(VLOOKUP(A14,Modelos[],IF(B14="EST",15,14),0),0)/C14 -> 0 | N14: =IF($G14<0,0,IFERROR((N$2*IFERROR(VLOOKUP(E14,Tabla11[],2,0),0))*($G14/SUM($G$5:$G$43)),0)) -> 7539.1653 | O14: =IF($G14<0,0,IFERROR((O$2*IFERROR(VLOOKUP(E14,Tabla11[],2,0),0))*($G14/SUM($G$5:$G$43)),0)) -> 1465.9488 | P14: =IF($G14<0,0,IFERROR((P$2*IFERROR(VLOOKUP(E14,Tabla11[],2,0),0))*($G14/SUM($G$5:$G$43)),0)) -> 7539.1653 | Q14: =IF($G14<0,0,IFERROR((Q$2*IFERROR(VLOOKUP(E14,Tabla11[],2,0),0))*($G14/SUM($G$5:$G$43)),0)) -> 10471.063 | R14: =K14*$R$2 -> 173496.8 | S14: =+R14*IFERROR(VLOOKUP(E14,Tabla11[],4,0),0) -> 26024.52 | T14: =IF(G14>0,$T$2/12,0) -> 25833.333 | U14: =K14-SUM(L14:T14) -> 174596.56 | V14: =IF($G14<0,0,IFERROR((V$2*IFERROR(VLOOKUP(E14,Tabla11[],2,0),0))*($G14/SUM($G$5:$G$43)),0)) -> 19040.127 | W14: =G14-G14*IFERROR(VLOOKUP(E14,Tabla11[],3,0),0)-L14-N14-O14-P14-Q14-G14*$R$2-(G14*$R$2)*IFERROR(VLOOKUP(E14,Tabla11[],4,0),0)-V14-T14 -> 48121.873 | X14: =U14-V14 -> 155556.43 | Y14: =ROUND(X14-W14,9) -> 107434.56
B15: EST | C15: 1 | D15: 1 | E15: Ripley | F15: La Serena | G15: =IFERROR(VLOOKUP(CONCATENATE(E15,F15),Ventas!D:H,5,0),0) -> 365890.77 | H15: =IFERROR(VLOOKUP(A15,Modelos[],18,0),0)*G15/C15 -> 0 | I15: =SUM(G15:H15) -> 365890.77 | J15: =I15*IFERROR(VLOOKUP(E15,Tabla11[],3,0),0) -> 128061.77 | K15: =I15-J15 -> 237829 | L15: =Sup!$A$2*D15 -> 6775.4474 | M15: =IFERROR(VLOOKUP(A15,Modelos[],IF(B15="EST",15,14),0),0)/C15 -> 0 | N15: =IF($G15<0,0,IFERROR((N$2*IFERROR(VLOOKUP(E15,Tabla11[],2,0),0))*($G15/SUM($G$5:$G$43)),0)) -> 4133.8679 | O15: =IF($G15<0,0,IFERROR((O$2*IFERROR(VLOOKUP(E15,Tabla11[],2,0),0))*($G15/SUM($G$5:$G$43)),0)) -> 803.80765 | P15: =IF($G15<0,0,IFERROR((P$2*IFERROR(VLOOKUP(E15,Tabla11[],2,0),0))*($G15/SUM($G$5:$G$43)),0)) -> 4133.8679 | Q15: =IF($G15<0,0,IFERROR((Q$2*IFERROR(VLOOKUP(E15,Tabla11[],2,0),0))*($G15/SUM($G$5:$G$43)),0)) -> 5741.4832 | R15: =K15*$R$2 -> 95131.6 | S15: =+R15*IFERROR(VLOOKUP(E15,Tabla11[],4,0),0) -> 14269.74 | T15: =IF(G15>0,$T$2/12,0) -> 25833.333 | U15: =K15-SUM(L15:T15) -> 81005.852 | V15: =IF($G15<0,0,IFERROR((V$2*IFERROR(VLOOKUP(E15,Tabla11[],2,0),0))*($G15/SUM($G$5:$G$43)),0)) -> 10440.064 | W15: =G15-G15*IFERROR(VLOOKUP(E15,Tabla11[],3,0),0)-L15-N15-O15-P15-Q15-G15*$R$2-(G15*$R$2)*IFERROR(VLOOKUP(E15,Tabla11[],4,0),0)-V15-T15 -> 11657.374 | X15: =U15-V15 -> 70565.788 | Y15: =ROUND(X15-W15,9) -> 58908.414
B16: EST | C16: 1 | D16: 1 | E16: Ripley | F16: Iquique | G16: =IFERROR(VLOOKUP(CONCATENATE(E16,F16),Ventas!D:H,5,0),0) -> 379946.15 | H16: =IFERROR(VLOOKUP(A16,Modelos[],18,0),0)*G16/C16 -> 0 | I16: =SUM(G16:H16) -> 379946.15 | J16: =I16*IFERROR(VLOOKUP(E16,Tabla11[],3,0),0) -> 132981.15 | K16: =I16-J16 -> 246965 | L16: =Sup!$A$2*D16 -> 6775.4474 | M16: =IFERROR(VLOOKUP(A16,Modelos[],IF(B16="EST",15,14),0),0)/C16 -> 0 | N16: =IF($G16<0,0,IFERROR((N$2*IFERROR(VLOOKUP(E16,Tabla11[],2,0),0))*($G16/SUM($G$5:$G$43)),0)) -> 4292.667 | O16: =IF($G16<0,0,IFERROR((O$2*IFERROR(VLOOKUP(E16,Tabla11[],2,0),0))*($G16/SUM($G$5:$G$43)),0)) -> 834.68525 | P16: =IF($G16<0,0,IFERROR((P$2*IFERROR(VLOOKUP(E16,Tabla11[],2,0),0))*($G16/SUM($G$5:$G$43)),0)) -> 4292.667 | Q16: =IF($G16<0,0,IFERROR((Q$2*IFERROR(VLOOKUP(E16,Tabla11[],2,0),0))*($G16/SUM($G$5:$G$43)),0)) -> 5962.0375 | R16: =K16*$R$2 -> 98786 | S16: =+R16*IFERROR(VLOOKUP(E16,Tabla11[],4,0),0) -> 14817.9 | T16: =IF(G16>0,$T$2/12,0) -> 25833.333 | U16: =K16-SUM(L16:T16) -> 85370.263 | V16: =IF($G16<0,0,IFERROR((V$2*IFERROR(VLOOKUP(E16,Tabla11[],2,0),0))*($G16/SUM($G$5:$G$43)),0)) -> 10841.111 | W16: =G16-G16*IFERROR(VLOOKUP(E16,Tabla11[],3,0),0)-L16-N16-O16-P16-Q16-G16*$R$2-(G16*$R$2)*IFERROR(VLOOKUP(E16,Tabla11[],4,0),0)-V16-T16 -> 13357.821 | X16: =U16-V16 -> 74529.152 | Y16: =ROUND(X16-W16,9) -> 61171.331
... B111: EST | C111: 1 | D111: 1 | E111: Johnson | F111: San Antonio | G111: =IFERROR(VLOOKUP(CONCATENATE(E111,F111),Ventas!D:H,5,0),0) -> -838.76923 | H111: =IFERROR(VLOOKUP(A111,Modelos[],18,0),0)*G111/C111 -> 0 | I111: =SUM(G111:H111) -> -838.76923 | J111: =I111*IFERROR(VLOOKUP(E111,Tabla11[],3,0),0) -> -293.56923 | K111: =I111-J111 -> -545.2 | L111: =Sup!$A$2*D111 -> 6775.4474 | M111: =IFERROR(VLOOKUP(A111,Modelos[],IF(B111="EST",15,14),0),0)/C111 -> 0 | N111: =IF($G111<0,0,IFERROR((N$2*IFERROR(VLOOKUP(E111,Tabla11[],2,0),0))*($G111/SUM($G$5:$G$43)),0)) -> 0 | O111: =IF($G111<0,0,IFERROR((O$2*IFERROR(VLOOKUP(E111,Tabla11[],2,0),0))*($G111/SUM($G$5:$G$43)),0)) -> 0 | P111: =IF($G111<0,0,IFERROR((P$2*IFERROR(VLOOKUP(E111,Tabla11[],2,0),0))*($G111/SUM($G$5:$G$43)),0)) -> 0 | Q111: =IF($G111<0,0,IFERROR((Q$2*IFERROR(VLOOKUP(E111,Tabla11[],2,0),0))*($G111/SUM($G$5:$G$43)),0)) -> 0 | R111: =K111*$R$2 -> -218.08 | S111: =+R111*IFERROR(VLOOKUP(E111,Tabla11[],4,0),0) -> -32.712 | T111: =IF(G111>0,$T$2/12,0) -> 0 | U111: =K111-SUM(L111:T111) -> -7069.8554 | V111: =IF($G111<0,0,IFERROR((V$2*IFERROR(VLOOKUP(E111,Tabla11[],2,0),0))*($G111/SUM($G$5:$G$43)),0)) -> 0 | W111: =G111-G111*IFERROR(VLOOKUP(E111,Tabla11[],3,0),0)-L111-N111-O111-P111-Q111-G111*$R$2-(G111*$R$2)*IFERROR(VLOOKUP(E111,Tabla11[],4,0),0)-V111-T111 -> -6934.8136 | X111: =U111-V111 -> -7069.8554 | Y111: =ROUND(X111-W111,9) -> -135.04185

Sheet Temporada Alta
N1: Porcentaje Costos Ripley | P1: 0.21
N2: 2206451.6 | O2: 429032.26 | P2: 2206451.6 | Q2: 3064516.1 | R2: 0.4 | S2: 0.15 | T2: 310000 | V2: 3519400
J3: 0.35 | AC3: 1 | AD3: 0.65 | AE3: =35*65% -> 22.75
A4: Modelo PDV | B4: Tipo | C4: Q Tiendas | D4: Sup. | E4: Cadena | F4: Sucursal | G4: Venta Promedio Temporada Alta | H4: Incremento de Venta | I4: Venta Total | J4: Comisión Ripley | K4: Margen Tienda | L4: Supervisión | M4: Vendedor / Reposición | N4: Bodegaje | O4: Packing | P4: Picking | Q4: Transporte | R4: Costo Mercadería | S4: Merma | T4: Muebles | U4: Margen Operacional | V4: Gastos de Administración | W4: Resultado Actual | X4: Resultado Modelo | Y4: Diferencial
A5: Mall - Full - Completo | B5: EST | C5: 1 | D5: 1 | E5: Ripley | F5: Marina Arauco | G5: =VLOOKUP(F5,Ventas!C:H,4,0) -> 779379 | H5: =IFERROR(VLOOKUP(A5,Modelos[],18,0),0)*G5/C5 -> 0 | I5: =SUM(G5:H5) -> 779379 | J5: =I5*$J$3 -> 272782.65 | K5: =I5-J5 -> 506596.35 | L5: =Sup!$A$2*D5 -> 6775.4474 | M5: =IFERROR(VLOOKUP(A5,Modelos[],IF(B5="EST",15,14),0),0)/C5 -> 0 | N5: =IF($G5<0,0,IFERROR((N$2*$P$1)*($G5/SUM($G$5:$G$43)),0)) -> 33755.91 | O5: =IF($G5<0,0,IFERROR((O$2*$P$1)*($G5/SUM($G$5:$G$43)),0)) -> 6563.6492 | P5: =IF($G5<0,0,IFERROR((P$2*$P$1)*($G5/SUM($G$5:$G$43)),0)) -> 33755.91 | Q5: =IF($G5<0,0,IFERROR((Q$2*$P$1)*($G5/SUM($G$5:$G$43)),0)) -> 46883.209 | R5: =K5*$R$2 -> 202638.54 | S5: =+R5*$S$2 -> 30395.781 | T5: =IF(G5>0,$T$2/12,0) -> 25833.333 | U5: =K5-SUM(L5:T5) -> 119994.57 | V5: =IF($G5<0,0,IFERROR((V$2*$P$1)*($G5/SUM($G$5:$G$43)),0)) -> 53842.355 | W5: =G5-G5*$J$3-L5-N5-O5-P5-Q5-(G5-G5*$J$3)*$R$2-((G5-G5*$J$3)*$R$2)*$S$2-T5-V5 -> 66152.216 | X5: =U5-V5 -> 66152.216 | Y5: =ROUND(X5-W5,9) -> 0
A6: Mall - Part - VSD | B6: EST | C6: 1 | D6: 1 | E6: Ripley | F6: M.Costanera P.Montt | G6: =VLOOKUP(F6,Ventas!C:H,4,0) -> 471134 | H6: =IFERROR(VLOOKUP(A6,Modelos[],18,0),0)*G6/C6 -> 0 | I6: =SUM(G6:H6) -> 471134 | J6: =I6*$J$3 -> 164896.9 | K6: =I6-J6 -> 306237.1 | L6: =Sup!$A$2*D6 -> 6775.4474 | M6: =IFERROR(VLOOKUP(A6,Modelos[],IF(B6="EST",15,14),0),0)/C6 -> 0 | N6: =IF($G6<0,0,IFERROR((N$2*$P$1)*($G6/SUM($G$5:$G$43)),0)) -> 20405.421 | O6: =IF($G6<0,0,IFERROR((O$2*$P$1)*($G6/SUM($G$5:$G$43)),0)) -> 3967.7208 | P6: =IF($G6<0,0,IFERROR((P$2*$P$1)*($G6/SUM($G$5:$G$43)),0)) -> 20405.421 | Q6: =IF($G6<0,0,IFERROR((Q$2*$P$1)*($G6/SUM($G$5:$G$43)),0)) -> 28340.863 | R6: =K6*$R$2 -> 122494.84 | S6: =+R6*$S$2 -> 18374.226 | T6: =IF(G6>0,$T$2/12,0) -> 25833.333 | U6: =K6-SUM(L6:T6) -> 59639.826 | V6: =IF($G6<0,0,IFERROR((V$2*$P$1)*($G6/SUM($G$5:$G$43)),0)) -> 32547.662 | W6: =G6-G6*$J$3-L6-N6-O6-P6-Q6-(G6-G6*$J$3)*$R$2-((G6-G6*$J$3)*$R$2)*$S$2-T6-V6 -> 27092.165 | X6: =U6-V6 -> 27092.165 | Y6: =ROUND(X6-W6,9) -> 0
A7: Calle - Part - SD | B7: EST | C7: 1 | D7: 1 | E7: Ripley | F7: Talca | G7: =VLOOKUP(F7,Ventas!C:H,4,0) -> 528406 | H7: =IFERROR(VLOOKUP(A7,Modelos[],18,0),0)*G7/C7 -> 0 | I7: =SUM(G7:H7) -> 528406 | J7: =I7*$J$3 -> 184942.1 | K7: =I7-J7 -> 343463.9 | L7: =Sup!$A$2*D7 -> 6775.4474 | M7: =IFERROR(VLOOKUP(A7,Modelos[],IF(B7="EST",15,14),0),0)/C7 -> 0 | N7: =IF($G7<0,0,IFERROR((N$2*$P$1)*($G7/SUM($G$5:$G$43)),0)) -> 22885.946 | O7: =IF($G7<0,0,IFERROR((O$2*$P$1)*($G7/SUM($G$5:$G$43)),0)) -> 4450.045 | P7: =IF($G7<0,0,IFERROR((P$2*$P$1)*($G7/SUM($G$5:$G$43)),0)) -> 22885.946 | Q7: =IF($G7<0,0,IFERROR((Q$2*$P$1)*($G7/SUM($G$5:$G$43)),0)) -> 31786.036 | R7: =K7*$R$2 -> 137385.56 | S7: =+R7*$S$2 -> 20607.834 | T7: =IF(G7>0,$T$2/12,0) -> 25833.333 | U7: =K7-SUM(L7:T7) -> 70853.753 | V7: =IF($G7<0,0,IFERROR((V$2*$P$1)*($G7/SUM($G$5:$G$43)),0)) -> 36504.221 | W7: =G7-G7*$J$3-L7-N7-O7-P7-Q7-(G7-G7*$J$3)*$R$2-((G7-G7*$J$3)*$R$2)*$S$2-T7-V7 -> 34349.532 | X7: =U7-V7 -> 34349.532 | Y7: =ROUND(X7-W7,9) -> 0
A8: Calle - Part - SD | B8: EST | C8: 1 | D8: 1 | E8: Ripley | F8: Temuco | G8: =VLOOKUP(F8,Ventas!C:H,4,0) -> 453690 | H8: =IFERROR(VLOOKUP(A8,Modelos[],18,0),0)*G8/C8 -> 0 | I8: =SUM(G8:H8) -> 453690 | J8: =I8*$J$3 -> 158791.5 | K8: =I8-J8 -> 294898.5 | L8: =Sup!$A$2*D8 -> 6775.4474 | M8: =IFERROR(VLOOKUP(A8,Modelos[],IF(B8="EST",15,14),0),0)/C8 -> 0 | N8: =IF($G8<0,0,IFERROR((N$2*$P$1)*($G8/SUM($G$5:$G$43)),0)) -> 19649.899 | O8: =IF($G8<0,0,IFERROR((O$2*$P$1)*($G8/SUM($G$5:$G$43)),0)) -> 3820.8138 | P8: =IF($G8<0,0,IFERROR((P$2*$P$1)*($G8/SUM($G$5:$G$43)),0)) -> 19649.899 | Q8: =IF($G8<0,0,IFERROR((Q$2*$P$1)*($G8/SUM($G$5:$G$43)),0)) -> 27291.527 | R8: =K8*$R$2 -> 117959.4 | S8: =+R8*$S$2 -> 17693.91 | T8: =IF(G8>0,$T$2/12,0) -> 25833.333 | U8: =K8-SUM(L8:T8) -> 56224.27 | V8: =IF($G8<0,0,IFERROR((V$2*$P$1)*($G8/SUM($G$5:$G$43)),0)) -> 31342.566 | W8: =G8-G8*$J$3-L8-N8-O8-P8-Q8-(G8-G8*$J$3)*$R$2-((G8-G8*$J$3)*$R$2)*$S$2-T8-V8 -> 24881.704 | X8: =U8-V8 -> 24881.704 | Y8: =ROUND(X8-W8,9) -> 0
A9: Mall - Part - VSD | B9: EST | C9: 1 | D9: 1 | E9: Ripley | F9: La Calera | G9: =VLOOKUP(F9,Ventas!C:H,4,0) -> 740030 | H9: =IFERROR(VLOOKUP(A9,Modelos[],18,0),0)*G9/C9 -> 0 | I9: =SUM(G9:H9) -> 740030 | J9: =I9*$J$3 -> 259010.5 | K9: =I9-J9 -> 481019.5 | L9: =Sup!$A$2*D9 -> 6775.4474 | M9: =IFERROR(VLOOKUP(A9,Modelos[],IF(B9="EST",15,14),0),0)/C9 -> 0 | N9: =IF($G9<0,0,IFERROR((N$2*$P$1)*($G9/SUM($G$5:$G$43)),0)) -> 32051.654 | O9: =IF($G9<0,0,IFERROR((O$2*$P$1)*($G9/SUM($G$5:$G$43)),0)) -> 6232.2661 | P9: =IF($G9<0,0,IFERROR((P$2*$P$1)*($G9/SUM($G$5:$G$43)),0)) -> 32051.654 | Q9: =IF($G9<0,0,IFERROR((Q$2*$P$1)*($G9/SUM($G$5:$G$43)),0)) -> 44516.186 | R9: =K9*$R$2 -> 192407.8 | S9: =+R9*$S$2 -> 28861.17 | T9: =IF(G9>0,$T$2/12,0) -> 25833.333 | U9: =K9-SUM(L9:T9) -> 112289.99 | V9: =IF($G9<0,0,IFERROR((V$2*$P$1)*($G9/SUM($G$5:$G$43)),0)) -> 51123.982 | W9: =G9-G9*$J$3-L9-N9-O9-P9-Q9-(G9-G9*$J$3)*$R$2-((G9-G9*$J$3)*$R$2)*$S$2-T9-V9 -> 61166.007 | X9: =U9-V9 -> 61166.007 | Y9: =ROUND(X9-W9,9) -> 0
A10: Mall - Part - VSD | B10: EST | C10: 1 | D10: 1 | E10: Ripley | F10: Mall Concepcion | G10: =VLOOKUP(F10,Ventas!C:H,4,0) -> 461101 | H10: =IFERROR(VLOOKUP(A10,Modelos[],18,0),0)*G10/C10 -> 0 | I10: =SUM(G10:H10) -> 461101 | J10: =I10*$J$3 -> 161385.35 | K10: =I10-J10 -> 299715.65 | L10: =Sup!$A$2*D10 -> 6775.4474 | M10: =IFERROR(VLOOKUP(A10,Modelos[],IF(B10="EST",15,14),0),0)/C10 -> 0 | N10: =IF($G10<0,0,IFERROR((N$2*$P$1)*($G10/SUM($G$5:$G$43)),0)) -> 19970.879 | O10: =IF($G10<0,0,IFERROR((O$2*$P$1)*($G10/SUM($G$5:$G$43)),0)) -> 3883.2265 | P10: =IF($G10<0,0,IFERROR((P$2*$P$1)*($G10/SUM($G$5:$G$43)),0)) -> 19970.879 | Q10: =IF($G10<0,0,IFERROR((Q$2*$P$1)*($G10/SUM($G$5:$G$43)),0)) -> 27737.332 | R10: =K10*$R$2 -> 119886.26 | S10: =+R10*$S$2 -> 17982.939 | T10: =IF(G10>0,$T$2/12,0) -> 25833.333 | U10: =K10-SUM(L10:T10) -> 57675.353 | V10: =IF($G10<0,0,IFERROR((V$2*$P$1)*($G10/SUM($G$5:$G$43)),0)) -> 31854.545 | W10: =G10-G10*$J$3-L10-N10-O10-P10-Q10-(G10-G10*$J$3)*$R$2-((G10-G10*$J$3)*$R$2)*$S$2-T10-V10 -> 25820.808 | X10: =U10-V10 -> 25820.808 | Y10: =ROUND(X10-W10,9) -> 0
A11: Calle - Part - LMVS | B11: EST | C11: 1 | D11: 1 | E11: Ripley | F11: Los Andes | G11: =VLOOKUP(F11,Ventas!C:H,4,0) -> 529180 | H11: =IFERROR(VLOOKUP(A11,Modelos[],18,0),0)*G11/C11 -> 0 | I11: =SUM(G11:H11) -> 529180 | J11: =I11*$J$3 -> 185213 | K11: =I11-J11 -> 343967 | L11: =Sup!$A$2*D11 -> 6775.4474 | M11: =IFERROR(VLOOKUP(A11,Modelos[],IF(B11="EST",15,14),0),0)/C11 -> 0 | N11: =IF($G11<0,0,IFERROR((N$2*$P$1)*($G11/SUM($G$5:$G$43)),0)) -> 22919.469 | O11: =IF($G11<0,0,IFERROR((O$2*$P$1)*($G11/SUM($G$5:$G$43)),0)) -> 4456.5633 | P11: =IF($G11<0,0,IFERROR((P$2*$P$1)*($G11/SUM($G$5:$G$43)),0)) -> 22919.469 | Q11: =IF($G11<0,0,IFERROR((Q$2*$P$1)*($G11/SUM($G$5:$G$43)),0)) -> 31832.595 | R11: =K11*$R$2 -> 137586.8 | S11: =+R11*$S$2 -> 20638.02 | T11: =IF(G11>0,$T$2/12,0) -> 25833.333 | U11: =K11-SUM(L11:T11) -> 71005.303 | V11: =IF($G11<0,0,IFERROR((V$2*$P$1)*($G11/SUM($G$5:$G$43)),0)) -> 36557.692 | W11: =G11-G11*$J$3-L11-N11-O11-P11-Q11-(G11-G11*$J$3)*$R$2-((G11-G11*$J$3)*$R$2)*$S$2-T11-V11 -> 34447.612 | X11: =U11-V11 -> 34447.612 | Y11: =ROUND(X11-W11,9) -> 0
A12: Mall - Full - Completo | B12: Outsourcing | C12: 1 | D12: 1 | E12: Ripley | F12: Costanera Center | G12: =VLOOKUP(F12,Ventas!C:H,4,0) -> 802607 | H12: =IFERROR(VLOOKUP(A12,Modelos[],18,0),0)*G12/C12 -> 0 | I12: =SUM(G12:H12) -> 802607 | J12: =I12*$J$3 -> 280912.45 | K12: =I12-J12 -> 521694.55 | L12: =Sup!$A$2*D12 -> 6775.4474 | M12: =IFERROR(VLOOKUP(A12,Modelos[],IF(B12="EST",15,14),0),0)/C12 -> 0 | N12: =IF($G12<0,0,IFERROR((N$2*$P$1)*($G12/SUM($G$5:$G$43)),0)) -> 34761.945 | O12: =IF($G12<0,0,IFERROR((O$2*$P$1)*($G12/SUM($G$5:$G$43)),0)) -> 6759.267 | P12: =IF($G12<0,0,IFERROR((P$2*$P$1)*($G12/SUM($G$5:$G$43)),0)) -> 34761.945 | Q12: =IF($G12<0,0,IFERROR((Q$2*$P$1)*($G12/SUM($G$5:$G$43)),0)) -> 48280.479 | R12: =K12*$R$2 -> 208677.82 | S12: =+R12*$S$2 -> 31301.673 | T12: =IF(G12>0,$T$2/12,0) -> 25833.333 | U12: =K12-SUM(L12:T12) -> 124542.64 | V12: =IF($G12<0,0,IFERROR((V$2*$P$1)*($G12/SUM($G$5:$G$43)),0)) -> 55447.03 | W12: =U12-V12 -> 69095.611 | X12: =U12-V12 -> 69095.611 | Y12: =ROUND(X12-W12,9) -> 0
A13: Mall - Ruta - SD | B13: EST | C13: 1 | D13: 1 | E13: Ripley | F13: Florida Center | G13: =VLOOKUP(F13,Ventas!C:H,4,0) -> 584206 | H13: =IFERROR(VLOOKUP(A13,Modelos[],18,0),0)*G13/C13 -> 0 | I13: =SUM(G13:H13) -> 584206 | J13: =I13*$J$3 -> 204472.1 | K13: =I13-J13 -> 379733.9 | L13: =Sup!$A$2*D13 -> 6775.4474 | M13: =IFERROR(VLOOKUP(A13,Modelos[],IF(B13="EST",15,14),0),0)/C13 -> 0 | N13: =IF($G13<0,0,IFERROR((N$2*$P$1)*($G13/SUM($G$5:$G$43)),0)) -> 25302.716 | O13: =IF($G13<0,0,IFERROR((O$2*$P$1)*($G13/SUM($G$5:$G$43)),0)) -> 4919.9725 | P13: =IF($G13<0,0,IFERROR((P$2*$P$1)*($G13/SUM($G$5:$G$43)),0)) -> 25302.716 | Q13: =IF($G13<0,0,IFERROR((Q$2*$P$1)*($G13/SUM($G$5:$G$43)),0)) -> 35142.661 | R13: =K13*$R$2 -> 151893.56 | S13: =+R13*$S$2 -> 22784.034 | T13: =IF(G13>0,$T$2/12,0) -> 25833.333 | U13: =K13-SUM(L13:T13) -> 81779.461 | V13: =IF($G13<0,0,IFERROR((V$2*$P$1)*($G13/SUM($G$5:$G$43)),0)) -> 40359.089 | W13: =G13-G13*$J$3-L13-N13-O13-P13-Q13-(G13-G13*$J$3)*$R$2-((G13-G13*$J$3)*$R$2)*$S$2-T13-V13 -> 41420.371 | X13: =U13-V13 -> 41420.371 | Y13: =ROUND(X13-W13,9) -> 0
A14: Mall - Ruta - SD | B14: EST | C14: 1 | D14: 1 | E14: Ripley | F14: Plaza Egana | G14: =VLOOKUP(F14,Ventas!C:H,4,0) -> 433742 | H14: =IFERROR(VLOOKUP(A14,Modelos[],18,0),0)*G14/C14 -> 0 | I14: =SUM(G14:H14) -> 433742 | J14: =I14*$J$3 -> 151809.7 | K14: =I14-J14 -> 281932.3 | L14: =Sup!$A$2*D14 -> 6775.4474 | M14: =IFERROR(VLOOKUP(A14,Modelos[],IF(B14="EST",15,14),0),0)/C14 -> 0 | N14: =IF($G14<0,0,IFERROR((N$2*$P$1)*($G14/SUM($G$5:$G$43)),0)) -> 18785.926 | O14: =IF($G14<0,0,IFERROR((O$2*$P$1)*($G14/SUM($G$5:$G$43)),0)) -> 3652.8189 | P14: =IF($G14<0,0,IFERROR((P$2*$P$1)*($G14/SUM($G$5:$G$43)),0)) -> 18785.926 | Q14: =IF($G14<0,0,IFERROR((Q$2*$P$1)*($G14/SUM($G$5:$G$43)),0)) -> 26091.563 | R14: =K14*$R$2 -> 112772.92 | S14: =+R14*$S$2 -> 16915.938 | T14: =IF(G14>0,$T$2/12,0) -> 25833.333 | U14: =K14-SUM(L14:T14) -> 52318.427 | V14: =IF($G14<0,0,IFERROR((V$2*$P$1)*($G14/SUM($G$5:$G$43)),0)) -> 29964.485 | W14: =G14-G14*$J$3-L14-N14-O14-P14-Q14-(G14-G14*$J$3)*$R$2-((G14-G14*$J$3)*$R$2)*$S$2-T14-V14 -> 22353.942 | X14: =U14-V14 -> 22353.942 | Y14: =ROUND(X14-W14,9) -> 0
A15: Mall - Ruta - SD | B15: EST | C15: 1 | D15: 1 | E15: Ripley | F15: La Serena | G15: =VLOOKUP(F15,Ventas!C:H,4,0) -> 237829 | H15: =IFERROR(VLOOKUP(A15,Modelos[],18,0),0)*G15/C15 -> 0 | I15: =SUM(G15:H15) -> 237829 | J15: =I15*$J$3 -> 83240.15 | K15: =I15-J15 -> 154588.85 | L15: =Sup!$A$2*D15 -> 6775.4474 | M15: =IFERROR(VLOOKUP(A15,Modelos[],IF(B15="EST",15,14),0),0)/C15 -> 0 | N15: =IF($G15<0,0,IFERROR((N$2*$P$1)*($G15/SUM($G$5:$G$43)),0)) -> 10300.681 | O15: =IF($G15<0,0,IFERROR((O$2*$P$1)*($G15/SUM($G$5:$G$43)),0)) -> 2002.9102 | P15: =IF($G15<0,0,IFERROR((P$2*$P$1)*($G15/SUM($G$5:$G$43)),0)) -> 10300.681 | Q15: =IF($G15<0,0,IFERROR((Q$2*$P$1)*($G15/SUM($G$5:$G$43)),0)) -> 14306.501 | R15: =K15*$R$2 -> 61835.54 | S15: =+R15*$S$2 -> 9275.331 | T15: =IF(G15>0,$T$2/12,0) -> 25833.333 | U15: =K15-SUM(L15:T15) -> 13958.425 | V15: =IF($G15<0,0,IFERROR((V$2*$P$1)*($G15/SUM($G$5:$G$43)),0)) -> 16430.098 | W15: =G15-G15*$J$3-L15-N15-O15-P15-Q15-(G15-G15*$J$3)*$R$2-((G15-G15*$J$3)*$R$2)*$S$2-T15-V15 -> -2471.6729 | X15: =U15-V15 -> -2471.6729 | Y15: =ROUND(X15-W15,9) -> 0
A16: Mall - Ruta - SD | B16: EST | C16: 1 | D16: 1 | E16: Ripley | F16: Iquique | G16: =VLOOKUP(F16,Ventas!C:H,4,0) -> 246965 | H16: =IFERROR(VLOOKUP(A16,Modelos[],18,0),0)*G16/C16 -> 0 | I16: =SUM(G16:H16) -> 246965 | J16: =I16*$J$3 -> 86437.75 | K16: =I16-J16 -> 160527.25 | L16: =Sup!$A$2*D16 -> 6775.4474 | M16: =IFERROR(VLOOKUP(A16,Modelos[],IF(B16="EST",15,14),0),0)/C16 -> 0 | N16: =IF($G16<0,0,IFERROR((N$2*$P$1)*($G16/SUM($G$5:$G$43)),0)) -> 10696.373 | O16: =IF($G16<0,0,IFERROR((O$2*$P$1)*($G16/SUM($G$5:$G$43)),0)) -> 2079.8503 | P16: =IF($G16<0,0,IFERROR((P$2*$P$1)*($G16/SUM($G$5:$G$43)),0)) -> 10696.373 | Q16: =IF($G16<0,0,IFERROR((Q$2*$P$1)*($G16/SUM($G$5:$G$43)),0)) -> 14856.073 | R16: =K16*$R$2 -> 64210.9 | S16: =+R16*$S$2 -> 9631.635 | T16: =IF(G16>0,$T$2/12,0) -> 25833.333 | U16: =K16-SUM(L16:T16) -> 15747.265 | V16: =IF($G16<0,0,IFERROR((V$2*$P$1)*($G16/SUM($G$5:$G$43)),0)) -> 17061.246 | W16: =G16-G16*$J$3-L16-N16-O16-P16-Q16-(G16-G16*$J$3)*$R$2-((G16-G16*$J$3)*$R$2)*$S$2-T16-V16 -> -1313.9814 | X16: =U16-V16 -> -1313.9814 | Y16: =ROUND(X16-W16,9) -> 0
A17: Mall - Ruta - SD | B17: EST | C17: 1 | D17: 1 | E17: Ripley | F17: Plaza Oeste | G17: =VLOOKUP(F17,Ventas!C:H,4,0) -> 228742 | H17: =IFERROR(VLOOKUP(A17,Modelos[],18,0),0)*G17/C17 -> 0 | I17: =SUM(G17:H17) -> 228742 | J17: =I17*$J$3 -> 80059.7 | K17: =I17-J17 -> 148682.3 | L17: =Sup!$A$2*D17 -> 6775.4474 | M17: =IFERROR(VLOOKUP(A17,Modelos[],IF(B17="EST",15,14),0),0)/C17 -> 0 | N17: =IF($G17<0,0,IFERROR((N$2*$P$1)*($G17/SUM($G$5:$G$43)),0)) -> 9907.1112 | O17: =IF($G17<0,0,IFERROR((O$2*$P$1)*($G17/SUM($G$5:$G$43)),0)) -> 1926.3827 | P17: =IF($G17<0,0,IFERROR((P$2*$P$1)*($G17/SUM($G$5:$G$43)),0)) -> 9907.1112 | Q17: =IF($G17<0,0,IFERROR((Q$2*$P$1)*($G17/SUM($G$5:$G$43)),0)) -> 13759.877 | R17: =K17*$R$2 -> 59472.92 | S17: =+R17*$S$2 -> 8920.938 | T17: =IF(G17>0,$T$2/12,0) -> 25833.333 | U17: =K17-SUM(L17:T17) -> 12179.18 | V17: =IF($G17<0,0,IFERROR((V$2*$P$1)*($G17/SUM($G$5:$G$43)),0)) -> 15802.335 | W17: =G17-G17*$J$3-L17-N17-O17-P17-Q17-(G17-G17*$J$3)*$R$2-((G17-G17*$J$3)*$R$2)*$S$2-T17-V17 -> -3623.1553 | X17: =U17-V17 -> -3623.1553 | Y17: =ROUND(X17-W17,9) -> 0
A18: Mall - Ruta - SD | B18: EST | C18: 1 | D18: 1 | E18: Ripley | F18: Plaza Vespucio | G18: =VLOOKUP(F18,Ventas!C:H,4,0) -> 381420 | H18: =IFERROR(VLOOKUP(A18,Modelos[],18,0),0)*G18/C18 -> 0 | I18: =SUM(G18:H18) -> 381420 | J18: =I18*$J$3 -> 133497 | K18: =I18-J18 -> 247923 | L18: =Sup!$A$2*D18 -> 6775.4474 | M18: =IFERROR(VLOOKUP(A18,Modelos[],IF(B18="EST",15,14),0),0)/C18 -> 0 | N18: =IF($G18<0,0,IFERROR((N$2*$P$1)*($G18/SUM($G$5:$G$43)),0)) -> 16519.792 | O18: =IF($G18<0,0,IFERROR((O$2*$P$1)*($G18/SUM($G$5:$G$43)),0)) -> 3212.1818 | P18: =IF($G18<0,0,IFERROR((P$2*$P$1)*($G18/SUM($G$5:$G$43)),0)) -> 16519.792 | Q18: =IF($G18<0,0,IFERROR((Q$2*$P$1)*($G18/SUM($G$5:$G$43)),0)) -> 22944.156 | R18: =K18*$R$2 -> 99169.2 | S18: =+R18*$S$2 -> 14875.38 | T18: =IF(G18>0,$T$2/12,0) -> 25833.333 | U18: =K18-SUM(L18:T18) -> 42073.717 | V18: =IF($G18<0,0,IFERROR((V$2*$P$1)*($G18/SUM($G$5:$G$43)),0)) -> 26349.89 | W18: =G18-G18*$J$3-L18-N18-O18-P18-Q18-(G18-G18*$J$3)*$R$2-((G18-G18*$J$3)*$R$2)*$S$2-T18-V18 -> 15723.827 | X18: =U18-V18 -> 15723.827 | Y18: =ROUND(X18-W18,9) -> 0
A19: Mall - Ruta - SD | B19: EST | C19: 1 | D19: 1 | E19: Ripley | F19: Rancagua | G19: =VLOOKUP(F19,Ventas!C:H,4,0) -> 548105 | H19: =IFERROR(VLOOKUP(A19,Modelos[],18,0),0)*G19/C19 -> 0 | I19: =SUM(G19:H19) -> 548105 | J19: =I19*$J$3 -> 191836.75 | K19: =I19-J19 -> 356268.25 | L19: =Sup!$A$2*D19 -> 6775.4474 | M19: =IFERROR(VLOOKUP(A19,Modelos[],IF(B19="EST",15,14),0),0)/C19 -> 0 | N19: =IF($G19<0,0,IFERROR((N$2*$P$1)*($G19/SUM($G$5:$G$43)),0)) -> 23739.135 | O19: =IF($G19<0,0,IFERROR((O$2*$P$1)*($G19/SUM($G$5:$G$43)),0)) -> 4615.9429 | P19: =IF($G19<0,0,IFERROR((P$2*$P$1)*($G19/SUM($G$5:$G$43)),0)) -> 23739.135 | Q19: =IF($G19<0,0,IFERROR((Q$2*$P$1)*($G19/SUM($G$5:$G$43)),0)) -> 32971.021 | R19: =K19*$R$2 -> 142507.3 | S19: =+R19*$S$2 -> 21376.095 | T19: =IF(G19>0,$T$2/12,0) -> 25833.333 | U19: =K19-SUM(L19:T19) -> 74710.841 | V19: =IF($G19<0,0,IFERROR((V$2*$P$1)*($G19/SUM($G$5:$G$43)),0)) -> 37865.1 | W19: =G19-G19*$J$3-L19-N19-O19-P19-Q19-(G19-G19*$J$3)*$R$2-((G19-G19*$J$3)*$R$2)*$S$2-T19-V19 -> 36845.741 | X19: =U19-V19 -> 36845.741 | Y19: =ROUND(X19-W19,9) -> 0
A20: Calle - Ruta - Completo | B20: EST | C20: 1 | D20: 1 | E20: Ripley | F20: Portal Temuco | G20: =VLOOKUP(F20,Ventas!C:H,4,0) -> 159114 | H20: =IFERROR(VLOOKUP(A20,Modelos[],18,0),0)*G20/C20 -> 0 | I20: =SUM(G20:H20) -> 159114 | J20: =I20*$J$3 -> 55689.9 | K20: =I20-J20 -> 103424.1 | L20: =Sup!$A$2*D20 -> 6775.4474 | M20: =IFERROR(VLOOKUP(A20,Modelos[],IF(B20="EST",15,14),0),0)/C20 -> 0 | N20: =IF($G20<0,0,IFERROR((N$2*$P$1)*($G20/SUM($G$5:$G$43)),0)) -> 6891.4327 | O20: =IF($G20<0,0,IFERROR((O$2*$P$1)*($G20/SUM($G$5:$G$43)),0)) -> 1340.0008 | P20: =IF($G20<0,0,IFERROR((P$2*$P$1)*($G20/SUM($G$5:$G$43)),0)) -> 6891.4327 | Q20: =IF($G20<0,0,IFERROR((Q$2*$P$1)*($G20/SUM($G$5:$G$43)),0)) -> 9571.4342 | R20: =K20*$R$2 -> 41369.64 | S20: =+R20*$S$2 -> 6205.446 | T20: =IF(G20>0,$T$2/12,0) -> 25833.333 | U20: =K20-SUM(L20:T20) -> -1454.0671 | V20: =IF($G20<0,0,IFERROR((V$2*$P$1)*($G20/SUM($G$5:$G$43)),0)) -> 10992.178 | W20: =G20-G20*$J$3-L20-N20-O20-P20-Q20-(G20-G20*$J$3)*$R$2-((G20-G20*$J$3)*$R$2)*$S$2-T20-V20 -> -12446.245 | X20: =U20-V20 -> -12446.245 | Y20: =ROUND(X20-W20,9) -> 0
A21: Mall - Ruta - SD | B21: EST | C21: 1 | D21: 1 | E21: Ripley | F21: Antofagasta | G21: =VLOOKUP(F21,Ventas!C:H,4,0) -> 428577 | H21: =IFERROR(VLOOKUP(A21,Modelos[],18,0),0)*G21/C21 -> 0 | I21: =SUM(G21:H21) -> 428577 | J21: =I21*$J$3 -> 150001.95 | K21: =I21-J21 -> 278575.05 | L21: =Sup!$A$2*D21 -> 6775.4474 | M21: =IFERROR(VLOOKUP(A21,Modelos[],IF(B21="EST",15,14),0),0)/C21 -> 0 | N21: =IF($G21<0,0,IFERROR((N$2*$P$1)*($G21/SUM($G$5:$G$43)),0)) -> 18562.223 | O21: =IF($G21<0,0,IFERROR((O$2*$P$1)*($G21/SUM($G$5:$G$43)),0)) -> 3609.3211 | P21: =IF($G21<0,0,IFERROR((P$2*$P$1)*($G21/SUM($G$5:$G$43)),0)) -> 18562.223 | Q21: =IF($G21<0,0,IFERROR((Q$2*$P$1)*($G21/SUM($G$5:$G$43)),0)) -> 25780.865 | R21: =K21*$R$2 -> 111430.02 | S21: =+R21*$S$2 -> 16714.503 | T21: =IF(G21>0,$T$2/12,0) -> 25833.333 | U21: =K21-SUM(L21:T21) -> 51307.114 | V21: =IF($G21<0,0,IFERROR((V$2*$P$1)*($G21/SUM($G$5:$G$43)),0)) -> 29607.668 | W21: =G21-G21*$J$3-L21-N21-O21-P21-Q21-(G21-G21*$J$3)*$R$2-((G21-G21*$J$3)*$R$2)*$S$2-T21-V21 -> 21699.446 | X21: =U21-V21 -> 21699.446 | Y21: =ROUND(X21-W21,9) -> 0
A22: Mall - Ruta - SD | B22: EST | C22: 1 | D22: 1 | E22: Ripley | F22: El Trebol | G22: =VLOOKUP(F22,Ventas!C:H,4,0) -> 294384 | H22: =IFERROR(VLOOKUP(A22,Modelos[],18,0),0)*G22/C22 -> 0 | I22: =SUM(G22:H22) -> 294384 | J22: =I22*$J$3 -> 103034.4 | K22: =I22-J22 -> 191349.6 | L22: =Sup!$A$2*D22 -> 6775.4474 | M22: =IFERROR(VLOOKUP(A22,Modelos[],IF(B22="EST",15,14),0),0)/C22 -> 0 | N22: =IF($G22<0,0,IFERROR((N$2*$P$1)*($G22/SUM($G$5:$G$43)),0)) -> 12750.151 | O22: =IF($G22<0,0,IFERROR((O$2*$P$1)*($G22/SUM($G$5:$G$43)),0)) -> 2479.196 | P22: =IF($G22<0,0,IFERROR((P$2*$P$1)*($G22/SUM($G$5:$G$43)),0)) -> 12750.151 | Q22: =IF($G22<0,0,IFERROR((Q$2*$P$1)*($G22/SUM($G$5:$G$43)),0)) -> 17708.543 | R22: =K22*$R$2 -> 76539.84 | S22: =+R22*$S$2 -> 11480.976 | T22: =IF(G22>0,$T$2/12,0) -> 25833.333 | U22: =K22-SUM(L22:T22) -> 25031.963 | V22: =IF($G22<0,0,IFERROR((V$2*$P$1)*($G22/SUM($G$5:$G$43)),0)) -> 20337.124 | W22: =G22-G22*$J$3-L22-N22-O22-P22-Q22-(G22-G22*$J$3)*$R$2-((G22-G22*$J$3)*$R$2)*$S$2-T22-V22 -> 4694.8381 | X22: =U22-V22 -> 4694.8381 | Y22: =ROUND(X22-W22,9) -> 0
C23: 1 | D23: 1 | E23: Ripley | F23: San Bernardo | G23: =VLOOKUP(F23,Ventas!C:H,4,0) -> 220639 | H23: =IFERROR(VLOOKUP(A23,Modelos[],18,0),0)*G23/C23 -> 0 | I23: =SUM(G23:H23) -> 220639 | J23: =I23*$J$3 -> 77223.65 | K23: =I23-J23 -> 143415.35 | L23: =Sup!$A$2*D23 -> 6775.4474 | M23: =IFERROR(VLOOKUP(A23,Modelos[],IF(B23="EST",15,14),0),0)/C23 -> 0 | N23: =IF($G23<0,0,IFERROR((N$2*$P$1)*($G23/SUM($G$5:$G$43)),0)) -> 9556.1598 | O23: =IF($G23<0,0,IFERROR((O$2*$P$1)*($G23/SUM($G$5:$G$43)),0)) -> 1858.1422 | P23: =IF($G23<0,0,IFERROR((P$2*$P$1)*($G23/SUM($G$5:$G$43)),0)) -> 9556.1598 | Q23: =IF($G23<0,0,IFERROR((Q$2*$P$1)*($G23/SUM($G$5:$G$43)),0)) -> 13272.444 | R23: =K23*$R$2 -> 57366.14 | S23: =+R23*$S$2 -> 8604.921 | T23: =IF(G23>0,$T$2/12,0) -> 25833.333 | U23: =K23-SUM(L23:T23) -> 10592.602 | V23: =IF($G23<0,0,IFERROR((V$2*$P$1)*($G23/SUM($G$5:$G$43)),0)) -> 15242.55 | W23: =G23-G23*$J$3-L23-N23-O23-P23-Q23-(G23-G23*$J$3)*$R$2-((G23-G23*$J$3)*$R$2)*$S$2-T23-V23 -> -4649.9476 | X23: =U23-V23 -> -4649.9476 | Y23: =ROUND(X23-W23,9) -> 0
C24: 1 | D24: 1 | E24: Ripley | F24: Puente | G24: =VLOOKUP(F24,Ventas!C:H,4,0) -> 189052 | H24: =IFERROR(VLOOKUP(A24,Modelos[],18,0),0)*G24/C24 -> 0 | I24: =SUM(G24:H24) -> 189052 | J24: =I24*$J$3 -> 66168.2 | K24: =I24-J24 -> 122883.8 | L24: =Sup!$A$2*D24 -> 6775.4474 | M24: =IFERROR(VLOOKUP(A24,Modelos[],IF(B24="EST",15,14),0),0)/C24 -> 0 | N24: =IF($G24<0,0,IFERROR((N$2*$P$1)*($G24/SUM($G$5:$G$43)),0)) -> 8188.0861 | O24: =IF($G24<0,0,IFERROR((O$2*$P$1)*($G24/SUM($G$5:$G$43)),0)) -> 1592.1278 | P24: =IF($G24<0,0,IFERROR((P$2*$P$1)*($G24/SUM($G$5:$G$43)),0)) -> 8188.0861 | Q24: =IF($G24<0,0,IFERROR((Q$2*$P$1)*($G24/SUM($G$5:$G$43)),0)) -> 11372.342 | R24: =K24*$R$2 -> 49153.52 | S24: =+R24*$S$2 -> 7373.028 | T24: =IF(G24>0,$T$2/12,0) -> 25833.333 | U24: =K24-SUM(L24:T24) -> 4407.8295 | V24: =IF($G24<0,0,IFERROR((V$2*$P$1)*($G24/SUM($G$5:$G$43)),0)) -> 13060.404 | W24: =G24-G24*$J$3-L24-N24-O24-P24-Q24-(G24-G24*$J$3)*$R$2-((G24-G24*$J$3)*$R$2)*$S$2-T24-V24 -> -8652.5748 | X24: =U24-V24 -> -8652.5748 | Y24: =ROUND(X24-W24,9) -> 0
C25: 1 | D25: 1 | E25: Ripley | F25: Curico | G25: =VLOOKUP(F25,Ventas!C:H,4,0) -> 339700 | H25: =IFERROR(VLOOKUP(A25,Modelos[],18,0),0)*G25/C25 -> 0 | I25: =SUM(G25:H25) -> 339700 | J25: =I25*$J$3 -> 118895 | K25: =I25-J25 -> 220805 | L25: =Sup!$A$2*D25 -> 6775.4474 | M25: =IFERROR(VLOOKUP(A25,Modelos[],IF(B25="EST",15,14),0),0)/C25 -> 0 | N25: =IF($G25<0,0,IFERROR((N$2*$P$1)*($G25/SUM($G$5:$G$43)),0)) -> 14712.845 | O25: =IF($G25<0,0,IFERROR((O$2*$P$1)*($G25/SUM($G$5:$G$43)),0)) -> 2860.831 | P25: =IF($G25<0,0,IFERROR((P$2*$P$1)*($G25/SUM($G$5:$G$43)),0)) -> 14712.845 | Q25: =IF($G25<0,0,IFERROR((Q$2*$P$1)*($G25/SUM($G$5:$G$43)),0)) -> 20434.507 | R25: =K25*$R$2 -> 88322 | S25: =+R25*$S$2 -> 13248.3 | T25: =IF(G25>0,$T$2/12,0) -> 25833.333 | U25: =K25-SUM(L25:T25) -> 33904.89 | V25: =IF($G25<0,0,IFERROR((V$2*$P$1)*($G25/SUM($G$5:$G$43)),0)) -> 23467.72 | W25: =G25-G25*$J$3-L25-N25-O25-P25-Q25-(G25-G25*$J$3)*$R$2-((G25-G25*$J$3)*$R$2)*$S$2-T25-V25 -> 10437.17 | X25: =U25-V25 -> 10437.17 | Y25: =ROUND(X25-W25,9) -> 0
C26: 1 | D26: 1 | E26: Ripley | F26: Nueva Valdivia Store | G26: =VLOOKUP(F26,Ventas!C:H,4,0) -> 161471 | H26: =IFERROR(VLOOKUP(A26,Modelos[],18,0),0)*G26/C26 -> 0 | I26: =SUM(G26:H26) -> 161471 | J26: =I26*$J$3 -> 56514.85 | K26: =I26-J26 -> 104956.15 | L26: =Sup!$A$2*D26 -> 6775.4474 | M26: =IFERROR(VLOOKUP(A26,Modelos[],IF(B26="EST",15,14),0),0)/C26 -> 0 | N26: =IF($G26<0,0,IFERROR((N$2*$P$1)*($G26/SUM($G$5:$G$43)),0)) -> 6993.5174 | O26: =IF($G26<0,0,IFERROR((O$2*$P$1)*($G26/SUM($G$5:$G$43)),0)) -> 1359.8506 | P26: =IF($G26<0,0,IFERROR((P$2*$P$1)*($G26/SUM($G$5:$G$43)),0)) -> 6993.5174 | Q26: =IF($G26<0,0,IFERROR((Q$2*$P$1)*($G26/SUM($G$5:$G$43)),0)) -> 9713.2186 | R26: =K26*$R$2 -> 41982.46 | S26: =+R26*$S$2 -> 6297.369 | T26: =IF(G26>0,$T$2/12,0) -> 25833.333 | U26: =K26-SUM(L26:T26) -> -992.56365 | V26: =IF($G26<0,0,IFERROR((V$2*$P$1)*($G26/SUM($G$5:$G$43)),0)) -> 11155.008 | W26: =G26-G26*$J$3-L26-N26-O26-P26-Q26-(G26-G26*$J$3)*$R$2-((G26-G26*$J$3)*$R$2)*$S$2-T26-V26 -> -12147.571 | X26: =U26-V26 -> -12147.571 | Y26: =ROUND(X26-W26,9) -> 0
C27: 1 | D27: 1 | E27: Ripley | F27: Los Angeles | G27: =VLOOKUP(F27,Ventas!C:H,4,0) -> 222874 | H27: =IFERROR(VLOOKUP(A27,Modelos[],18,0),0)*G27/C27 -> 0 | I27: =SUM(G27:H27) -> 222874 | J27: =I27*$J$3 -> 78005.9 | K27: =I27-J27 -> 144868.1 | L27: =Sup!$A$2*D27 -> 6775.4474 | M27: =IFERROR(VLOOKUP(A27,Modelos[],IF(B27="EST",15,14),0),0)/C27 -> 0 | N27: =IF($G27<0,0,IFERROR((N$2*$P$1)*($G27/SUM($G$5:$G$43)),0)) -> 9652.9605 | O27: =IF($G27<0,0,IFERROR((O$2*$P$1)*($G27/SUM($G$5:$G$43)),0)) -> 1876.9645 | P27: =IF($G27<0,0,IFERROR((P$2*$P$1)*($G27/SUM($G$5:$G$43)),0)) -> 9652.9605 | Q27: =IF($G27<0,0,IFERROR((Q$2*$P$1)*($G27/SUM($G$5:$G$43)),0)) -> 13406.89 | R27: =K27*$R$2 -> 57947.24 | S27: =+R27*$S$2 -> 8692.086 | T27: =IF(G27>0,$T$2/12,0) -> 25833.333 | U27: =K27-SUM(L27:T27) -> 11030.218 | V27: =IF($G27<0,0,IFERROR((V$2*$P$1)*($G27/SUM($G$5:$G$43)),0)) -> 15396.952 | W27: =G27-G27*$J$3-L27-N27-O27-P27-Q27-(G27-G27*$J$3)*$R$2-((G27-G27*$J$3)*$R$2)*$S$2-T27-V27 -> -4366.7338 | X27: =U27-V27 -> -4366.7338 | Y27: =ROUND(X27-W27,9) -> 0
C28: 1 | D28: 1 | E28: Ripley | F28: Maipu | G28: =VLOOKUP(F28,Ventas!C:H,4,0) -> 172710 | H28: =IFERROR(VLOOKUP(A28,Modelos[],18,0),0)*G28/C28 -> 0 | I28: =SUM(G28:H28) -> 172710 | J28: =I28*$J$3 -> 60448.5 | K28: =I28-J28 -> 112261.5 | L28: =Sup!$A$2*D28 -> 6775.4474 | M28: =IFERROR(VLOOKUP(A28,Modelos[],IF(B28="EST",15,14),0),0)/C28 -> 0 | N28: =IF($G28<0,0,IFERROR((N$2*$P$1)*($G28/SUM($G$5:$G$43)),0)) -> 7480.293 | O28: =IF($G28<0,0,IFERROR((O$2*$P$1)*($G28/SUM($G$5:$G$43)),0)) -> 1454.5014 | P28: =IF($G28<0,0,IFERROR((P$2*$P$1)*($G28/SUM($G$5:$G$43)),0)) -> 7480.293 | Q28: =IF($G28<0,0,IFERROR((Q$2*$P$1)*($G28/SUM($G$5:$G$43)),0)) -> 10389.296 | R28: =K28*$R$2 -> 44904.6 | S28: =+R28*$S$2 -> 6735.69 | T28: =IF(G28>0,$T$2/12,0) -> 25833.333 | U28: =K28-SUM(L28:T28) -> 1208.0461 | V28: =IF($G28<0,0,IFERROR((V$2*$P$1)*($G28/SUM($G$5:$G$43)),0)) -> 11931.439 | W28: =G28-G28*$J$3-L28-N28-O28-P28-Q28-(G28-G28*$J$3)*$R$2-((G28-G28*$J$3)*$R$2)*$S$2-T28-V28 -> -10723.393 | X28: =U28-V28 -> -10723.393 | Y28: =ROUND(X28-W28,9) -> 0
C29: 1 | D29: 1 | E29: Ripley | F29: Nueva Alameda | G29: =VLOOKUP(F29,Ventas!C:H,4,0) -> 60200 | H29: =IFERROR(VLOOKUP(A29,Modelos[],18,0),0)*G29/C29 -> 0 | I29: =SUM(G29:H29) -> 60200 | J29: =I29*$J$3 -> 21070 | K29: =I29-J29 -> 39130 | L29: =Sup!$A$2*D29 -> 6775.4474 | M29: =IFERROR(VLOOKUP(A29,Modelos[],IF(B29="EST",15,14),0),0)/C29 -> 0 | N29: =IF($G29<0,0,IFERROR((N$2*$P$1)*($G29/SUM($G$5:$G$43)),0)) -> 2607.3397 | O29: =IF($G29<0,0,IFERROR((O$2*$P$1)*($G29/SUM($G$5:$G$43)),0)) -> 506.98272 | P29: =IF($G29<0,0,IFERROR((P$2*$P$1)*($G29/SUM($G$5:$G$43)),0)) -> 2607.3397 | Q29: =IF($G29<0,0,IFERROR((Q$2*$P$1)*($G29/SUM($G$5:$G$43)),0)) -> 3621.3051 | R29: =K29*$R$2 -> 15652 | S29: =+R29*$S$2 -> 2347.8 | T29: =IF(G29>0,$T$2/12,0) -> 25833.333 | U29: =K29-SUM(L29:T29) -> -20821.548 | V29: =IF($G29<0,0,IFERROR((V$2*$P$1)*($G29/SUM($G$5:$G$43)),0)) -> 4158.8364 | W29: =G29-G29*$J$3-L29-N29-O29-P29-Q29-(G29-G29*$J$3)*$R$2-((G29-G29*$J$3)*$R$2)*$S$2-T29-V29 -> -24980.384 | X29: =U29-V29 -> -24980.384 | Y29: =ROUND(X29-W29,9) -> 0
C30: 1 | D30: 1 | E30: Ripley | F30: Valparaiso | G30: =VLOOKUP(F30,Ventas!C:H,4,0) -> 315029 | H30: =IFERROR(VLOOKUP(A30,Modelos[],18,0),0)*G30/C30 -> 0 | I30: =SUM(G30:H30) -> 315029 | J30: =I30*$J$3 -> 110260.15 | K30: =I30-J30 -> 204768.85 | L30: =Sup!$A$2*D30 -> 6775.4474 | M30: =IFERROR(VLOOKUP(A30,Modelos[],IF(B30="EST",15,14),0),0)/C30 -> 0 | N30: =IF($G30<0,0,IFERROR((N$2*$P$1)*($G30/SUM($G$5:$G$43)),0)) -> 13644.312 | O30: =IF($G30<0,0,IFERROR((O$2*$P$1)*($G30/SUM($G$5:$G$43)),0)) -> 2653.0608 | P30: =IF($G30<0,0,IFERROR((P$2*$P$1)*($G30/SUM($G$5:$G$43)),0)) -> 13644.312 | Q30: =IF($G30<0,0,IFERROR((Q$2*$P$1)*($G30/SUM($G$5:$G$43)),0)) -> 18950.434 | R30: =K30*$R$2 -> 81907.54 | S30: =+R30*$S$2 -> 12286.131 | T30: =IF(G30>0,$T$2/12,0) -> 25833.333 | U30: =K30-SUM(L30:T30) -> 29074.278 | V30: =IF($G30<0,0,IFERROR((V$2*$P$1)*($G30/SUM($G$5:$G$43)),0)) -> 21763.357 | W30: =G30-G30*$J$3-L30-N30-O30-P30-Q30-(G30-G30*$J$3)*$R$2-((G30-G30*$J$3)*$R$2)*$S$2-T30-V30 -> 7310.9219 | X30: =U30-V30 -> 7310.9219 | Y30: =ROUND(X30-W30,9) -> 0
C31: 1 | D31: 1 | E31: Ripley | F31: Parque Arauco | G31: =VLOOKUP(F31,Ventas!C:H,4,0) -> 251895 | H31: =IFERROR(VLOOKUP(A31,Modelos[],18,0),0)*G31/C31 -> 0 | I31: =SUM(G31:H31) -> 251895 | J31: =I31*$J$3 -> 88163.25 | K31: =I31-J31 -> 163731.75 | L31: =Sup!$A$2*D31 -> 6775.4474 | M31: =IFERROR(VLOOKUP(A31,Modelos[],IF(B31="EST",15,14),0),0)/C31 -> 0 | N31: =IF($G31<0,0,IFERROR((N$2*$P$1)*($G31/SUM($G$5:$G$43)),0)) -> 10909.897 | O31: =IF($G31<0,0,IFERROR((O$2*$P$1)*($G31/SUM($G$5:$G$43)),0)) -> 2121.369 | P31: =IF($G31<0,0,IFERROR((P$2*$P$1)*($G31/SUM($G$5:$G$43)),0)) -> 10909.897 | Q31: =IF($G31<0,0,IFERROR((Q$2*$P$1)*($G31/SUM($G$5:$G$43)),0)) -> 15152.635 | R31: =K31*$R$2 -> 65492.7 | S31: =+R31*$S$2 -> 9823.905 | T31: =IF(G31>0,$T$2/12,0) -> 25833.333 | U31: =K31-SUM(L31:T31) -> 16712.565 | V31: =IF($G31<0,0,IFERROR((V$2*$P$1)*($G31/SUM($G$5:$G$43)),0)) -> 17401.829 | W31: =G31-G31*$J$3-L31-N31-O31-P31-Q31-(G31-G31*$J$3)*$R$2-((G31-G31*$J$3)*$R$2)*$S$2-T31-V31 -> -689.26386 | X31: =U31-V31 -> -689.26386 | Y31: =ROUND(X31-W31,9) -> 0
C32: 1 | D32: 1 | E32: Ripley | F32: Huechuraba | G32: =VLOOKUP(F32,Ventas!C:H,4,0) -> 20622 | H32: =IFERROR(VLOOKUP(A32,Modelos[],18,0),0)*G32/C32 -> 0 | I32: =SUM(G32:H32) -> 20622 | J32: =I32*$J$3 -> 7217.7 | K32: =I32-J32 -> 13404.3 | L32: =Sup!$A$2*D32 -> 6775.4474 | M32: =IFERROR(VLOOKUP(A32,Modelos[],IF(B32="EST",15,14),0),0)/C32 -> 0 | N32: =IF($G32<0,0,IFERROR((N$2*$P$1)*($G32/SUM($G$5:$G$43)),0)) -> 893.16543 | O32: =IF($G32<0,0,IFERROR((O$2*$P$1)*($G32/SUM($G$5:$G$43)),0)) -> 173.67106 | P32: =IF($G32<0,0,IFERROR((P$2*$P$1)*($G32/SUM($G$5:$G$43)),0)) -> 893.16543 | Q32: =IF($G32<0,0,IFERROR((Q$2*$P$1)*($G32/SUM($G$5:$G$43)),0)) -> 1240.5075 | R32: =K32*$R$2 -> 5361.72 | S32: =+R32*$S$2 -> 804.258 | T32: =IF(G32>0,$T$2/12,0) -> 25833.333 | U32: =K32-SUM(L32:T32) -> -28570.968 | V32: =IF($G32<0,0,IFERROR((V$2*$P$1)*($G32/SUM($G$5:$G$43)),0)) -> 1424.6433 | W32: =G32-G32*$J$3-L32-N32-O32-P32-Q32-(G32-G32*$J$3)*$R$2-((G32-G32*$J$3)*$R$2)*$S$2-T32-V32 -> -29995.611 | X32: =U32-V32 -> -29995.611 | Y32: =ROUND(X32-W32,9) -> 0
C33: 1 | D33: 1 | E33: Ripley | F33: Copiapo | G33: =VLOOKUP(F33,Ventas!C:H,4,0) -> 227648 | H33: =IFERROR(VLOOKUP(A33,Modelos[],18,0),0)*G33/C33 -> 0 | I33: =SUM(G33:H33) -> 227648 | J33: =I33*$J$3 -> 79676.8 | K33: =I33-J33 -> 147971.2 | L33: =Sup!$A$2*D33 -> 6775.4474 | M33: =IFERROR(VLOOKUP(A33,Modelos[],IF(B33="EST",15,14),0),0)/C33 -> 0 | N33: =IF($G33<0,0,IFERROR((N$2*$P$1)*($G33/SUM($G$5:$G$43)),0)) -> 9859.7286 | O33: =IF($G33<0,0,IFERROR((O$2*$P$1)*($G33/SUM($G$5:$G$43)),0)) -> 1917.1695 | P33: =IF($G33<0,0,IFERROR((P$2*$P$1)*($G33/SUM($G$5:$G$43)),0)) -> 9859.7286 | Q33: =IF($G33<0,0,IFERROR((Q$2*$P$1)*($G33/SUM($G$5:$G$43)),0)) -> 13694.068 | R33: =K33*$R$2 -> 59188.48 | S33: =+R33*$S$2 -> 8878.272 | T33: =IF(G33>0,$T$2/12,0) -> 25833.333 | U33: =K33-SUM(L33:T33) -> 11964.973 | V33: =IF($G33<0,0,IFERROR((V$2*$P$1)*($G33/SUM($G$5:$G$43)),0)) -> 15726.757 | W33: =G33-G33*$J$3-L33-N33-O33-P33-Q33-(G33-G33*$J$3)*$R$2-((G33-G33*$J$3)*$R$2)*$S$2-T33-V33 -> -3761.7843 | X33: =U33-V33 -> -3761.7843 | Y33: =ROUND(X33-W33,9) -> 0
C34: 1 | D34: 1 | E34: Ripley | F34: Concepcion 2 | G34: =VLOOKUP(F34,Ventas!C:H,4,0) -> 104986 | H34: =IFERROR(VLOOKUP(A34,Modelos[],18,0),0)*G34/C34 -> 0 | I34: =SUM(G34:H34) -> 104986 | J34: =I34*$J$3 -> 36745.1 | K34: =I34-J34 -> 68240.9 | L34: =Sup!$A$2*D34 -> 6775.4474 | M34: =IFERROR(VLOOKUP(A34,Modelos[],IF(B34="EST",15,14),0),0)/C34 -> 0 | N34: =IF($G34<0,0,IFERROR((N$2*$P$1)*($G34/SUM($G$5:$G$43)),0)) -> 4547.0791 | O34: =IF($G34<0,0,IFERROR((O$2*$P$1)*($G34/SUM($G$5:$G$43)),0)) -> 884.15427 | P34: =IF($G34<0,0,IFERROR((P$2*$P$1)*($G34/SUM($G$5:$G$43)),0)) -> 4547.0791 | Q34: =IF($G34<0,0,IFERROR((Q$2*$P$1)*($G34/SUM($G$5:$G$43)),0)) -> 6315.3877 | R34: =K34*$R$2 -> 27296.36 | S34: =+R34*$S$2 -> 4094.454 | T34: =IF(G34>0,$T$2/12,0) -> 25833.333 | U34: =K34-SUM(L34:T34) -> -12052.395 | V34: =IF($G34<0,0,IFERROR((V$2*$P$1)*($G34/SUM($G$5:$G$43)),0)) -> 7252.8172 | W34: =G34-G34*$J$3-L34-N34-O34-P34-Q34-(G34-G34*$J$3)*$R$2-((G34-G34*$J$3)*$R$2)*$S$2-T34-V34 -> -19305.212 | X34: =U34-V34 -> -19305.212 | Y34: =ROUND(X34-W34,9) -> 0
... C38: 1 | D38: 1 | E38: Ripley | F38: Crillon | G38: =VLOOKUP(F38,Ventas!C:H,4,0) -> 0 | H38: =IFERROR(VLOOKUP(A38,Modelos[],18,0),0)*G38/C38 -> 0 | I38: =SUM(G38:H38) -> 0 | J38: =I38*$J$3 -> 0 | K38: =I38-J38 -> 0 | L38: =Sup!$A$2*D38 -> 6775.4474 | M38: =IFERROR(VLOOKUP(A38,Modelos[],IF(B38="EST",15,14),0),0)/C38 -> 0 | N38: =IF($G38<0,0,IFERROR((N$2*$P$1)*($G38/SUM($G$5:$G$43)),0)) -> 0 | O38: =IF($G38<0,0,IFERROR((O$2*$P$1)*($G38/SUM($G$5:$G$43)),0)) -> 0 | P38: =IF($G38<0,0,IFERROR((P$2*$P$1)*($G38/SUM($G$5:$G$43)),0)) -> 0 | Q38: =IF($G38<0,0,IFERROR((Q$2*$P$1)*($G38/SUM($G$5:$G$43)),0)) -> 0 | R38: =K38*$R$2 -> 0 | S38: =+R38*$S$2 -> 0 | T38: =IF(G38>0,$T$2/12,0) -> 0 | U38: =K38-SUM(L38:T38) -> -6775.4474 | V38: =IF($G38<0,0,IFERROR((V$2*$P$1)*($G38/SUM($G$5:$G$43)),0)) -> 0 | W38: =G38-G38*$J$3-L38-N38-O38-P38-Q38-(G38-G38*$J$3)*$R$2-((G38-G38*$J$3)*$R$2)*$S$2-T38-V38 -> -6775.4474 | X38: =U38-V38 -> -6775.4474 | Y38: =ROUND(X38-W38,9) -> 0
C39: 1 | E39: Ripley | F39: Viña | G39: 0 | H39: =IFERROR(VLOOKUP(A39,Modelos[],18,0),0)*G39/C39 -> 0 | I39: =SUM(G39:H39) -> 0 | J39: =I39*$J$3 -> 0 | K39: =I39-J39 -> 0 | L39: =Sup!$A$2*D39 -> 0 | M39: =IFERROR(VLOOKUP(A39,Modelos[],IF(B39="EST",15,14),0),0)/C39 -> 0 | N39: =IF($G39<0,0,IFERROR((N$2*$P$1)*($G39/SUM($G$5:$G$43)),0)) -> 0 | O39: =IF($G39<0,0,IFERROR((O$2*$P$1)*($G39/SUM($G$5:$G$43)),0)) -> 0 | P39: =IF($G39<0,0,IFERROR((P$2*$P$1)*($G39/SUM($G$5:$G$43)),0)) -> 0 | Q39: =IF($G39<0,0,IFERROR((Q$2*$P$1)*($G39/SUM($G$5:$G$43)),0)) -> 0 | R39: =K39*$R$2 -> 0 | S39: =+R39*$S$2 -> 0 | T39: =IF(G39>0,$T$2/12,0) -> 0 | U39: =K39-SUM(L39:T39) -> 0 | V39: =IF($G39<0,0,IFERROR((V$2*$P$1)*($G39/SUM($G$5:$G$43)),0)) -> 0 | W39: =G39-G39*$J$3-L39-N39-O39-P39-Q39-(G39-G39*$J$3)*$R$2-((G39-G39*$J$3)*$R$2)*$S$2-T39-V39 -> 0 | X39: =U39-V39 -> 0 | Y39: =ROUND(X39-W39,9) -> 0
